Workbook

Sheet Dashboard
A1: Injection Mold Job Dashboard
A2: Combined view across New Tooling Jobs and Reorders. Click a tab below to edit underlying data.
A3: =CONCATENATE("Last opened: ", TEXT(TODAY(),"dddd, mmmm d, yyyy"))
A5: Active Jobs | C5: New Tooling | E5: Reorders | G5: Overdue
A6: =COUNTIFS('New Tooling Jobs'!A13:A62,"<>",'New Tooling Jobs'!E13:E62,"<>Completed",'New Tooling Jobs'!E13:E62,"<>")+COUNTIFS(Reorders!A13:A62,"<>",Reorders!E13:E62,"<>Completed",Reorders!E13:E62,"<>") | C6: =COUNTIFS('New Tooling Jobs'!A13:A62,"<>",'New Tooling Jobs'!E13:E62,"<>Completed",'New Tooling Jobs'!E13:E62,"<>") | E6: =COUNTIFS(Reorders!A13:A62,"<>",Reorders!E13:E62,"<>Completed",Reorders!E13:E62,"<>") | G6: =SUMPRODUCT(('New Tooling Jobs'!X13:X62<>"")*(IFERROR('New Tooling Jobs'!X13:X62+0,99999)<0)*('New Tooling Jobs'!E13:E62<>"Completed"))+SUMPRODUCT((Reorders!T13:T62<>"")*(IFERROR(Reorders!T13:T62+0,99999)<0)*(Reorders!E13:E62<>"Completed"))
A9: Job # | B9: Job Type | C9: Customer | D9: Stage | E9: Customer PO # | F9: Molder PO # | G9: Next Action / Waiting On
A10: =IFERROR(IF(1<=COUNTIFS('New Tooling Jobs'!A$13:A$62,"<>",'New Tooling Jobs'!E$13:E$62,"<>Completed"),INDEX('New Tooling Jobs'!A$13:A$62,MATCH(1,'New Tooling Jobs'!AG$13:AG$62,0)),INDEX(Reorders!A$13:A$62,MATCH(1-COUNTIFS('New Tooling Jobs'!A$13:A$62,"<>",'New Tooling Jobs'!E$13:E$62,"<>Completed"),Reorders!AC$13:AC$62,0))),"") | B10: =IFERROR(IF(1<=COUNTIFS('New Tooling Jobs'!A$13:A$62,"<>",'New Tooling Jobs'!E$13:E$62,"<>Completed"),IF(INDEX('New Tooling Jobs'!A$13:A$62,MATCH(1,'New Tooling Jobs'!AG$13:AG$62,0))<>"","New Tooling",""),IF(INDEX(Reorders!A$13:A$62,MATCH(1-COUNTIFS('New Tooling Jobs'!A$13:A$62,"<>",'New Tooling Jobs'!E$13:E$62,"<>Completed"),Reorders!AC$13:AC$62,0))<>"","Reorder","")),"") | C10: =IFERROR(IF(1<=COUNTIFS('New Tooling Jobs'!A$13:A$62,"<>",'New Tooling Jobs'!E$13:E$62,"<>Completed"),INDEX('New Tooling Jobs'!B$13:B$62,MATCH(1,'New Tooling Jobs'!AG$13:AG$62,0)),INDEX(Reorders!B$13:B$62,MATCH(1-COUNTIFS('New Tooling Jobs'!A$13:A$62,"<>",'New Tooling Jobs'!E$13:E$62,"<>Completed"),Reorders!AC$13:AC$62,0))),"") | D10: =IFERROR(IF(1<=COUNTIFS('New Tooling Jobs'!A$13:A$62,"<>",'New Tooling Jobs'!E$13:E$62,"<>Completed"),INDEX('New Tooling Jobs'!E$13:E$62,MATCH(1,'New Tooling Jobs'!AG$13:AG$62,0)),INDEX(Reorders!E$13:E$62,MATCH(1-COUNTIFS('New Tooling Jobs'!A$13:A$62,"<>",'New Tooling Jobs'!E$13:E$62,"<>Completed"),Reorders!AC$13:AC$62,0))),"") | E10: =IFERROR(IF(1<=COUNTIFS('New Tooling Jobs'!A$13:A$62,"<>",'New Tooling Jobs'!E$13:E$62,"<>Completed"),INDEX('New Tooling Jobs'!G$13:G$62,MATCH(1,'New Tooling Jobs'!AG$13:AG$62,0)),INDEX(Reorders!G$13:G$62,MATCH(1-COUNTIFS('New Tooling Jobs'!A$13:A$62,"<>",'New Tooling Jobs'!E$13:E$62,"<>Completed"),Reorders!AC$13:AC$62,0))),"") | F10: =IFERROR(IF(1<=COUNTIFS('New Tooling Jobs'!A$13:A$62,"<>",'New Tooling Jobs'!E$13:E$62,"<>Completed"),INDEX('New Tooling Jobs'!H$13:H$62,MATCH(1,'New Tooling Jobs'!AG$13:AG$62,0)),INDEX(Reorders!H$13:H$62,MATCH(1-COUNTIFS('New Tooling Jobs'!A$13:A$62,"<>",'New Tooling Jobs'!E$13:E$62,"<>Completed"),Reorders!AC$13:AC$62,0))),"") | G10: =IFERROR(IF(1<=COUNTIFS('New Tooling Jobs'!A$13:A$62,"<>",'New Tooling Jobs'!E$13:E$62,"<>Completed"),INDEX('New Tooling Jobs'!I$13:I$62,MATCH(1,'New Tooling Jobs'!AG$13:AG$62,0)),INDEX(Reorders!I$13:I$62,MATCH(1-COUNTIFS('New Tooling Jobs'!A$13:A$62,"<>",'New Tooling Jobs'!E$13:E$62,"<>Completed"),Reorders!AC$13:AC$62,0))),"")
A11: =IFERROR(IF(2<=COUNTIFS('New Tooling Jobs'!A$13:A$62,"<>",'New Tooling Jobs'!E$13:E$62,"<>Completed"),INDEX('New Tooling Jobs'!A$13:A$62,MATCH(2,'New Tooling Jobs'!AG$13:AG$62,0)),INDEX(Reorders!A$13:A$62,MATCH(2-COUNTIFS('New Tooling Jobs'!A$13:A$62,"<>",'New Tooling Jobs'!E$13:E$62,"<>Completed"),Reorders!AC$13:AC$62,0))),"") | B11: =IFERROR(IF(2<=COUNTIFS('New Tooling Jobs'!A$13:A$62,"<>",'New Tooling Jobs'!E$13:E$62,"<>Completed"),IF(INDEX('New Tooling Jobs'!A$13:A$62,MATCH(2,'New Tooling Jobs'!AG$13:AG$62,0))<>"","New Tooling",""),IF(INDEX(Reorders!A$13:A$62,MATCH(2-COUNTIFS('New Tooling Jobs'!A$13:A$62,"<>",'New Tooling Jobs'!E$13:E$62,"<>Completed"),Reorders!AC$13:AC$62,0))<>"","Reorder","")),"") | C11: =IFERROR(IF(2<=COUNTIFS('New Tooling Jobs'!A$13:A$62,"<>",'New Tooling Jobs'!E$13:E$62,"<>Completed"),INDEX('New Tooling Jobs'!B$13:B$62,MATCH(2,'New Tooling Jobs'!AG$13:AG$62,0)),INDEX(Reorders!B$13:B$62,MATCH(2-COUNTIFS('New Tooling Jobs'!A$13:A$62,"<>",'New Tooling Jobs'!E$13:E$62,"<>Completed"),Reorders!AC$13:AC$62,0))),"") | D11: =IFERROR(IF(2<=COUNTIFS('New Tooling Jobs'!A$13:A$62,"<>",'New Tooling Jobs'!E$13:E$62,"<>Completed"),INDEX('New Tooling Jobs'!E$13:E$62,MATCH(2,'New Tooling Jobs'!AG$13:AG$62,0)),INDEX(Reorders!E$13:E$62,MATCH(2-COUNTIFS('New Tooling Jobs'!A$13:A$62,"<>",'New Tooling Jobs'!E$13:E$62,"<>Completed"),Reorders!AC$13:AC$62,0))),"") | E11: =IFERROR(IF(2<=COUNTIFS('New Tooling Jobs'!A$13:A$62,"<>",'New Tooling Jobs'!E$13:E$62,"<>Completed"),INDEX('New Tooling Jobs'!G$13:G$62,MATCH(2,'New Tooling Jobs'!AG$13:AG$62,0)),INDEX(Reorders!G$13:G$62,MATCH(2-COUNTIFS('New Tooling Jobs'!A$13:A$62,"<>",'New Tooling Jobs'!E$13:E$62,"<>Completed"),Reorders!AC$13:AC$62,0))),"") | F11: =IFERROR(IF(2<=COUNTIFS('New Tooling Jobs'!A$13:A$62,"<>",'New Tooling Jobs'!E$13:E$62,"<>Completed"),INDEX('New Tooling Jobs'!H$13:H$62,MATCH(2,'New Tooling Jobs'!AG$13:AG$62,0)),INDEX(Reorders!H$13:H$62,MATCH(2-COUNTIFS('New Tooling Jobs'!A$13:A$62,"<>",'New Tooling Jobs'!E$13:E$62,"<>Completed"),Reorders!AC$13:AC$62,0))),"") | G11: =IFERROR(IF(2<=COUNTIFS('New Tooling Jobs'!A$13:A$62,"<>",'New Tooling Jobs'!E$13:E$62,"<>Completed"),INDEX('New Tooling Jobs'!I$13:I$62,MATCH(2,'New Tooling Jobs'!AG$13:AG$62,0)),INDEX(Reorders!I$13:I$62,MATCH(2-COUNTIFS('New Tooling Jobs'!A$13:A$62,"<>",'New Tooling Jobs'!E$13:E$62,"<>Completed"),Reorders!AC$13:AC$62,0))),"")
A12: =IFERROR(IF(3<=COUNTIFS('New Tooling Jobs'!A$13:A$62,"<>",'New Tooling Jobs'!E$13:E$62,"<>Completed"),INDEX('New Tooling Jobs'!A$13:A$62,MATCH(3,'New Tooling Jobs'!AG$13:AG$62,0)),INDEX(Reorders!A$13:A$62,MATCH(3-COUNTIFS('New Tooling Jobs'!A$13:A$62,"<>",'New Tooling Jobs'!E$13:E$62,"<>Completed"),Reorders!AC$13:AC$62,0))),"") | B12: =IFERROR(IF(3<=COUNTIFS('New Tooling Jobs'!A$13:A$62,"<>",'New Tooling Jobs'!E$13:E$62,"<>Completed"),IF(INDEX('New Tooling Jobs'!A$13:A$62,MATCH(3,'New Tooling Jobs'!AG$13:AG$62,0))<>"","New Tooling",""),IF(INDEX(Reorders!A$13:A$62,MATCH(3-COUNTIFS('New Tooling Jobs'!A$13:A$62,"<>",'New Tooling Jobs'!E$13:E$62,"<>Completed"),Reorders!AC$13:AC$62,0))<>"","Reorder","")),"") | C12: =IFERROR(IF(3<=COUNTIFS('New Tooling Jobs'!A$13:A$62,"<>",'New Tooling Jobs'!E$13:E$62,"<>Completed"),INDEX('New Tooling Jobs'!B$13:B$62,MATCH(3,'New Tooling Jobs'!AG$13:AG$62,0)),INDEX(Reorders!B$13:B$62,MATCH(3-COUNTIFS('New Tooling Jobs'!A$13:A$62,"<>",'New Tooling Jobs'!E$13:E$62,"<>Completed"),Reorders!AC$13:AC$62,0))),"") | D12: =IFERROR(IF(3<=COUNTIFS('New Tooling Jobs'!A$13:A$62,"<>",'New Tooling Jobs'!E$13:E$62,"<>Completed"),INDEX('New Tooling Jobs'!E$13:E$62,MATCH(3,'New Tooling Jobs'!AG$13:AG$62,0)),INDEX(Reorders!E$13:E$62,MATCH(3-COUNTIFS('New Tooling Jobs'!A$13:A$62,"<>",'New Tooling Jobs'!E$13:E$62,"<>Completed"),Reorders!AC$13:AC$62,0))),"") | E12: =IFERROR(IF(3<=COUNTIFS('New Tooling Jobs'!A$13:A$62,"<>",'New Tooling Jobs'!E$13:E$62,"<>Completed"),INDEX('New Tooling Jobs'!G$13:G$62,MATCH(3,'New Tooling Jobs'!AG$13:AG$62,0)),INDEX(Reorders!G$13:G$62,MATCH(3-COUNTIFS('New Tooling Jobs'!A$13:A$62,"<>",'New Tooling Jobs'!E$13:E$62,"<>Completed"),Reorders!AC$13:AC$62,0))),"") | F12: =IFERROR(IF(3<=COUNTIFS('New Tooling Jobs'!A$13:A$62,"<>",'New Tooling Jobs'!E$13:E$62,"<>Completed"),INDEX('New Tooling Jobs'!H$13:H$62,MATCH(3,'New Tooling Jobs'!AG$13:AG$62,0)),INDEX(Reorders!H$13:H$62,MATCH(3-COUNTIFS('New Tooling Jobs'!A$13:A$62,"<>",'New Tooling Jobs'!E$13:E$62,"<>Completed"),Reorders!AC$13:AC$62,0))),"") | G12: =IFERROR(IF(3<=COUNTIFS('New Tooling Jobs'!A$13:A$62,"<>",'New Tooling Jobs'!E$13:E$62,"<>Completed"),INDEX('New Tooling Jobs'!I$13:I$62,MATCH(3,'New Tooling Jobs'!AG$13:AG$62,0)),INDEX(Reorders!I$13:I$62,MATCH(3-COUNTIFS('New Tooling Jobs'!A$13:A$62,"<>",'New Tooling Jobs'!E$13:E$62,"<>Completed"),Reorders!AC$13:AC$62,0))),"")
A13: =IFERROR(IF(4<=COUNTIFS('New Tooling Jobs'!A$13:A$62,"<>",'New Tooling Jobs'!E$13:E$62,"<>Completed"),INDEX('New Tooling Jobs'!A$13:A$62,MATCH(4,'New Tooling Jobs'!AG$13:AG$62,0)),INDEX(Reorders!A$13:A$62,MATCH(4-COUNTIFS('New Tooling Jobs'!A$13:A$62,"<>",'New Tooling Jobs'!E$13:E$62,"<>Completed"),Reorders!AC$13:AC$62,0))),"") | B13: =IFERROR(IF(4<=COUNTIFS('New Tooling Jobs'!A$13:A$62,"<>",'New Tooling Jobs'!E$13:E$62,"<>Completed"),IF(INDEX('New Tooling Jobs'!A$13:A$62,MATCH(4,'New Tooling Jobs'!AG$13:AG$62,0))<>"","New Tooling",""),IF(INDEX(Reorders!A$13:A$62,MATCH(4-COUNTIFS('New Tooling Jobs'!A$13:A$62,"<>",'New Tooling Jobs'!E$13:E$62,"<>Completed"),Reorders!AC$13:AC$62,0))<>"","Reorder","")),"") | C13: =IFERROR(IF(4<=COUNTIFS('New Tooling Jobs'!A$13:A$62,"<>",'New Tooling Jobs'!E$13:E$62,"<>Completed"),INDEX('New Tooling Jobs'!B$13:B$62,MATCH(4,'New Tooling Jobs'!AG$13:AG$62,0)),INDEX(Reorders!B$13:B$62,MATCH(4-COUNTIFS('New Tooling Jobs'!A$13:A$62,"<>",'New Tooling Jobs'!E$13:E$62,"<>Completed"),Reorders!AC$13:AC$62,0))),"") | D13: =IFERROR(IF(4<=COUNTIFS('New Tooling Jobs'!A$13:A$62,"<>",'New Tooling Jobs'!E$13:E$62,"<>Completed"),INDEX('New Tooling Jobs'!E$13:E$62,MATCH(4,'New Tooling Jobs'!AG$13:AG$62,0)),INDEX(Reorders!E$13:E$62,MATCH(4-COUNTIFS('New Tooling Jobs'!A$13:A$62,"<>",'New Tooling Jobs'!E$13:E$62,"<>Completed"),Reorders!AC$13:AC$62,0))),"") | E13: =IFERROR(IF(4<=COUNTIFS('New Tooling Jobs'!A$13:A$62,"<>",'New Tooling Jobs'!E$13:E$62,"<>Completed"),INDEX('New Tooling Jobs'!G$13:G$62,MATCH(4,'New Tooling Jobs'!AG$13:AG$62,0)),INDEX(Reorders!G$13:G$62,MATCH(4-COUNTIFS('New Tooling Jobs'!A$13:A$62,"<>",'New Tooling Jobs'!E$13:E$62,"<>Completed"),Reorders!AC$13:AC$62,0))),"") | F13: =IFERROR(IF(4<=COUNTIFS('New Tooling Jobs'!A$13:A$62,"<>",'New Tooling Jobs'!E$13:E$62,"<>Completed"),INDEX('New Tooling Jobs'!H$13:H$62,MATCH(4,'New Tooling Jobs'!AG$13:AG$62,0)),INDEX(Reorders!H$13:H$62,MATCH(4-COUNTIFS('New Tooling Jobs'!A$13:A$62,"<>",'New Tooling Jobs'!E$13:E$62,"<>Completed"),Reorders!AC$13:AC$62,0))),"") | G13: =IFERROR(IF(4<=COUNTIFS('New Tooling Jobs'!A$13:A$62,"<>",'New Tooling Jobs'!E$13:E$62,"<>Completed"),INDEX('New Tooling Jobs'!I$13:I$62,MATCH(4,'New Tooling Jobs'!AG$13:AG$62,0)),INDEX(Reorders!I$13:I$62,MATCH(4-COUNTIFS('New Tooling Jobs'!A$13:A$62,"<>",'New Tooling Jobs'!E$13:E$62,"<>Completed"),Reorders!AC$13:AC$62,0))),"")
A14: =IFERROR(IF(5<=COUNTIFS('New Tooling Jobs'!A$13:A$62,"<>",'New Tooling Jobs'!E$13:E$62,"<>Completed"),INDEX('New Tooling Jobs'!A$13:A$62,MATCH(5,'New Tooling Jobs'!AG$13:AG$62,0)),INDEX(Reorders!A$13:A$62,MATCH(5-COUNTIFS('New Tooling Jobs'!A$13:A$62,"<>",'New Tooling Jobs'!E$13:E$62,"<>Completed"),Reorders!AC$13:AC$62,0))),"") | B14: =IFERROR(IF(5<=COUNTIFS('New Tooling Jobs'!A$13:A$62,"<>",'New Tooling Jobs'!E$13:E$62,"<>Completed"),IF(INDEX('New Tooling Jobs'!A$13:A$62,MATCH(5,'New Tooling Jobs'!AG$13:AG$62,0))<>"","New Tooling",""),IF(INDEX(Reorders!A$13:A$62,MATCH(5-COUNTIFS('New Tooling Jobs'!A$13:A$62,"<>",'New Tooling Jobs'!E$13:E$62,"<>Completed"),Reorders!AC$13:AC$62,0))<>"","Reorder","")),"") | C14: =IFERROR(IF(5<=COUNTIFS('New Tooling Jobs'!A$13:A$62,"<>",'New Tooling Jobs'!E$13:E$62,"<>Completed"),INDEX('New Tooling Jobs'!B$13:B$62,MATCH(5,'New Tooling Jobs'!AG$13:AG$62,0)),INDEX(Reorders!B$13:B$62,MATCH(5-COUNTIFS('New Tooling Jobs'!A$13:A$62,"<>",'New Tooling Jobs'!E$13:E$62,"<>Completed"),Reorders!AC$13:AC$62,0))),"") | D14: =IFERROR(IF(5<=COUNTIFS('New Tooling Jobs'!A$13:A$62,"<>",'New Tooling Jobs'!E$13:E$62,"<>Completed"),INDEX('New Tooling Jobs'!E$13:E$62,MATCH(5,'New Tooling Jobs'!AG$13:AG$62,0)),INDEX(Reorders!E$13:E$62,MATCH(5-COUNTIFS('New Tooling Jobs'!A$13:A$62,"<>",'New Tooling Jobs'!E$13:E$62,"<>Completed"),Reorders!AC$13:AC$62,0))),"") | E14: =IFERROR(IF(5<=COUNTIFS('New Tooling Jobs'!A$13:A$62,"<>",'New Tooling Jobs'!E$13:E$62,"<>Completed"),INDEX('New Tooling Jobs'!G$13:G$62,MATCH(5,'New Tooling Jobs'!AG$13:AG$62,0)),INDEX(Reorders!G$13:G$62,MATCH(5-COUNTIFS('New Tooling Jobs'!A$13:A$62,"<>",'New Tooling Jobs'!E$13:E$62,"<>Completed"),Reorders!AC$13:AC$62,0))),"") | F14: =IFERROR(IF(5<=COUNTIFS('New Tooling Jobs'!A$13:A$62,"<>",'New Tooling Jobs'!E$13:E$62,"<>Completed"),INDEX('New Tooling Jobs'!H$13:H$62,MATCH(5,'New Tooling Jobs'!AG$13:AG$62,0)),INDEX(Reorders!H$13:H$62,MATCH(5-COUNTIFS('New Tooling Jobs'!A$13:A$62,"<>",'New Tooling Jobs'!E$13:E$62,"<>Completed"),Reorders!AC$13:AC$62,0))),"") | G14: =IFERROR(IF(5<=COUNTIFS('New Tooling Jobs'!A$13:A$62,"<>",'New Tooling Jobs'!E$13:E$62,"<>Completed"),INDEX('New Tooling Jobs'!I$13:I$62,MATCH(5,'New Tooling Jobs'!AG$13:AG$62,0)),INDEX(Reorders!I$13:I$62,MATCH(5-COUNTIFS('New Tooling Jobs'!A$13:A$62,"<>",'New Tooling Jobs'!E$13:E$62,"<>Completed"),Reorders!AC$13:AC$62,0))),"")
A15: =IFERROR(IF(6<=COUNTIFS('New Tooling Jobs'!A$13:A$62,"<>",'New Tooling Jobs'!E$13:E$62,"<>Completed"),INDEX('New Tooling Jobs'!A$13:A$62,MATCH(6,'New Tooling Jobs'!AG$13:AG$62,0)),INDEX(Reorders!A$13:A$62,MATCH(6-COUNTIFS('New Tooling Jobs'!A$13:A$62,"<>",'New Tooling Jobs'!E$13:E$62,"<>Completed"),Reorders!AC$13:AC$62,0))),"") | B15: =IFERROR(IF(6<=COUNTIFS('New Tooling Jobs'!A$13:A$62,"<>",'New Tooling Jobs'!E$13:E$62,"<>Completed"),IF(INDEX('New Tooling Jobs'!A$13:A$62,MATCH(6,'New Tooling Jobs'!AG$13:AG$62,0))<>"","New Tooling",""),IF(INDEX(Reorders!A$13:A$62,MATCH(6-COUNTIFS('New Tooling Jobs'!A$13:A$62,"<>",'New Tooling Jobs'!E$13:E$62,"<>Completed"),Reorders!AC$13:AC$62,0))<>"","Reorder","")),"") | C15: =IFERROR(IF(6<=COUNTIFS('New Tooling Jobs'!A$13:A$62,"<>",'New Tooling Jobs'!E$13:E$62,"<>Completed"),INDEX('New Tooling Jobs'!B$13:B$62,MATCH(6,'New Tooling Jobs'!AG$13:AG$62,0)),INDEX(Reorders!B$13:B$62,MATCH(6-COUNTIFS('New Tooling Jobs'!A$13:A$62,"<>",'New Tooling Jobs'!E$13:E$62,"<>Completed"),Reorders!AC$13:AC$62,0))),"") | D15: =IFERROR(IF(6<=COUNTIFS('New Tooling Jobs'!A$13:A$62,"<>",'New Tooling Jobs'!E$13:E$62,"<>Completed"),INDEX('New Tooling Jobs'!E$13:E$62,MATCH(6,'New Tooling Jobs'!AG$13:AG$62,0)),INDEX(Reorders!E$13:E$62,MATCH(6-COUNTIFS('New Tooling Jobs'!A$13:A$62,"<>",'New Tooling Jobs'!E$13:E$62,"<>Completed"),Reorders!AC$13:AC$62,0))),"") | E15: =IFERROR(IF(6<=COUNTIFS('New Tooling Jobs'!A$13:A$62,"<>",'New Tooling Jobs'!E$13:E$62,"<>Completed"),INDEX('New Tooling Jobs'!G$13:G$62,MATCH(6,'New Tooling Jobs'!AG$13:AG$62,0)),INDEX(Reorders!G$13:G$62,MATCH(6-COUNTIFS('New Tooling Jobs'!A$13:A$62,"<>",'New Tooling Jobs'!E$13:E$62,"<>Completed"),Reorders!AC$13:AC$62,0))),"") | F15: =IFERROR(IF(6<=COUNTIFS('New Tooling Jobs'!A$13:A$62,"<>",'New Tooling Jobs'!E$13:E$62,"<>Completed"),INDEX('New Tooling Jobs'!H$13:H$62,MATCH(6,'New Tooling Jobs'!AG$13:AG$62,0)),INDEX(Reorders!H$13:H$62,MATCH(6-COUNTIFS('New Tooling Jobs'!A$13:A$62,"<>",'New Tooling Jobs'!E$13:E$62,"<>Completed"),Reorders!AC$13:AC$62,0))),"") | G15: =IFERROR(IF(6<=COUNTIFS('New Tooling Jobs'!A$13:A$62,"<>",'New Tooling Jobs'!E$13:E$62,"<>Completed"),INDEX('New Tooling Jobs'!I$13:I$62,MATCH(6,'New Tooling Jobs'!AG$13:AG$62,0)),INDEX(Reorders!I$13:I$62,MATCH(6-COUNTIFS('New Tooling Jobs'!A$13:A$62,"<>",'New Tooling Jobs'!E$13:E$62,"<>Completed"),Reorders!AC$13:AC$62,0))),"")
A16: =IFERROR(IF(7<=COUNTIFS('New Tooling Jobs'!A$13:A$62,"<>",'New Tooling Jobs'!E$13:E$62,"<>Completed"),INDEX('New Tooling Jobs'!A$13:A$62,MATCH(7,'New Tooling Jobs'!AG$13:AG$62,0)),INDEX(Reorders!A$13:A$62,MATCH(7-COUNTIFS('New Tooling Jobs'!A$13:A$62,"<>",'New Tooling Jobs'!E$13:E$62,"<>Completed"),Reorders!AC$13:AC$62,0))),"") | B16: =IFERROR(IF(7<=COUNTIFS('New Tooling Jobs'!A$13:A$62,"<>",'New Tooling Jobs'!E$13:E$62,"<>Completed"),IF(INDEX('New Tooling Jobs'!A$13:A$62,MATCH(7,'New Tooling Jobs'!AG$13:AG$62,0))<>"","New Tooling",""),IF(INDEX(Reorders!A$13:A$62,MATCH(7-COUNTIFS('New Tooling Jobs'!A$13:A$62,"<>",'New Tooling Jobs'!E$13:E$62,"<>Completed"),Reorders!AC$13:AC$62,0))<>"","Reorder","")),"") | C16: =IFERROR(IF(7<=COUNTIFS('New Tooling Jobs'!A$13:A$62,"<>",'New Tooling Jobs'!E$13:E$62,"<>Completed"),INDEX('New Tooling Jobs'!B$13:B$62,MATCH(7,'New Tooling Jobs'!AG$13:AG$62,0)),INDEX(Reorders!B$13:B$62,MATCH(7-COUNTIFS('New Tooling Jobs'!A$13:A$62,"<>",'New Tooling Jobs'!E$13:E$62,"<>Completed"),Reorders!AC$13:AC$62,0))),"") | D16: =IFERROR(IF(7<=COUNTIFS('New Tooling Jobs'!A$13:A$62,"<>",'New Tooling Jobs'!E$13:E$62,"<>Completed"),INDEX('New Tooling Jobs'!E$13:E$62,MATCH(7,'New Tooling Jobs'!AG$13:AG$62,0)),INDEX(Reorders!E$13:E$62,MATCH(7-COUNTIFS('New Tooling Jobs'!A$13:A$62,"<>",'New Tooling Jobs'!E$13:E$62,"<>Completed"),Reorders!AC$13:AC$62,0))),"") | E16: =IFERROR(IF(7<=COUNTIFS('New Tooling Jobs'!A$13:A$62,"<>",'New Tooling Jobs'!E$13:E$62,"<>Completed"),INDEX('New Tooling Jobs'!G$13:G$62,MATCH(7,'New Tooling Jobs'!AG$13:AG$62,0)),INDEX(Reorders!G$13:G$62,MATCH(7-COUNTIFS('New Tooling Jobs'!A$13:A$62,"<>",'New Tooling Jobs'!E$13:E$62,"<>Completed"),Reorders!AC$13:AC$62,0))),"") | F16: =IFERROR(IF(7<=COUNTIFS('New Tooling Jobs'!A$13:A$62,"<>",'New Tooling Jobs'!E$13:E$62,"<>Completed"),INDEX('New Tooling Jobs'!H$13:H$62,MATCH(7,'New Tooling Jobs'!AG$13:AG$62,0)),INDEX(Reorders!H$13:H$62,MATCH(7-COUNTIFS('New Tooling Jobs'!A$13:A$62,"<>",'New Tooling Jobs'!E$13:E$62,"<>Completed"),Reorders!AC$13:AC$62,0))),"") | G16: =IFERROR(IF(7<=COUNTIFS('New Tooling Jobs'!A$13:A$62,"<>",'New Tooling Jobs'!E$13:E$62,"<>Completed"),INDEX('New Tooling Jobs'!I$13:I$62,MATCH(7,'New Tooling Jobs'!AG$13:AG$62,0)),INDEX(Reorders!I$13:I$62,MATCH(7-COUNTIFS('New Tooling Jobs'!A$13:A$62,"<>",'New Tooling Jobs'!E$13:E$62,"<>Completed"),Reorders!AC$13:AC$62,0))),"")
A17: =IFERROR(IF(8<=COUNTIFS('New Tooling Jobs'!A$13:A$62,"<>",'New Tooling Jobs'!E$13:E$62,"<>Completed"),INDEX('New Tooling Jobs'!A$13:A$62,MATCH(8,'New Tooling Jobs'!AG$13:AG$62,0)),INDEX(Reorders!A$13:A$62,MATCH(8-COUNTIFS('New Tooling Jobs'!A$13:A$62,"<>",'New Tooling Jobs'!E$13:E$62,"<>Completed"),Reorders!AC$13:AC$62,0))),"") | B17: =IFERROR(IF(8<=COUNTIFS('New Tooling Jobs'!A$13:A$62,"<>",'New Tooling Jobs'!E$13:E$62,"<>Completed"),IF(INDEX('New Tooling Jobs'!A$13:A$62,MATCH(8,'New Tooling Jobs'!AG$13:AG$62,0))<>"","New Tooling",""),IF(INDEX(Reorders!A$13:A$62,MATCH(8-COUNTIFS('New Tooling Jobs'!A$13:A$62,"<>",'New Tooling Jobs'!E$13:E$62,"<>Completed"),Reorders!AC$13:AC$62,0))<>"","Reorder","")),"") | C17: =IFERROR(IF(8<=COUNTIFS('New Tooling Jobs'!A$13:A$62,"<>",'New Tooling Jobs'!E$13:E$62,"<>Completed"),INDEX('New Tooling Jobs'!B$13:B$62,MATCH(8,'New Tooling Jobs'!AG$13:AG$62,0)),INDEX(Reorders!B$13:B$62,MATCH(8-COUNTIFS('New Tooling Jobs'!A$13:A$62,"<>",'New Tooling Jobs'!E$13:E$62,"<>Completed"),Reorders!AC$13:AC$62,0))),"") | D17: =IFERROR(IF(8<=COUNTIFS('New Tooling Jobs'!A$13:A$62,"<>",'New Tooling Jobs'!E$13:E$62,"<>Completed"),INDEX('New Tooling Jobs'!E$13:E$62,MATCH(8,'New Tooling Jobs'!AG$13:AG$62,0)),INDEX(Reorders!E$13:E$62,MATCH(8-COUNTIFS('New Tooling Jobs'!A$13:A$62,"<>",'New Tooling Jobs'!E$13:E$62,"<>Completed"),Reorders!AC$13:AC$62,0))),"") | E17: =IFERROR(IF(8<=COUNTIFS('New Tooling Jobs'!A$13:A$62,"<>",'New Tooling Jobs'!E$13:E$62,"<>Completed"),INDEX('New Tooling Jobs'!G$13:G$62,MATCH(8,'New Tooling Jobs'!AG$13:AG$62,0)),INDEX(Reorders!G$13:G$62,MATCH(8-COUNTIFS('New Tooling Jobs'!A$13:A$62,"<>",'New Tooling Jobs'!E$13:E$62,"<>Completed"),Reorders!AC$13:AC$62,0))),"") | F17: =IFERROR(IF(8<=COUNTIFS('New Tooling Jobs'!A$13:A$62,"<>",'New Tooling Jobs'!E$13:E$62,"<>Completed"),INDEX('New Tooling Jobs'!H$13:H$62,MATCH(8,'New Tooling Jobs'!AG$13:AG$62,0)),INDEX(Reorders!H$13:H$62,MATCH(8-COUNTIFS('New Tooling Jobs'!A$13:A$62,"<>",'New Tooling Jobs'!E$13:E$62,"<>Completed"),Reorders!AC$13:AC$62,0))),"") | G17: =IFERROR(IF(8<=COUNTIFS('New Tooling Jobs'!A$13:A$62,"<>",'New Tooling Jobs'!E$13:E$62,"<>Completed"),INDEX('New Tooling Jobs'!I$13:I$62,MATCH(8,'New Tooling Jobs'!AG$13:AG$62,0)),INDEX(Reorders!I$13:I$62,MATCH(8-COUNTIFS('New Tooling Jobs'!A$13:A$62,"<>",'New Tooling Jobs'!E$13:E$62,"<>Completed"),Reorders!AC$13:AC$62,0))),"")
A18: =IFERROR(IF(9<=COUNTIFS('New Tooling Jobs'!A$13:A$62,"<>",'New Tooling Jobs'!E$13:E$62,"<>Completed"),INDEX('New Tooling Jobs'!A$13:A$62,MATCH(9,'New Tooling Jobs'!AG$13:AG$62,0)),INDEX(Reorders!A$13:A$62,MATCH(9-COUNTIFS('New Tooling Jobs'!A$13:A$62,"<>",'New Tooling Jobs'!E$13:E$62,"<>Completed"),Reorders!AC$13:AC$62,0))),"") | B18: =IFERROR(IF(9<=COUNTIFS('New Tooling Jobs'!A$13:A$62,"<>",'New Tooling Jobs'!E$13:E$62,"<>Completed"),IF(INDEX('New Tooling Jobs'!A$13:A$62,MATCH(9,'New Tooling Jobs'!AG$13:AG$62,0))<>"","New Tooling",""),IF(INDEX(Reorders!A$13:A$62,MATCH(9-COUNTIFS('New Tooling Jobs'!A$13:A$62,"<>",'New Tooling Jobs'!E$13:E$62,"<>Completed"),Reorders!AC$13:AC$62,0))<>"","Reorder","")),"") | C18: =IFERROR(IF(9<=COUNTIFS('New Tooling Jobs'!A$13:A$62,"<>",'New Tooling Jobs'!E$13:E$62,"<>Completed"),INDEX('New Tooling Jobs'!B$13:B$62,MATCH(9,'New Tooling Jobs'!AG$13:AG$62,0)),INDEX(Reorders!B$13:B$62,MATCH(9-COUNTIFS('New Tooling Jobs'!A$13:A$62,"<>",'New Tooling Jobs'!E$13:E$62,"<>Completed"),Reorders!AC$13:AC$62,0))),"") | D18: =IFERROR(IF(9<=COUNTIFS('New Tooling Jobs'!A$13:A$62,"<>",'New Tooling Jobs'!E$13:E$62,"<>Completed"),INDEX('New Tooling Jobs'!E$13:E$62,MATCH(9,'New Tooling Jobs'!AG$13:AG$62,0)),INDEX(Reorders!E$13:E$62,MATCH(9-COUNTIFS('New Tooling Jobs'!A$13:A$62,"<>",'New Tooling Jobs'!E$13:E$62,"<>Completed"),Reorders!AC$13:AC$62,0))),"") | E18: =IFERROR(IF(9<=COUNTIFS('New Tooling Jobs'!A$13:A$62,"<>",'New Tooling Jobs'!E$13:E$62,"<>Completed"),INDEX('New Tooling Jobs'!G$13:G$62,MATCH(9,'New Tooling Jobs'!AG$13:AG$62,0)),INDEX(Reorders!G$13:G$62,MATCH(9-COUNTIFS('New Tooling Jobs'!A$13:A$62,"<>",'New Tooling Jobs'!E$13:E$62,"<>Completed"),Reorders!AC$13:AC$62,0))),"") | F18: =IFERROR(IF(9<=COUNTIFS('New Tooling Jobs'!A$13:A$62,"<>",'New Tooling Jobs'!E$13:E$62,"<>Completed"),INDEX('New Tooling Jobs'!H$13:H$62,MATCH(9,'New Tooling Jobs'!AG$13:AG$62,0)),INDEX(Reorders!H$13:H$62,MATCH(9-COUNTIFS('New Tooling Jobs'!A$13:A$62,"<>",'New Tooling Jobs'!E$13:E$62,"<>Completed"),Reorders!AC$13:AC$62,0))),"") | G18: =IFERROR(IF(9<=COUNTIFS('New Tooling Jobs'!A$13:A$62,"<>",'New Tooling Jobs'!E$13:E$62,"<>Completed"),INDEX('New Tooling Jobs'!I$13:I$62,MATCH(9,'New Tooling Jobs'!AG$13:AG$62,0)),INDEX(Reorders!I$13:I$62,MATCH(9-COUNTIFS('New Tooling Jobs'!A$13:A$62,"<>",'New Tooling Jobs'!E$13:E$62,"<>Completed"),Reorders!AC$13:AC$62,0))),"")
A19: =IFERROR(IF(10<=COUNTIFS('New Tooling Jobs'!A$13:A$62,"<>",'New Tooling Jobs'!E$13:E$62,"<>Completed"),INDEX('New Tooling Jobs'!A$13:A$62,MATCH(10,'New Tooling Jobs'!AG$13:AG$62,0)),INDEX(Reorders!A$13:A$62,MATCH(10-COUNTIFS('New Tooling Jobs'!A$13:A$62,"<>",'New Tooling Jobs'!E$13:E$62,"<>Completed"),Reorders!AC$13:AC$62,0))),"") | B19: =IFERROR(IF(10<=COUNTIFS('New Tooling Jobs'!A$13:A$62,"<>",'New Tooling Jobs'!E$13:E$62,"<>Completed"),IF(INDEX('New Tooling Jobs'!A$13:A$62,MATCH(10,'New Tooling Jobs'!AG$13:AG$62,0))<>"","New Tooling",""),IF(INDEX(Reorders!A$13:A$62,MATCH(10-COUNTIFS('New Tooling Jobs'!A$13:A$62,"<>",'New Tooling Jobs'!E$13:E$62,"<>Completed"),Reorders!AC$13:AC$62,0))<>"","Reorder","")),"") | C19: =IFERROR(IF(10<=COUNTIFS('New Tooling Jobs'!A$13:A$62,"<>",'New Tooling Jobs'!E$13:E$62,"<>Completed"),INDEX('New Tooling Jobs'!B$13:B$62,MATCH(10,'New Tooling Jobs'!AG$13:AG$62,0)),INDEX(Reorders!B$13:B$62,MATCH(10-COUNTIFS('New Tooling Jobs'!A$13:A$62,"<>",'New Tooling Jobs'!E$13:E$62,"<>Completed"),Reorders!AC$13:AC$62,0))),"") | D19: =IFERROR(IF(10<=COUNTIFS('New Tooling Jobs'!A$13:A$62,"<>",'New Tooling Jobs'!E$13:E$62,"<>Completed"),INDEX('New Tooling Jobs'!E$13:E$62,MATCH(10,'New Tooling Jobs'!AG$13:AG$62,0)),INDEX(Reorders!E$13:E$62,MATCH(10-COUNTIFS('New Tooling Jobs'!A$13:A$62,"<>",'New Tooling Jobs'!E$13:E$62,"<>Completed"),Reorders!AC$13:AC$62,0))),"") | E19: =IFERROR(IF(10<=COUNTIFS('New Tooling Jobs'!A$13:A$62,"<>",'New Tooling Jobs'!E$13:E$62,"<>Completed"),INDEX('New Tooling Jobs'!G$13:G$62,MATCH(10,'New Tooling Jobs'!AG$13:AG$62,0)),INDEX(Reorders!G$13:G$62,MATCH(10-COUNTIFS('New Tooling Jobs'!A$13:A$62,"<>",'New Tooling Jobs'!E$13:E$62,"<>Completed"),Reorders!AC$13:AC$62,0))),"") | F19: =IFERROR(IF(10<=COUNTIFS('New Tooling Jobs'!A$13:A$62,"<>",'New Tooling Jobs'!E$13:E$62,"<>Completed"),INDEX('New Tooling Jobs'!H$13:H$62,MATCH(10,'New Tooling Jobs'!AG$13:AG$62,0)),INDEX(Reorders!H$13:H$62,MATCH(10-COUNTIFS('New Tooling Jobs'!A$13:A$62,"<>",'New Tooling Jobs'!E$13:E$62,"<>Completed"),Reorders!AC$13:AC$62,0))),"") | G19: =IFERROR(IF(10<=COUNTIFS('New Tooling Jobs'!A$13:A$62,"<>",'New Tooling Jobs'!E$13:E$62,"<>Completed"),INDEX('New Tooling Jobs'!I$13:I$62,MATCH(10,'New Tooling Jobs'!AG$13:AG$62,0)),INDEX(Reorders!I$13:I$62,MATCH(10-COUNTIFS('New Tooling Jobs'!A$13:A$62,"<>",'New Tooling Jobs'!E$13:E$62,"<>Completed"),Reorders!AC$13:AC$62,0))),"")
A20: =IFERROR(IF(11<=COUNTIFS('New Tooling Jobs'!A$13:A$62,"<>",'New Tooling Jobs'!E$13:E$62,"<>Completed"),INDEX('New Tooling Jobs'!A$13:A$62,MATCH(11,'New Tooling Jobs'!AG$13:AG$62,0)),INDEX(Reorders!A$13:A$62,MATCH(11-COUNTIFS('New Tooling Jobs'!A$13:A$62,"<>",'New Tooling Jobs'!E$13:E$62,"<>Completed"),Reorders!AC$13:AC$62,0))),"") | B20: =IFERROR(IF(11<=COUNTIFS('New Tooling Jobs'!A$13:A$62,"<>",'New Tooling Jobs'!E$13:E$62,"<>Completed"),IF(INDEX('New Tooling Jobs'!A$13:A$62,MATCH(11,'New Tooling Jobs'!AG$13:AG$62,0))<>"","New Tooling",""),IF(INDEX(Reorders!A$13:A$62,MATCH(11-COUNTIFS('New Tooling Jobs'!A$13:A$62,"<>",'New Tooling Jobs'!E$13:E$62,"<>Completed"),Reorders!AC$13:AC$62,0))<>"","Reorder","")),"") | C20: =IFERROR(IF(11<=COUNTIFS('New Tooling Jobs'!A$13:A$62,"<>",'New Tooling Jobs'!E$13:E$62,"<>Completed"),INDEX('New Tooling Jobs'!B$13:B$62,MATCH(11,'New Tooling Jobs'!AG$13:AG$62,0)),INDEX(Reorders!B$13:B$62,MATCH(11-COUNTIFS('New Tooling Jobs'!A$13:A$62,"<>",'New Tooling Jobs'!E$13:E$62,"<>Completed"),Reorders!AC$13:AC$62,0))),"") | D20: =IFERROR(IF(11<=COUNTIFS('New Tooling Jobs'!A$13:A$62,"<>",'New Tooling Jobs'!E$13:E$62,"<>Completed"),INDEX('New Tooling Jobs'!E$13:E$62,MATCH(11,'New Tooling Jobs'!AG$13:AG$62,0)),INDEX(Reorders!E$13:E$62,MATCH(11-COUNTIFS('New Tooling Jobs'!A$13:A$62,"<>",'New Tooling Jobs'!E$13:E$62,"<>Completed"),Reorders!AC$13:AC$62,0))),"") | E20: =IFERROR(IF(11<=COUNTIFS('New Tooling Jobs'!A$13:A$62,"<>",'New Tooling Jobs'!E$13:E$62,"<>Completed"),INDEX('New Tooling Jobs'!G$13:G$62,MATCH(11,'New Tooling Jobs'!AG$13:AG$62,0)),INDEX(Reorders!G$13:G$62,MATCH(11-COUNTIFS('New Tooling Jobs'!A$13:A$62,"<>",'New Tooling Jobs'!E$13:E$62,"<>Completed"),Reorders!AC$13:AC$62,0))),"") | F20: =IFERROR(IF(11<=COUNTIFS('New Tooling Jobs'!A$13:A$62,"<>",'New Tooling Jobs'!E$13:E$62,"<>Completed"),INDEX('New Tooling Jobs'!H$13:H$62,MATCH(11,'New Tooling Jobs'!AG$13:AG$62,0)),INDEX(Reorders!H$13:H$62,MATCH(11-COUNTIFS('New Tooling Jobs'!A$13:A$62,"<>",'New Tooling Jobs'!E$13:E$62,"<>Completed"),Reorders!AC$13:AC$62,0))),"") | G20: =IFERROR(IF(11<=COUNTIFS('New Tooling Jobs'!A$13:A$62,"<>",'New Tooling Jobs'!E$13:E$62,"<>Completed"),INDEX('New Tooling Jobs'!I$13:I$62,MATCH(11,'New Tooling Jobs'!AG$13:AG$62,0)),INDEX(Reorders!I$13:I$62,MATCH(11-COUNTIFS('New Tooling Jobs'!A$13:A$62,"<>",'New Tooling Jobs'!E$13:E$62,"<>Completed"),Reorders!AC$13:AC$62,0))),"")
A21: =IFERROR(IF(12<=COUNTIFS('New Tooling Jobs'!A$13:A$62,"<>",'New Tooling Jobs'!E$13:E$62,"<>Completed"),INDEX('New Tooling Jobs'!A$13:A$62,MATCH(12,'New Tooling Jobs'!AG$13:AG$62,0)),INDEX(Reorders!A$13:A$62,MATCH(12-COUNTIFS('New Tooling Jobs'!A$13:A$62,"<>",'New Tooling Jobs'!E$13:E$62,"<>Completed"),Reorders!AC$13:AC$62,0))),"") | B21: =IFERROR(IF(12<=COUNTIFS('New Tooling Jobs'!A$13:A$62,"<>",'New Tooling Jobs'!E$13:E$62,"<>Completed"),IF(INDEX('New Tooling Jobs'!A$13:A$62,MATCH(12,'New Tooling Jobs'!AG$13:AG$62,0))<>"","New Tooling",""),IF(INDEX(Reorders!A$13:A$62,MATCH(12-COUNTIFS('New Tooling Jobs'!A$13:A$62,"<>",'New Tooling Jobs'!E$13:E$62,"<>Completed"),Reorders!AC$13:AC$62,0))<>"","Reorder","")),"") | C21: =IFERROR(IF(12<=COUNTIFS('New Tooling Jobs'!A$13:A$62,"<>",'New Tooling Jobs'!E$13:E$62,"<>Completed"),INDEX('New Tooling Jobs'!B$13:B$62,MATCH(12,'New Tooling Jobs'!AG$13:AG$62,0)),INDEX(Reorders!B$13:B$62,MATCH(12-COUNTIFS('New Tooling Jobs'!A$13:A$62,"<>",'New Tooling Jobs'!E$13:E$62,"<>Completed"),Reorders!AC$13:AC$62,0))),"") | D21: =IFERROR(IF(12<=COUNTIFS('New Tooling Jobs'!A$13:A$62,"<>",'New Tooling Jobs'!E$13:E$62,"<>Completed"),INDEX('New Tooling Jobs'!E$13:E$62,MATCH(12,'New Tooling Jobs'!AG$13:AG$62,0)),INDEX(Reorders!E$13:E$62,MATCH(12-COUNTIFS('New Tooling Jobs'!A$13:A$62,"<>",'New Tooling Jobs'!E$13:E$62,"<>Completed"),Reorders!AC$13:AC$62,0))),"") | E21: =IFERROR(IF(12<=COUNTIFS('New Tooling Jobs'!A$13:A$62,"<>",'New Tooling Jobs'!E$13:E$62,"<>Completed"),INDEX('New Tooling Jobs'!G$13:G$62,MATCH(12,'New Tooling Jobs'!AG$13:AG$62,0)),INDEX(Reorders!G$13:G$62,MATCH(12-COUNTIFS('New Tooling Jobs'!A$13:A$62,"<>",'New Tooling Jobs'!E$13:E$62,"<>Completed"),Reorders!AC$13:AC$62,0))),"") | F21: =IFERROR(IF(12<=COUNTIFS('New Tooling Jobs'!A$13:A$62,"<>",'New Tooling Jobs'!E$13:E$62,"<>Completed"),INDEX('New Tooling Jobs'!H$13:H$62,MATCH(12,'New Tooling Jobs'!AG$13:AG$62,0)),INDEX(Reorders!H$13:H$62,MATCH(12-COUNTIFS('New Tooling Jobs'!A$13:A$62,"<>",'New Tooling Jobs'!E$13:E$62,"<>Completed"),Reorders!AC$13:AC$62,0))),"") | G21: =IFERROR(IF(12<=COUNTIFS('New Tooling Jobs'!A$13:A$62,"<>",'New Tooling Jobs'!E$13:E$62,"<>Completed"),INDEX('New Tooling Jobs'!I$13:I$62,MATCH(12,'New Tooling Jobs'!AG$13:AG$62,0)),INDEX(Reorders!I$13:I$62,MATCH(12-COUNTIFS('New Tooling Jobs'!A$13:A$62,"<>",'New Tooling Jobs'!E$13:E$62,"<>Completed"),Reorders!AC$13:AC$62,0))),"")
A22: =IFERROR(IF(13<=COUNTIFS('New Tooling Jobs'!A$13:A$62,"<>",'New Tooling Jobs'!E$13:E$62,"<>Completed"),INDEX('New Tooling Jobs'!A$13:A$62,MATCH(13,'New Tooling Jobs'!AG$13:AG$62,0)),INDEX(Reorders!A$13:A$62,MATCH(13-COUNTIFS('New Tooling Jobs'!A$13:A$62,"<>",'New Tooling Jobs'!E$13:E$62,"<>Completed"),Reorders!AC$13:AC$62,0))),"") | B22: =IFERROR(IF(13<=COUNTIFS('New Tooling Jobs'!A$13:A$62,"<>",'New Tooling Jobs'!E$13:E$62,"<>Completed"),IF(INDEX('New Tooling Jobs'!A$13:A$62,MATCH(13,'New Tooling Jobs'!AG$13:AG$62,0))<>"","New Tooling",""),IF(INDEX(Reorders!A$13:A$62,MATCH(13-COUNTIFS('New Tooling Jobs'!A$13:A$62,"<>",'New Tooling Jobs'!E$13:E$62,"<>Completed"),Reorders!AC$13:AC$62,0))<>"","Reorder","")),"") | C22: =IFERROR(IF(13<=COUNTIFS('New Tooling Jobs'!A$13:A$62,"<>",'New Tooling Jobs'!E$13:E$62,"<>Completed"),INDEX('New Tooling Jobs'!B$13:B$62,MATCH(13,'New Tooling Jobs'!AG$13:AG$62,0)),INDEX(Reorders!B$13:B$62,MATCH(13-COUNTIFS('New Tooling Jobs'!A$13:A$62,"<>",'New Tooling Jobs'!E$13:E$62,"<>Completed"),Reorders!AC$13:AC$62,0))),"") | D22: =IFERROR(IF(13<=COUNTIFS('New Tooling Jobs'!A$13:A$62,"<>",'New Tooling Jobs'!E$13:E$62,"<>Completed"),INDEX('New Tooling Jobs'!E$13:E$62,MATCH(13,'New Tooling Jobs'!AG$13:AG$62,0)),INDEX(Reorders!E$13:E$62,MATCH(13-COUNTIFS('New Tooling Jobs'!A$13:A$62,"<>",'New Tooling Jobs'!E$13:E$62,"<>Completed"),Reorders!AC$13:AC$62,0))),"") | E22: =IFERROR(IF(13<=COUNTIFS('New Tooling Jobs'!A$13:A$62,"<>",'New Tooling Jobs'!E$13:E$62,"<>Completed"),INDEX('New Tooling Jobs'!G$13:G$62,MATCH(13,'New Tooling Jobs'!AG$13:AG$62,0)),INDEX(Reorders!G$13:G$62,MATCH(13-COUNTIFS('New Tooling Jobs'!A$13:A$62,"<>",'New Tooling Jobs'!E$13:E$62,"<>Completed"),Reorders!AC$13:AC$62,0))),"") | F22: =IFERROR(IF(13<=COUNTIFS('New Tooling Jobs'!A$13:A$62,"<>",'New Tooling Jobs'!E$13:E$62,"<>Completed"),INDEX('New Tooling Jobs'!H$13:H$62,MATCH(13,'New Tooling Jobs'!AG$13:AG$62,0)),INDEX(Reorders!H$13:H$62,MATCH(13-COUNTIFS('New Tooling Jobs'!A$13:A$62,"<>",'New Tooling Jobs'!E$13:E$62,"<>Completed"),Reorders!AC$13:AC$62,0))),"") | G22: =IFERROR(IF(13<=COUNTIFS('New Tooling Jobs'!A$13:A$62,"<>",'New Tooling Jobs'!E$13:E$62,"<>Completed"),INDEX('New Tooling Jobs'!I$13:I$62,MATCH(13,'New Tooling Jobs'!AG$13:AG$62,0)),INDEX(Reorders!I$13:I$62,MATCH(13-COUNTIFS('New Tooling Jobs'!A$13:A$62,"<>",'New Tooling Jobs'!E$13:E$62,"<>Completed"),Reorders!AC$13:AC$62,0))),"")
A23: =IFERROR(IF(14<=COUNTIFS('New Tooling Jobs'!A$13:A$62,"<>",'New Tooling Jobs'!E$13:E$62,"<>Completed"),INDEX('New Tooling Jobs'!A$13:A$62,MATCH(14,'New Tooling Jobs'!AG$13:AG$62,0)),INDEX(Reorders!A$13:A$62,MATCH(14-COUNTIFS('New Tooling Jobs'!A$13:A$62,"<>",'New Tooling Jobs'!E$13:E$62,"<>Completed"),Reorders!AC$13:AC$62,0))),"") | B23: =IFERROR(IF(14<=COUNTIFS('New Tooling Jobs'!A$13:A$62,"<>",'New Tooling Jobs'!E$13:E$62,"<>Completed"),IF(INDEX('New Tooling Jobs'!A$13:A$62,MATCH(14,'New Tooling Jobs'!AG$13:AG$62,0))<>"","New Tooling",""),IF(INDEX(Reorders!A$13:A$62,MATCH(14-COUNTIFS('New Tooling Jobs'!A$13:A$62,"<>",'New Tooling Jobs'!E$13:E$62,"<>Completed"),Reorders!AC$13:AC$62,0))<>"","Reorder","")),"") | C23: =IFERROR(IF(14<=COUNTIFS('New Tooling Jobs'!A$13:A$62,"<>",'New Tooling Jobs'!E$13:E$62,"<>Completed"),INDEX('New Tooling Jobs'!B$13:B$62,MATCH(14,'New Tooling Jobs'!AG$13:AG$62,0)),INDEX(Reorders!B$13:B$62,MATCH(14-COUNTIFS('New Tooling Jobs'!A$13:A$62,"<>",'New Tooling Jobs'!E$13:E$62,"<>Completed"),Reorders!AC$13:AC$62,0))),"") | D23: =IFERROR(IF(14<=COUNTIFS('New Tooling Jobs'!A$13:A$62,"<>",'New Tooling Jobs'!E$13:E$62,"<>Completed"),INDEX('New Tooling Jobs'!E$13:E$62,MATCH(14,'New Tooling Jobs'!AG$13:AG$62,0)),INDEX(Reorders!E$13:E$62,MATCH(14-COUNTIFS('New Tooling Jobs'!A$13:A$62,"<>",'New Tooling Jobs'!E$13:E$62,"<>Completed"),Reorders!AC$13:AC$62,0))),"") | E23: =IFERROR(IF(14<=COUNTIFS('New Tooling Jobs'!A$13:A$62,"<>",'New Tooling Jobs'!E$13:E$62,"<>Completed"),INDEX('New Tooling Jobs'!G$13:G$62,MATCH(14,'New Tooling Jobs'!AG$13:AG$62,0)),INDEX(Reorders!G$13:G$62,MATCH(14-COUNTIFS('New Tooling Jobs'!A$13:A$62,"<>",'New Tooling Jobs'!E$13:E$62,"<>Completed"),Reorders!AC$13:AC$62,0))),"") | F23: =IFERROR(IF(14<=COUNTIFS('New Tooling Jobs'!A$13:A$62,"<>",'New Tooling Jobs'!E$13:E$62,"<>Completed"),INDEX('New Tooling Jobs'!H$13:H$62,MATCH(14,'New Tooling Jobs'!AG$13:AG$62,0)),INDEX(Reorders!H$13:H$62,MATCH(14-COUNTIFS('New Tooling Jobs'!A$13:A$62,"<>",'New Tooling Jobs'!E$13:E$62,"<>Completed"),Reorders!AC$13:AC$62,0))),"") | G23: =IFERROR(IF(14<=COUNTIFS('New Tooling Jobs'!A$13:A$62,"<>",'New Tooling Jobs'!E$13:E$62,"<>Completed"),INDEX('New Tooling Jobs'!I$13:I$62,MATCH(14,'New Tooling Jobs'!AG$13:AG$62,0)),INDEX(Reorders!I$13:I$62,MATCH(14-COUNTIFS('New Tooling Jobs'!A$13:A$62,"<>",'New Tooling Jobs'!E$13:E$62,"<>Completed"),Reorders!AC$13:AC$62,0))),"")
A24: =IFERROR(IF(15<=COUNTIFS('New Tooling Jobs'!A$13:A$62,"<>",'New Tooling Jobs'!E$13:E$62,"<>Completed"),INDEX('New Tooling Jobs'!A$13:A$62,MATCH(15,'New Tooling Jobs'!AG$13:AG$62,0)),INDEX(Reorders!A$13:A$62,MATCH(15-COUNTIFS('New Tooling Jobs'!A$13:A$62,"<>",'New Tooling Jobs'!E$13:E$62,"<>Completed"),Reorders!AC$13:AC$62,0))),"") | B24: =IFERROR(IF(15<=COUNTIFS('New Tooling Jobs'!A$13:A$62,"<>",'New Tooling Jobs'!E$13:E$62,"<>Completed"),IF(INDEX('New Tooling Jobs'!A$13:A$62,MATCH(15,'New Tooling Jobs'!AG$13:AG$62,0))<>"","New Tooling",""),IF(INDEX(Reorders!A$13:A$62,MATCH(15-COUNTIFS('New Tooling Jobs'!A$13:A$62,"<>",'New Tooling Jobs'!E$13:E$62,"<>Completed"),Reorders!AC$13:AC$62,0))<>"","Reorder","")),"") | C24: =IFERROR(IF(15<=COUNTIFS('New Tooling Jobs'!A$13:A$62,"<>",'New Tooling Jobs'!E$13:E$62,"<>Completed"),INDEX('New Tooling Jobs'!B$13:B$62,MATCH(15,'New Tooling Jobs'!AG$13:AG$62,0)),INDEX(Reorders!B$13:B$62,MATCH(15-COUNTIFS('New Tooling Jobs'!A$13:A$62,"<>",'New Tooling Jobs'!E$13:E$62,"<>Completed"),Reorders!AC$13:AC$62,0))),"") | D24: =IFERROR(IF(15<=COUNTIFS('New Tooling Jobs'!A$13:A$62,"<>",'New Tooling Jobs'!E$13:E$62,"<>Completed"),INDEX('New Tooling Jobs'!E$13:E$62,MATCH(15,'New Tooling Jobs'!AG$13:AG$62,0)),INDEX(Reorders!E$13:E$62,MATCH(15-COUNTIFS('New Tooling Jobs'!A$13:A$62,"<>",'New Tooling Jobs'!E$13:E$62,"<>Completed"),Reorders!AC$13:AC$62,0))),"") | E24: =IFERROR(IF(15<=COUNTIFS('New Tooling Jobs'!A$13:A$62,"<>",'New Tooling Jobs'!E$13:E$62,"<>Completed"),INDEX('New Tooling Jobs'!G$13:G$62,MATCH(15,'New Tooling Jobs'!AG$13:AG$62,0)),INDEX(Reorders!G$13:G$62,MATCH(15-COUNTIFS('New Tooling Jobs'!A$13:A$62,"<>",'New Tooling Jobs'!E$13:E$62,"<>Completed"),Reorders!AC$13:AC$62,0))),"") | F24: =IFERROR(IF(15<=COUNTIFS('New Tooling Jobs'!A$13:A$62,"<>",'New Tooling Jobs'!E$13:E$62,"<>Completed"),INDEX('New Tooling Jobs'!H$13:H$62,MATCH(15,'New Tooling Jobs'!AG$13:AG$62,0)),INDEX(Reorders!H$13:H$62,MATCH(15-COUNTIFS('New Tooling Jobs'!A$13:A$62,"<>",'New Tooling Jobs'!E$13:E$62,"<>Completed"),Reorders!AC$13:AC$62,0))),"") | G24: =IFERROR(IF(15<=COUNTIFS('New Tooling Jobs'!A$13:A$62,"<>",'New Tooling Jobs'!E$13:E$62,"<>Completed"),INDEX('New Tooling Jobs'!I$13:I$62,MATCH(15,'New Tooling Jobs'!AG$13:AG$62,0)),INDEX(Reorders!I$13:I$62,MATCH(15-COUNTIFS('New Tooling Jobs'!A$13:A$62,"<>",'New Tooling Jobs'!E$13:E$62,"<>Completed"),Reorders!AC$13:AC$62,0))),"")
A25: =IFERROR(IF(16<=COUNTIFS('New Tooling Jobs'!A$13:A$62,"<>",'New Tooling Jobs'!E$13:E$62,"<>Completed"),INDEX('New Tooling Jobs'!A$13:A$62,MATCH(16,'New Tooling Jobs'!AG$13:AG$62,0)),INDEX(Reorders!A$13:A$62,MATCH(16-COUNTIFS('New Tooling Jobs'!A$13:A$62,"<>",'New Tooling Jobs'!E$13:E$62,"<>Completed"),Reorders!AC$13:AC$62,0))),"") | B25: =IFERROR(IF(16<=COUNTIFS('New Tooling Jobs'!A$13:A$62,"<>",'New Tooling Jobs'!E$13:E$62,"<>Completed"),IF(INDEX('New Tooling Jobs'!A$13:A$62,MATCH(16,'New Tooling Jobs'!AG$13:AG$62,0))<>"","New Tooling",""),IF(INDEX(Reorders!A$13:A$62,MATCH(16-COUNTIFS('New Tooling Jobs'!A$13:A$62,"<>",'New Tooling Jobs'!E$13:E$62,"<>Completed"),Reorders!AC$13:AC$62,0))<>"","Reorder","")),"") | C25: =IFERROR(IF(16<=COUNTIFS('New Tooling Jobs'!A$13:A$62,"<>",'New Tooling Jobs'!E$13:E$62,"<>Completed"),INDEX('New Tooling Jobs'!B$13:B$62,MATCH(16,'New Tooling Jobs'!AG$13:AG$62,0)),INDEX(Reorders!B$13:B$62,MATCH(16-COUNTIFS('New Tooling Jobs'!A$13:A$62,"<>",'New Tooling Jobs'!E$13:E$62,"<>Completed"),Reorders!AC$13:AC$62,0))),"") | D25: =IFERROR(IF(16<=COUNTIFS('New Tooling Jobs'!A$13:A$62,"<>",'New Tooling Jobs'!E$13:E$62,"<>Completed"),INDEX('New Tooling Jobs'!E$13:E$62,MATCH(16,'New Tooling Jobs'!AG$13:AG$62,0)),INDEX(Reorders!E$13:E$62,MATCH(16-COUNTIFS('New Tooling Jobs'!A$13:A$62,"<>",'New Tooling Jobs'!E$13:E$62,"<>Completed"),Reorders!AC$13:AC$62,0))),"") | E25: =IFERROR(IF(16<=COUNTIFS('New Tooling Jobs'!A$13:A$62,"<>",'New Tooling Jobs'!E$13:E$62,"<>Completed"),INDEX('New Tooling Jobs'!G$13:G$62,MATCH(16,'New Tooling Jobs'!AG$13:AG$62,0)),INDEX(Reorders!G$13:G$62,MATCH(16-COUNTIFS('New Tooling Jobs'!A$13:A$62,"<>",'New Tooling Jobs'!E$13:E$62,"<>Completed"),Reorders!AC$13:AC$62,0))),"") | F25: =IFERROR(IF(16<=COUNTIFS('New Tooling Jobs'!A$13:A$62,"<>",'New Tooling Jobs'!E$13:E$62,"<>Completed"),INDEX('New Tooling Jobs'!H$13:H$62,MATCH(16,'New Tooling Jobs'!AG$13:AG$62,0)),INDEX(Reorders!H$13:H$62,MATCH(16-COUNTIFS('New Tooling Jobs'!A$13:A$62,"<>",'New Tooling Jobs'!E$13:E$62,"<>Completed"),Reorders!AC$13:AC$62,0))),"") | G25: =IFERROR(IF(16<=COUNTIFS('New Tooling Jobs'!A$13:A$62,"<>",'New Tooling Jobs'!E$13:E$62,"<>Completed"),INDEX('New Tooling Jobs'!I$13:I$62,MATCH(16,'New Tooling Jobs'!AG$13:AG$62,0)),INDEX(Reorders!I$13:I$62,MATCH(16-COUNTIFS('New Tooling Jobs'!A$13:A$62,"<>",'New Tooling Jobs'!E$13:E$62,"<>Completed"),Reorders!AC$13:AC$62,0))),"")
A26: =IFERROR(IF(17<=COUNTIFS('New Tooling Jobs'!A$13:A$62,"<>",'New Tooling Jobs'!E$13:E$62,"<>Completed"),INDEX('New Tooling Jobs'!A$13:A$62,MATCH(17,'New Tooling Jobs'!AG$13:AG$62,0)),INDEX(Reorders!A$13:A$62,MATCH(17-COUNTIFS('New Tooling Jobs'!A$13:A$62,"<>",'New Tooling Jobs'!E$13:E$62,"<>Completed"),Reorders!AC$13:AC$62,0))),"") | B26: =IFERROR(IF(17<=COUNTIFS('New Tooling Jobs'!A$13:A$62,"<>",'New Tooling Jobs'!E$13:E$62,"<>Completed"),IF(INDEX('New Tooling Jobs'!A$13:A$62,MATCH(17,'New Tooling Jobs'!AG$13:AG$62,0))<>"","New Tooling",""),IF(INDEX(Reorders!A$13:A$62,MATCH(17-COUNTIFS('New Tooling Jobs'!A$13:A$62,"<>",'New Tooling Jobs'!E$13:E$62,"<>Completed"),Reorders!AC$13:AC$62,0))<>"","Reorder","")),"") | C26: =IFERROR(IF(17<=COUNTIFS('New Tooling Jobs'!A$13:A$62,"<>",'New Tooling Jobs'!E$13:E$62,"<>Completed"),INDEX('New Tooling Jobs'!B$13:B$62,MATCH(17,'New Tooling Jobs'!AG$13:AG$62,0)),INDEX(Reorders!B$13:B$62,MATCH(17-COUNTIFS('New Tooling Jobs'!A$13:A$62,"<>",'New Tooling Jobs'!E$13:E$62,"<>Completed"),Reorders!AC$13:AC$62,0))),"") | D26: =IFERROR(IF(17<=COUNTIFS('New Tooling Jobs'!A$13:A$62,"<>",'New Tooling Jobs'!E$13:E$62,"<>Completed"),INDEX('New Tooling Jobs'!E$13:E$62,MATCH(17,'New Tooling Jobs'!AG$13:AG$62,0)),INDEX(Reorders!E$13:E$62,MATCH(17-COUNTIFS('New Tooling Jobs'!A$13:A$62,"<>",'New Tooling Jobs'!E$13:E$62,"<>Completed"),Reorders!AC$13:AC$62,0))),"") | E26: =IFERROR(IF(17<=COUNTIFS('New Tooling Jobs'!A$13:A$62,"<>",'New Tooling Jobs'!E$13:E$62,"<>Completed"),INDEX('New Tooling Jobs'!G$13:G$62,MATCH(17,'New Tooling Jobs'!AG$13:AG$62,0)),INDEX(Reorders!G$13:G$62,MATCH(17-COUNTIFS('New Tooling Jobs'!A$13:A$62,"<>",'New Tooling Jobs'!E$13:E$62,"<>Completed"),Reorders!AC$13:AC$62,0))),"") | F26: =IFERROR(IF(17<=COUNTIFS('New Tooling Jobs'!A$13:A$62,"<>",'New Tooling Jobs'!E$13:E$62,"<>Completed"),INDEX('New Tooling Jobs'!H$13:H$62,MATCH(17,'New Tooling Jobs'!AG$13:AG$62,0)),INDEX(Reorders!H$13:H$62,MATCH(17-COUNTIFS('New Tooling Jobs'!A$13:A$62,"<>",'New Tooling Jobs'!E$13:E$62,"<>Completed"),Reorders!AC$13:AC$62,0))),"") | G26: =IFERROR(IF(17<=COUNTIFS('New Tooling Jobs'!A$13:A$62,"<>",'New Tooling Jobs'!E$13:E$62,"<>Completed"),INDEX('New Tooling Jobs'!I$13:I$62,MATCH(17,'New Tooling Jobs'!AG$13:AG$62,0)),INDEX(Reorders!I$13:I$62,MATCH(17-COUNTIFS('New Tooling Jobs'!A$13:A$62,"<>",'New Tooling Jobs'!E$13:E$62,"<>Completed"),Reorders!AC$13:AC$62,0))),"")
A27: =IFERROR(IF(18<=COUNTIFS('New Tooling Jobs'!A$13:A$62,"<>",'New Tooling Jobs'!E$13:E$62,"<>Completed"),INDEX('New Tooling Jobs'!A$13:A$62,MATCH(18,'New Tooling Jobs'!AG$13:AG$62,0)),INDEX(Reorders!A$13:A$62,MATCH(18-COUNTIFS('New Tooling Jobs'!A$13:A$62,"<>",'New Tooling Jobs'!E$13:E$62,"<>Completed"),Reorders!AC$13:AC$62,0))),"") | B27: =IFERROR(IF(18<=COUNTIFS('New Tooling Jobs'!A$13:A$62,"<>",'New Tooling Jobs'!E$13:E$62,"<>Completed"),IF(INDEX('New Tooling Jobs'!A$13:A$62,MATCH(18,'New Tooling Jobs'!AG$13:AG$62,0))<>"","New Tooling",""),IF(INDEX(Reorders!A$13:A$62,MATCH(18-COUNTIFS('New Tooling Jobs'!A$13:A$62,"<>",'New Tooling Jobs'!E$13:E$62,"<>Completed"),Reorders!AC$13:AC$62,0))<>"","Reorder","")),"") | C27: =IFERROR(IF(18<=COUNTIFS('New Tooling Jobs'!A$13:A$62,"<>",'New Tooling Jobs'!E$13:E$62,"<>Completed"),INDEX('New Tooling Jobs'!B$13:B$62,MATCH(18,'New Tooling Jobs'!AG$13:AG$62,0)),INDEX(Reorders!B$13:B$62,MATCH(18-COUNTIFS('New Tooling Jobs'!A$13:A$62,"<>",'New Tooling Jobs'!E$13:E$62,"<>Completed"),Reorders!AC$13:AC$62,0))),"") | D27: =IFERROR(IF(18<=COUNTIFS('New Tooling Jobs'!A$13:A$62,"<>",'New Tooling Jobs'!E$13:E$62,"<>Completed"),INDEX('New Tooling Jobs'!E$13:E$62,MATCH(18,'New Tooling Jobs'!AG$13:AG$62,0)),INDEX(Reorders!E$13:E$62,MATCH(18-COUNTIFS('New Tooling Jobs'!A$13:A$62,"<>",'New Tooling Jobs'!E$13:E$62,"<>Completed"),Reorders!AC$13:AC$62,0))),"") | E27: =IFERROR(IF(18<=COUNTIFS('New Tooling Jobs'!A$13:A$62,"<>",'New Tooling Jobs'!E$13:E$62,"<>Completed"),INDEX('New Tooling Jobs'!G$13:G$62,MATCH(18,'New Tooling Jobs'!AG$13:AG$62,0)),INDEX(Reorders!G$13:G$62,MATCH(18-COUNTIFS('New Tooling Jobs'!A$13:A$62,"<>",'New Tooling Jobs'!E$13:E$62,"<>Completed"),Reorders!AC$13:AC$62,0))),"") | F27: =IFERROR(IF(18<=COUNTIFS('New Tooling Jobs'!A$13:A$62,"<>",'New Tooling Jobs'!E$13:E$62,"<>Completed"),INDEX('New Tooling Jobs'!H$13:H$62,MATCH(18,'New Tooling Jobs'!AG$13:AG$62,0)),INDEX(Reorders!H$13:H$62,MATCH(18-COUNTIFS('New Tooling Jobs'!A$13:A$62,"<>",'New Tooling Jobs'!E$13:E$62,"<>Completed"),Reorders!AC$13:AC$62,0))),"") | G27: =IFERROR(IF(18<=COUNTIFS('New Tooling Jobs'!A$13:A$62,"<>",'New Tooling Jobs'!E$13:E$62,"<>Completed"),INDEX('New Tooling Jobs'!I$13:I$62,MATCH(18,'New Tooling Jobs'!AG$13:AG$62,0)),INDEX(Reorders!I$13:I$62,MATCH(18-COUNTIFS('New Tooling Jobs'!A$13:A$62,"<>",'New Tooling Jobs'!E$13:E$62,"<>Completed"),Reorders!AC$13:AC$62,0))),"")
A28: =IFERROR(IF(19<=COUNTIFS('New Tooling Jobs'!A$13:A$62,"<>",'New Tooling Jobs'!E$13:E$62,"<>Completed"),INDEX('New Tooling Jobs'!A$13:A$62,MATCH(19,'New Tooling Jobs'!AG$13:AG$62,0)),INDEX(Reorders!A$13:A$62,MATCH(19-COUNTIFS('New Tooling Jobs'!A$13:A$62,"<>",'New Tooling Jobs'!E$13:E$62,"<>Completed"),Reorders!AC$13:AC$62,0))),"") | B28: =IFERROR(IF(19<=COUNTIFS('New Tooling Jobs'!A$13:A$62,"<>",'New Tooling Jobs'!E$13:E$62,"<>Completed"),IF(INDEX('New Tooling Jobs'!A$13:A$62,MATCH(19,'New Tooling Jobs'!AG$13:AG$62,0))<>"","New Tooling",""),IF(INDEX(Reorders!A$13:A$62,MATCH(19-COUNTIFS('New Tooling Jobs'!A$13:A$62,"<>",'New Tooling Jobs'!E$13:E$62,"<>Completed"),Reorders!AC$13:AC$62,0))<>"","Reorder","")),"") | C28: =IFERROR(IF(19<=COUNTIFS('New Tooling Jobs'!A$13:A$62,"<>",'New Tooling Jobs'!E$13:E$62,"<>Completed"),INDEX('New Tooling Jobs'!B$13:B$62,MATCH(19,'New Tooling Jobs'!AG$13:AG$62,0)),INDEX(Reorders!B$13:B$62,MATCH(19-COUNTIFS('New Tooling Jobs'!A$13:A$62,"<>",'New Tooling Jobs'!E$13:E$62,"<>Completed"),Reorders!AC$13:AC$62,0))),"") | D28: =IFERROR(IF(19<=COUNTIFS('New Tooling Jobs'!A$13:A$62,"<>",'New Tooling Jobs'!E$13:E$62,"<>Completed"),INDEX('New Tooling Jobs'!E$13:E$62,MATCH(19,'New Tooling Jobs'!AG$13:AG$62,0)),INDEX(Reorders!E$13:E$62,MATCH(19-COUNTIFS('New Tooling Jobs'!A$13:A$62,"<>",'New Tooling Jobs'!E$13:E$62,"<>Completed"),Reorders!AC$13:AC$62,0))),"") | E28: =IFERROR(IF(19<=COUNTIFS('New Tooling Jobs'!A$13:A$62,"<>",'New Tooling Jobs'!E$13:E$62,"<>Completed"),INDEX('New Tooling Jobs'!G$13:G$62,MATCH(19,'New Tooling Jobs'!AG$13:AG$62,0)),INDEX(Reorders!G$13:G$62,MATCH(19-COUNTIFS('New Tooling Jobs'!A$13:A$62,"<>",'New Tooling Jobs'!E$13:E$62,"<>Completed"),Reorders!AC$13:AC$62,0))),"") | F28: =IFERROR(IF(19<=COUNTIFS('New Tooling Jobs'!A$13:A$62,"<>",'New Tooling Jobs'!E$13:E$62,"<>Completed"),INDEX('New Tooling Jobs'!H$13:H$62,MATCH(19,'New Tooling Jobs'!AG$13:AG$62,0)),INDEX(Reorders!H$13:H$62,MATCH(19-COUNTIFS('New Tooling Jobs'!A$13:A$62,"<>",'New Tooling Jobs'!E$13:E$62,"<>Completed"),Reorders!AC$13:AC$62,0))),"") | G28: =IFERROR(IF(19<=COUNTIFS('New Tooling Jobs'!A$13:A$62,"<>",'New Tooling Jobs'!E$13:E$62,"<>Completed"),INDEX('New Tooling Jobs'!I$13:I$62,MATCH(19,'New Tooling Jobs'!AG$13:AG$62,0)),INDEX(Reorders!I$13:I$62,MATCH(19-COUNTIFS('New Tooling Jobs'!A$13:A$62,"<>",'New Tooling Jobs'!E$13:E$62,"<>Completed"),Reorders!AC$13:AC$62,0))),"")
A29: =IFERROR(IF(20<=COUNTIFS('New Tooling Jobs'!A$13:A$62,"<>",'New Tooling Jobs'!E$13:E$62,"<>Completed"),INDEX('New Tooling Jobs'!A$13:A$62,MATCH(20,'New Tooling Jobs'!AG$13:AG$62,0)),INDEX(Reorders!A$13:A$62,MATCH(20-COUNTIFS('New Tooling Jobs'!A$13:A$62,"<>",'New Tooling Jobs'!E$13:E$62,"<>Completed"),Reorders!AC$13:AC$62,0))),"") | B29: =IFERROR(IF(20<=COUNTIFS('New Tooling Jobs'!A$13:A$62,"<>",'New Tooling Jobs'!E$13:E$62,"<>Completed"),IF(INDEX('New Tooling Jobs'!A$13:A$62,MATCH(20,'New Tooling Jobs'!AG$13:AG$62,0))<>"","New Tooling",""),IF(INDEX(Reorders!A$13:A$62,MATCH(20-COUNTIFS('New Tooling Jobs'!A$13:A$62,"<>",'New Tooling Jobs'!E$13:E$62,"<>Completed"),Reorders!AC$13:AC$62,0))<>"","Reorder","")),"") | C29: =IFERROR(IF(20<=COUNTIFS('New Tooling Jobs'!A$13:A$62,"<>",'New Tooling Jobs'!E$13:E$62,"<>Completed"),INDEX('New Tooling Jobs'!B$13:B$62,MATCH(20,'New Tooling Jobs'!AG$13:AG$62,0)),INDEX(Reorders!B$13:B$62,MATCH(20-COUNTIFS('New Tooling Jobs'!A$13:A$62,"<>",'New Tooling Jobs'!E$13:E$62,"<>Completed"),Reorders!AC$13:AC$62,0))),"") | D29: =IFERROR(IF(20<=COUNTIFS('New Tooling Jobs'!A$13:A$62,"<>",'New Tooling Jobs'!E$13:E$62,"<>Completed"),INDEX('New Tooling Jobs'!E$13:E$62,MATCH(20,'New Tooling Jobs'!AG$13:AG$62,0)),INDEX(Reorders!E$13:E$62,MATCH(20-COUNTIFS('New Tooling Jobs'!A$13:A$62,"<>",'New Tooling Jobs'!E$13:E$62,"<>Completed"),Reorders!AC$13:AC$62,0))),"") | E29: =IFERROR(IF(20<=COUNTIFS('New Tooling Jobs'!A$13:A$62,"<>",'New Tooling Jobs'!E$13:E$62,"<>Completed"),INDEX('New Tooling Jobs'!G$13:G$62,MATCH(20,'New Tooling Jobs'!AG$13:AG$62,0)),INDEX(Reorders!G$13:G$62,MATCH(20-COUNTIFS('New Tooling Jobs'!A$13:A$62,"<>",'New Tooling Jobs'!E$13:E$62,"<>Completed"),Reorders!AC$13:AC$62,0))),"") | F29: =IFERROR(IF(20<=COUNTIFS('New Tooling Jobs'!A$13:A$62,"<>",'New Tooling Jobs'!E$13:E$62,"<>Completed"),INDEX('New Tooling Jobs'!H$13:H$62,MATCH(20,'New Tooling Jobs'!AG$13:AG$62,0)),INDEX(Reorders!H$13:H$62,MATCH(20-COUNTIFS('New Tooling Jobs'!A$13:A$62,"<>",'New Tooling Jobs'!E$13:E$62,"<>Completed"),Reorders!AC$13:AC$62,0))),"") | G29: =IFERROR(IF(20<=COUNTIFS('New Tooling Jobs'!A$13:A$62,"<>",'New Tooling Jobs'!E$13:E$62,"<>Completed"),INDEX('New Tooling Jobs'!I$13:I$62,MATCH(20,'New Tooling Jobs'!AG$13:AG$62,0)),INDEX(Reorders!I$13:I$62,MATCH(20-COUNTIFS('New Tooling Jobs'!A$13:A$62,"<>",'New Tooling Jobs'!E$13:E$62,"<>Completed"),Reorders!AC$13:AC$62,0))),"")
A30: =IFERROR(IF(21<=COUNTIFS('New Tooling Jobs'!A$13:A$62,"<>",'New Tooling Jobs'!E$13:E$62,"<>Completed"),INDEX('New Tooling Jobs'!A$13:A$62,MATCH(21,'New Tooling Jobs'!AG$13:AG$62,0)),INDEX(Reorders!A$13:A$62,MATCH(21-COUNTIFS('New Tooling Jobs'!A$13:A$62,"<>",'New Tooling Jobs'!E$13:E$62,"<>Completed"),Reorders!AC$13:AC$62,0))),"") | B30: =IFERROR(IF(21<=COUNTIFS('New Tooling Jobs'!A$13:A$62,"<>",'New Tooling Jobs'!E$13:E$62,"<>Completed"),IF(INDEX('New Tooling Jobs'!A$13:A$62,MATCH(21,'New Tooling Jobs'!AG$13:AG$62,0))<>"","New Tooling",""),IF(INDEX(Reorders!A$13:A$62,MATCH(21-COUNTIFS('New Tooling Jobs'!A$13:A$62,"<>",'New Tooling Jobs'!E$13:E$62,"<>Completed"),Reorders!AC$13:AC$62,0))<>"","Reorder","")),"") | C30: =IFERROR(IF(21<=COUNTIFS('New Tooling Jobs'!A$13:A$62,"<>",'New Tooling Jobs'!E$13:E$62,"<>Completed"),INDEX('New Tooling Jobs'!B$13:B$62,MATCH(21,'New Tooling Jobs'!AG$13:AG$62,0)),INDEX(Reorders!B$13:B$62,MATCH(21-COUNTIFS('New Tooling Jobs'!A$13:A$62,"<>",'New Tooling Jobs'!E$13:E$62,"<>Completed"),Reorders!AC$13:AC$62,0))),"") | D30: =IFERROR(IF(21<=COUNTIFS('New Tooling Jobs'!A$13:A$62,"<>",'New Tooling Jobs'!E$13:E$62,"<>Completed"),INDEX('New Tooling Jobs'!E$13:E$62,MATCH(21,'New Tooling Jobs'!AG$13:AG$62,0)),INDEX(Reorders!E$13:E$62,MATCH(21-COUNTIFS('New Tooling Jobs'!A$13:A$62,"<>",'New Tooling Jobs'!E$13:E$62,"<>Completed"),Reorders!AC$13:AC$62,0))),"") | E30: =IFERROR(IF(21<=COUNTIFS('New Tooling Jobs'!A$13:A$62,"<>",'New Tooling Jobs'!E$13:E$62,"<>Completed"),INDEX('New Tooling Jobs'!G$13:G$62,MATCH(21,'New Tooling Jobs'!AG$13:AG$62,0)),INDEX(Reorders!G$13:G$62,MATCH(21-COUNTIFS('New Tooling Jobs'!A$13:A$62,"<>",'New Tooling Jobs'!E$13:E$62,"<>Completed"),Reorders!AC$13:AC$62,0))),"") | F30: =IFERROR(IF(21<=COUNTIFS('New Tooling Jobs'!A$13:A$62,"<>",'New Tooling Jobs'!E$13:E$62,"<>Completed"),INDEX('New Tooling Jobs'!H$13:H$62,MATCH(21,'New Tooling Jobs'!AG$13:AG$62,0)),INDEX(Reorders!H$13:H$62,MATCH(21-COUNTIFS('New Tooling Jobs'!A$13:A$62,"<>",'New Tooling Jobs'!E$13:E$62,"<>Completed"),Reorders!AC$13:AC$62,0))),"") | G30: =IFERROR(IF(21<=COUNTIFS('New Tooling Jobs'!A$13:A$62,"<>",'New Tooling Jobs'!E$13:E$62,"<>Completed"),INDEX('New Tooling Jobs'!I$13:I$62,MATCH(21,'New Tooling Jobs'!AG$13:AG$62,0)),INDEX(Reorders!I$13:I$62,MATCH(21-COUNTIFS('New Tooling Jobs'!A$13:A$62,"<>",'New Tooling Jobs'!E$13:E$62,"<>Completed"),Reorders!AC$13:AC$62,0))),"")
A31: =IFERROR(IF(22<=COUNTIFS('New Tooling Jobs'!A$13:A$62,"<>",'New Tooling Jobs'!E$13:E$62,"<>Completed"),INDEX('New Tooling Jobs'!A$13:A$62,MATCH(22,'New Tooling Jobs'!AG$13:AG$62,0)),INDEX(Reorders!A$13:A$62,MATCH(22-COUNTIFS('New Tooling Jobs'!A$13:A$62,"<>",'New Tooling Jobs'!E$13:E$62,"<>Completed"),Reorders!AC$13:AC$62,0))),"") | B31: =IFERROR(IF(22<=COUNTIFS('New Tooling Jobs'!A$13:A$62,"<>",'New Tooling Jobs'!E$13:E$62,"<>Completed"),IF(INDEX('New Tooling Jobs'!A$13:A$62,MATCH(22,'New Tooling Jobs'!AG$13:AG$62,0))<>"","New Tooling",""),IF(INDEX(Reorders!A$13:A$62,MATCH(22-COUNTIFS('New Tooling Jobs'!A$13:A$62,"<>",'New Tooling Jobs'!E$13:E$62,"<>Completed"),Reorders!AC$13:AC$62,0))<>"","Reorder","")),"") | C31: =IFERROR(IF(22<=COUNTIFS('New Tooling Jobs'!A$13:A$62,"<>",'New Tooling Jobs'!E$13:E$62,"<>Completed"),INDEX('New Tooling Jobs'!B$13:B$62,MATCH(22,'New Tooling Jobs'!AG$13:AG$62,0)),INDEX(Reorders!B$13:B$62,MATCH(22-COUNTIFS('New Tooling Jobs'!A$13:A$62,"<>",'New Tooling Jobs'!E$13:E$62,"<>Completed"),Reorders!AC$13:AC$62,0))),"") | D31: =IFERROR(IF(22<=COUNTIFS('New Tooling Jobs'!A$13:A$62,"<>",'New Tooling Jobs'!E$13:E$62,"<>Completed"),INDEX('New Tooling Jobs'!E$13:E$62,MATCH(22,'New Tooling Jobs'!AG$13:AG$62,0)),INDEX(Reorders!E$13:E$62,MATCH(22-COUNTIFS('New Tooling Jobs'!A$13:A$62,"<>",'New Tooling Jobs'!E$13:E$62,"<>Completed"),Reorders!AC$13:AC$62,0))),"") | E31: =IFERROR(IF(22<=COUNTIFS('New Tooling Jobs'!A$13:A$62,"<>",'New Tooling Jobs'!E$13:E$62,"<>Completed"),INDEX('New Tooling Jobs'!G$13:G$62,MATCH(22,'New Tooling Jobs'!AG$13:AG$62,0)),INDEX(Reorders!G$13:G$62,MATCH(22-COUNTIFS('New Tooling Jobs'!A$13:A$62,"<>",'New Tooling Jobs'!E$13:E$62,"<>Completed"),Reorders!AC$13:AC$62,0))),"") | F31: =IFERROR(IF(22<=COUNTIFS('New Tooling Jobs'!A$13:A$62,"<>",'New Tooling Jobs'!E$13:E$62,"<>Completed"),INDEX('New Tooling Jobs'!H$13:H$62,MATCH(22,'New Tooling Jobs'!AG$13:AG$62,0)),INDEX(Reorders!H$13:H$62,MATCH(22-COUNTIFS('New Tooling Jobs'!A$13:A$62,"<>",'New Tooling Jobs'!E$13:E$62,"<>Completed"),Reorders!AC$13:AC$62,0))),"") | G31: =IFERROR(IF(22<=COUNTIFS('New Tooling Jobs'!A$13:A$62,"<>",'New Tooling Jobs'!E$13:E$62,"<>Completed"),INDEX('New Tooling Jobs'!I$13:I$62,MATCH(22,'New Tooling Jobs'!AG$13:AG$62,0)),INDEX(Reorders!I$13:I$62,MATCH(22-COUNTIFS('New Tooling Jobs'!A$13:A$62,"<>",'New Tooling Jobs'!E$13:E$62,"<>Completed"),Reorders!AC$13:AC$62,0))),"")
A32: =IFERROR(IF(23<=COUNTIFS('New Tooling Jobs'!A$13:A$62,"<>",'New Tooling Jobs'!E$13:E$62,"<>Completed"),INDEX('New Tooling Jobs'!A$13:A$62,MATCH(23,'New Tooling Jobs'!AG$13:AG$62,0)),INDEX(Reorders!A$13:A$62,MATCH(23-COUNTIFS('New Tooling Jobs'!A$13:A$62,"<>",'New Tooling Jobs'!E$13:E$62,"<>Completed"),Reorders!AC$13:AC$62,0))),"") | B32: =IFERROR(IF(23<=COUNTIFS('New Tooling Jobs'!A$13:A$62,"<>",'New Tooling Jobs'!E$13:E$62,"<>Completed"),IF(INDEX('New Tooling Jobs'!A$13:A$62,MATCH(23,'New Tooling Jobs'!AG$13:AG$62,0))<>"","New Tooling",""),IF(INDEX(Reorders!A$13:A$62,MATCH(23-COUNTIFS('New Tooling Jobs'!A$13:A$62,"<>",'New Tooling Jobs'!E$13:E$62,"<>Completed"),Reorders!AC$13:AC$62,0))<>"","Reorder","")),"") | C32: =IFERROR(IF(23<=COUNTIFS('New Tooling Jobs'!A$13:A$62,"<>",'New Tooling Jobs'!E$13:E$62,"<>Completed"),INDEX('New Tooling Jobs'!B$13:B$62,MATCH(23,'New Tooling Jobs'!AG$13:AG$62,0)),INDEX(Reorders!B$13:B$62,MATCH(23-COUNTIFS('New Tooling Jobs'!A$13:A$62,"<>",'New Tooling Jobs'!E$13:E$62,"<>Completed"),Reorders!AC$13:AC$62,0))),"") | D32: =IFERROR(IF(23<=COUNTIFS('New Tooling Jobs'!A$13:A$62,"<>",'New Tooling Jobs'!E$13:E$62,"<>Completed"),INDEX('New Tooling Jobs'!E$13:E$62,MATCH(23,'New Tooling Jobs'!AG$13:AG$62,0)),INDEX(Reorders!E$13:E$62,MATCH(23-COUNTIFS('New Tooling Jobs'!A$13:A$62,"<>",'New Tooling Jobs'!E$13:E$62,"<>Completed"),Reorders!AC$13:AC$62,0))),"") | E32: =IFERROR(IF(23<=COUNTIFS('New Tooling Jobs'!A$13:A$62,"<>",'New Tooling Jobs'!E$13:E$62,"<>Completed"),INDEX('New Tooling Jobs'!G$13:G$62,MATCH(23,'New Tooling Jobs'!AG$13:AG$62,0)),INDEX(Reorders!G$13:G$62,MATCH(23-COUNTIFS('New Tooling Jobs'!A$13:A$62,"<>",'New Tooling Jobs'!E$13:E$62,"<>Completed"),Reorders!AC$13:AC$62,0))),"") | F32: =IFERROR(IF(23<=COUNTIFS('New Tooling Jobs'!A$13:A$62,"<>",'New Tooling Jobs'!E$13:E$62,"<>Completed"),INDEX('New Tooling Jobs'!H$13:H$62,MATCH(23,'New Tooling Jobs'!AG$13:AG$62,0)),INDEX(Reorders!H$13:H$62,MATCH(23-COUNTIFS('New Tooling Jobs'!A$13:A$62,"<>",'New Tooling Jobs'!E$13:E$62,"<>Completed"),Reorders!AC$13:AC$62,0))),"") | G32: =IFERROR(IF(23<=COUNTIFS('New Tooling Jobs'!A$13:A$62,"<>",'New Tooling Jobs'!E$13:E$62,"<>Completed"),INDEX('New Tooling Jobs'!I$13:I$62,MATCH(23,'New Tooling Jobs'!AG$13:AG$62,0)),INDEX(Reorders!I$13:I$62,MATCH(23-COUNTIFS('New Tooling Jobs'!A$13:A$62,"<>",'New Tooling Jobs'!E$13:E$62,"<>Completed"),Reorders!AC$13:AC$62,0))),"")
A33: =IFERROR(IF(24<=COUNTIFS('New Tooling Jobs'!A$13:A$62,"<>",'New Tooling Jobs'!E$13:E$62,"<>Completed"),INDEX('New Tooling Jobs'!A$13:A$62,MATCH(24,'New Tooling Jobs'!AG$13:AG$62,0)),INDEX(Reorders!A$13:A$62,MATCH(24-COUNTIFS('New Tooling Jobs'!A$13:A$62,"<>",'New Tooling Jobs'!E$13:E$62,"<>Completed"),Reorders!AC$13:AC$62,0))),"") | B33: =IFERROR(IF(24<=COUNTIFS('New Tooling Jobs'!A$13:A$62,"<>",'New Tooling Jobs'!E$13:E$62,"<>Completed"),IF(INDEX('New Tooling Jobs'!A$13:A$62,MATCH(24,'New Tooling Jobs'!AG$13:AG$62,0))<>"","New Tooling",""),IF(INDEX(Reorders!A$13:A$62,MATCH(24-COUNTIFS('New Tooling Jobs'!A$13:A$62,"<>",'New Tooling Jobs'!E$13:E$62,"<>Completed"),Reorders!AC$13:AC$62,0))<>"","Reorder","")),"") | C33: =IFERROR(IF(24<=COUNTIFS('New Tooling Jobs'!A$13:A$62,"<>",'New Tooling Jobs'!E$13:E$62,"<>Completed"),INDEX('New Tooling Jobs'!B$13:B$62,MATCH(24,'New Tooling Jobs'!AG$13:AG$62,0)),INDEX(Reorders!B$13:B$62,MATCH(24-COUNTIFS('New Tooling Jobs'!A$13:A$62,"<>",'New Tooling Jobs'!E$13:E$62,"<>Completed"),Reorders!AC$13:AC$62,0))),"") | D33: =IFERROR(IF(24<=COUNTIFS('New Tooling Jobs'!A$13:A$62,"<>",'New Tooling Jobs'!E$13:E$62,"<>Completed"),INDEX('New Tooling Jobs'!E$13:E$62,MATCH(24,'New Tooling Jobs'!AG$13:AG$62,0)),INDEX(Reorders!E$13:E$62,MATCH(24-COUNTIFS('New Tooling Jobs'!A$13:A$62,"<>",'New Tooling Jobs'!E$13:E$62,"<>Completed"),Reorders!AC$13:AC$62,0))),"") | E33: =IFERROR(IF(24<=COUNTIFS('New Tooling Jobs'!A$13:A$62,"<>",'New Tooling Jobs'!E$13:E$62,"<>Completed"),INDEX('New Tooling Jobs'!G$13:G$62,MATCH(24,'New Tooling Jobs'!AG$13:AG$62,0)),INDEX(Reorders!G$13:G$62,MATCH(24-COUNTIFS('New Tooling Jobs'!A$13:A$62,"<>",'New Tooling Jobs'!E$13:E$62,"<>Completed"),Reorders!AC$13:AC$62,0))),"") | F33: =IFERROR(IF(24<=COUNTIFS('New Tooling Jobs'!A$13:A$62,"<>",'New Tooling Jobs'!E$13:E$62,"<>Completed"),INDEX('New Tooling Jobs'!H$13:H$62,MATCH(24,'New Tooling Jobs'!AG$13:AG$62,0)),INDEX(Reorders!H$13:H$62,MATCH(24-COUNTIFS('New Tooling Jobs'!A$13:A$62,"<>",'New Tooling Jobs'!E$13:E$62,"<>Completed"),Reorders!AC$13:AC$62,0))),"") | G33: =IFERROR(IF(24<=COUNTIFS('New Tooling Jobs'!A$13:A$62,"<>",'New Tooling Jobs'!E$13:E$62,"<>Completed"),INDEX('New Tooling Jobs'!I$13:I$62,MATCH(24,'New Tooling Jobs'!AG$13:AG$62,0)),INDEX(Reorders!I$13:I$62,MATCH(24-COUNTIFS('New Tooling Jobs'!A$13:A$62,"<>",'New Tooling Jobs'!E$13:E$62,"<>Completed"),Reorders!AC$13:AC$62,0))),"")
A34: =IFERROR(IF(25<=COUNTIFS('New Tooling Jobs'!A$13:A$62,"<>",'New Tooling Jobs'!E$13:E$62,"<>Completed"),INDEX('New Tooling Jobs'!A$13:A$62,MATCH(25,'New Tooling Jobs'!AG$13:AG$62,0)),INDEX(Reorders!A$13:A$62,MATCH(25-COUNTIFS('New Tooling Jobs'!A$13:A$62,"<>",'New Tooling Jobs'!E$13:E$62,"<>Completed"),Reorders!AC$13:AC$62,0))),"") | B34: =IFERROR(IF(25<=COUNTIFS('New Tooling Jobs'!A$13:A$62,"<>",'New Tooling Jobs'!E$13:E$62,"<>Completed"),IF(INDEX('New Tooling Jobs'!A$13:A$62,MATCH(25,'New Tooling Jobs'!AG$13:AG$62,0))<>"","New Tooling",""),IF(INDEX(Reorders!A$13:A$62,MATCH(25-COUNTIFS('New Tooling Jobs'!A$13:A$62,"<>",'New Tooling Jobs'!E$13:E$62,"<>Completed"),Reorders!AC$13:AC$62,0))<>"","Reorder","")),"") | C34: =IFERROR(IF(25<=COUNTIFS('New Tooling Jobs'!A$13:A$62,"<>",'New Tooling Jobs'!E$13:E$62,"<>Completed"),INDEX('New Tooling Jobs'!B$13:B$62,MATCH(25,'New Tooling Jobs'!AG$13:AG$62,0)),INDEX(Reorders!B$13:B$62,MATCH(25-COUNTIFS('New Tooling Jobs'!A$13:A$62,"<>",'New Tooling Jobs'!E$13:E$62,"<>Completed"),Reorders!AC$13:AC$62,0))),"") | D34: =IFERROR(IF(25<=COUNTIFS('New Tooling Jobs'!A$13:A$62,"<>",'New Tooling Jobs'!E$13:E$62,"<>Completed"),INDEX('New Tooling Jobs'!E$13:E$62,MATCH(25,'New Tooling Jobs'!AG$13:AG$62,0)),INDEX(Reorders!E$13:E$62,MATCH(25-COUNTIFS('New Tooling Jobs'!A$13:A$62,"<>",'New Tooling Jobs'!E$13:E$62,"<>Completed"),Reorders!AC$13:AC$62,0))),"") | E34: =IFERROR(IF(25<=COUNTIFS('New Tooling Jobs'!A$13:A$62,"<>",'New Tooling Jobs'!E$13:E$62,"<>Completed"),INDEX('New Tooling Jobs'!G$13:G$62,MATCH(25,'New Tooling Jobs'!AG$13:AG$62,0)),INDEX(Reorders!G$13:G$62,MATCH(25-COUNTIFS('New Tooling Jobs'!A$13:A$62,"<>",'New Tooling Jobs'!E$13:E$62,"<>Completed"),Reorders!AC$13:AC$62,0))),"") | F34: =IFERROR(IF(25<=COUNTIFS('New Tooling Jobs'!A$13:A$62,"<>",'New Tooling Jobs'!E$13:E$62,"<>Completed"),INDEX('New Tooling Jobs'!H$13:H$62,MATCH(25,'New Tooling Jobs'!AG$13:AG$62,0)),INDEX(Reorders!H$13:H$62,MATCH(25-COUNTIFS('New Tooling Jobs'!A$13:A$62,"<>",'New Tooling Jobs'!E$13:E$62,"<>Completed"),Reorders!AC$13:AC$62,0))),"") | G34: =IFERROR(IF(25<=COUNTIFS('New Tooling Jobs'!A$13:A$62,"<>",'New Tooling Jobs'!E$13:E$62,"<>Completed"),INDEX('New Tooling Jobs'!I$13:I$62,MATCH(25,'New Tooling Jobs'!AG$13:AG$62,0)),INDEX(Reorders!I$13:I$62,MATCH(25-COUNTIFS('New Tooling Jobs'!A$13:A$62,"<>",'New Tooling Jobs'!E$13:E$62,"<>Completed"),Reorders!AC$13:AC$62,0))),"")
A35: =IFERROR(IF(26<=COUNTIFS('New Tooling Jobs'!A$13:A$62,"<>",'New Tooling Jobs'!E$13:E$62,"<>Completed"),INDEX('New Tooling Jobs'!A$13:A$62,MATCH(26,'New Tooling Jobs'!AG$13:AG$62,0)),INDEX(Reorders!A$13:A$62,MATCH(26-COUNTIFS('New Tooling Jobs'!A$13:A$62,"<>",'New Tooling Jobs'!E$13:E$62,"<>Completed"),Reorders!AC$13:AC$62,0))),"") | B35: =IFERROR(IF(26<=COUNTIFS('New Tooling Jobs'!A$13:A$62,"<>",'New Tooling Jobs'!E$13:E$62,"<>Completed"),IF(INDEX('New Tooling Jobs'!A$13:A$62,MATCH(26,'New Tooling Jobs'!AG$13:AG$62,0))<>"","New Tooling",""),IF(INDEX(Reorders!A$13:A$62,MATCH(26-COUNTIFS('New Tooling Jobs'!A$13:A$62,"<>",'New Tooling Jobs'!E$13:E$62,"<>Completed"),Reorders!AC$13:AC$62,0))<>"","Reorder","")),"") | C35: =IFERROR(IF(26<=COUNTIFS('New Tooling Jobs'!A$13:A$62,"<>",'New Tooling Jobs'!E$13:E$62,"<>Completed"),INDEX('New Tooling Jobs'!B$13:B$62,MATCH(26,'New Tooling Jobs'!AG$13:AG$62,0)),INDEX(Reorders!B$13:B$62,MATCH(26-COUNTIFS('New Tooling Jobs'!A$13:A$62,"<>",'New Tooling Jobs'!E$13:E$62,"<>Completed"),Reorders!AC$13:AC$62,0))),"") | D35: =IFERROR(IF(26<=COUNTIFS('New Tooling Jobs'!A$13:A$62,"<>",'New Tooling Jobs'!E$13:E$62,"<>Completed"),INDEX('New Tooling Jobs'!E$13:E$62,MATCH(26,'New Tooling Jobs'!AG$13:AG$62,0)),INDEX(Reorders!E$13:E$62,MATCH(26-COUNTIFS('New Tooling Jobs'!A$13:A$62,"<>",'New Tooling Jobs'!E$13:E$62,"<>Completed"),Reorders!AC$13:AC$62,0))),"") | E35: =IFERROR(IF(26<=COUNTIFS('New Tooling Jobs'!A$13:A$62,"<>",'New Tooling Jobs'!E$13:E$62,"<>Completed"),INDEX('New Tooling Jobs'!G$13:G$62,MATCH(26,'New Tooling Jobs'!AG$13:AG$62,0)),INDEX(Reorders!G$13:G$62,MATCH(26-COUNTIFS('New Tooling Jobs'!A$13:A$62,"<>",'New Tooling Jobs'!E$13:E$62,"<>Completed"),Reorders!AC$13:AC$62,0))),"") | F35: =IFERROR(IF(26<=COUNTIFS('New Tooling Jobs'!A$13:A$62,"<>",'New Tooling Jobs'!E$13:E$62,"<>Completed"),INDEX('New Tooling Jobs'!H$13:H$62,MATCH(26,'New Tooling Jobs'!AG$13:AG$62,0)),INDEX(Reorders!H$13:H$62,MATCH(26-COUNTIFS('New Tooling Jobs'!A$13:A$62,"<>",'New Tooling Jobs'!E$13:E$62,"<>Completed"),Reorders!AC$13:AC$62,0))),"") | G35: =IFERROR(IF(26<=COUNTIFS('New Tooling Jobs'!A$13:A$62,"<>",'New Tooling Jobs'!E$13:E$62,"<>Completed"),INDEX('New Tooling Jobs'!I$13:I$62,MATCH(26,'New Tooling Jobs'!AG$13:AG$62,0)),INDEX(Reorders!I$13:I$62,MATCH(26-COUNTIFS('New Tooling Jobs'!A$13:A$62,"<>",'New Tooling Jobs'!E$13:E$62,"<>Completed"),Reorders!AC$13:AC$62,0))),"")
A36: =IFERROR(IF(27<=COUNTIFS('New Tooling Jobs'!A$13:A$62,"<>",'New Tooling Jobs'!E$13:E$62,"<>Completed"),INDEX('New Tooling Jobs'!A$13:A$62,MATCH(27,'New Tooling Jobs'!AG$13:AG$62,0)),INDEX(Reorders!A$13:A$62,MATCH(27-COUNTIFS('New Tooling Jobs'!A$13:A$62,"<>",'New Tooling Jobs'!E$13:E$62,"<>Completed"),Reorders!AC$13:AC$62,0))),"") | B36: =IFERROR(IF(27<=COUNTIFS('New Tooling Jobs'!A$13:A$62,"<>",'New Tooling Jobs'!E$13:E$62,"<>Completed"),IF(INDEX('New Tooling Jobs'!A$13:A$62,MATCH(27,'New Tooling Jobs'!AG$13:AG$62,0))<>"","New Tooling",""),IF(INDEX(Reorders!A$13:A$62,MATCH(27-COUNTIFS('New Tooling Jobs'!A$13:A$62,"<>",'New Tooling Jobs'!E$13:E$62,"<>Completed"),Reorders!AC$13:AC$62,0))<>"","Reorder","")),"") | C36: =IFERROR(IF(27<=COUNTIFS('New Tooling Jobs'!A$13:A$62,"<>",'New Tooling Jobs'!E$13:E$62,"<>Completed"),INDEX('New Tooling Jobs'!B$13:B$62,MATCH(27,'New Tooling Jobs'!AG$13:AG$62,0)),INDEX(Reorders!B$13:B$62,MATCH(27-COUNTIFS('New Tooling Jobs'!A$13:A$62,"<>",'New Tooling Jobs'!E$13:E$62,"<>Completed"),Reorders!AC$13:AC$62,0))),"") | D36: =IFERROR(IF(27<=COUNTIFS('New Tooling Jobs'!A$13:A$62,"<>",'New Tooling Jobs'!E$13:E$62,"<>Completed"),INDEX('New Tooling Jobs'!E$13:E$62,MATCH(27,'New Tooling Jobs'!AG$13:AG$62,0)),INDEX(Reorders!E$13:E$62,MATCH(27-COUNTIFS('New Tooling Jobs'!A$13:A$62,"<>",'New Tooling Jobs'!E$13:E$62,"<>Completed"),Reorders!AC$13:AC$62,0))),"") | E36: =IFERROR(IF(27<=COUNTIFS('New Tooling Jobs'!A$13:A$62,"<>",'New Tooling Jobs'!E$13:E$62,"<>Completed"),INDEX('New Tooling Jobs'!G$13:G$62,MATCH(27,'New Tooling Jobs'!AG$13:AG$62,0)),INDEX(Reorders!G$13:G$62,MATCH(27-COUNTIFS('New Tooling Jobs'!A$13:A$62,"<>",'New Tooling Jobs'!E$13:E$62,"<>Completed"),Reorders!AC$13:AC$62,0))),"") | F36: =IFERROR(IF(27<=COUNTIFS('New Tooling Jobs'!A$13:A$62,"<>",'New Tooling Jobs'!E$13:E$62,"<>Completed"),INDEX('New Tooling Jobs'!H$13:H$62,MATCH(27,'New Tooling Jobs'!AG$13:AG$62,0)),INDEX(Reorders!H$13:H$62,MATCH(27-COUNTIFS('New Tooling Jobs'!A$13:A$62,"<>",'New Tooling Jobs'!E$13:E$62,"<>Completed"),Reorders!AC$13:AC$62,0))),"") | G36: =IFERROR(IF(27<=COUNTIFS('New Tooling Jobs'!A$13:A$62,"<>",'New Tooling Jobs'!E$13:E$62,"<>Completed"),INDEX('New Tooling Jobs'!I$13:I$62,MATCH(27,'New Tooling Jobs'!AG$13:AG$62,0)),INDEX(Reorders!I$13:I$62,MATCH(27-COUNTIFS('New Tooling Jobs'!A$13:A$62,"<>",'New Tooling Jobs'!E$13:E$62,"<>Completed"),Reorders!AC$13:AC$62,0))),"")
A37: =IFERROR(IF(28<=COUNTIFS('New Tooling Jobs'!A$13:A$62,"<>",'New Tooling Jobs'!E$13:E$62,"<>Completed"),INDEX('New Tooling Jobs'!A$13:A$62,MATCH(28,'New Tooling Jobs'!AG$13:AG$62,0)),INDEX(Reorders!A$13:A$62,MATCH(28-COUNTIFS('New Tooling Jobs'!A$13:A$62,"<>",'New Tooling Jobs'!E$13:E$62,"<>Completed"),Reorders!AC$13:AC$62,0))),"") | B37: =IFERROR(IF(28<=COUNTIFS('New Tooling Jobs'!A$13:A$62,"<>",'New Tooling Jobs'!E$13:E$62,"<>Completed"),IF(INDEX('New Tooling Jobs'!A$13:A$62,MATCH(28,'New Tooling Jobs'!AG$13:AG$62,0))<>"","New Tooling",""),IF(INDEX(Reorders!A$13:A$62,MATCH(28-COUNTIFS('New Tooling Jobs'!A$13:A$62,"<>",'New Tooling Jobs'!E$13:E$62,"<>Completed"),Reorders!AC$13:AC$62,0))<>"","Reorder","")),"") | C37: =IFERROR(IF(28<=COUNTIFS('New Tooling Jobs'!A$13:A$62,"<>",'New Tooling Jobs'!E$13:E$62,"<>Completed"),INDEX('New Tooling Jobs'!B$13:B$62,MATCH(28,'New Tooling Jobs'!AG$13:AG$62,0)),INDEX(Reorders!B$13:B$62,MATCH(28-COUNTIFS('New Tooling Jobs'!A$13:A$62,"<>",'New Tooling Jobs'!E$13:E$62,"<>Completed"),Reorders!AC$13:AC$62,0))),"") | D37: =IFERROR(IF(28<=COUNTIFS('New Tooling Jobs'!A$13:A$62,"<>",'New Tooling Jobs'!E$13:E$62,"<>Completed"),INDEX('New Tooling Jobs'!E$13:E$62,MATCH(28,'New Tooling Jobs'!AG$13:AG$62,0)),INDEX(Reorders!E$13:E$62,MATCH(28-COUNTIFS('New Tooling Jobs'!A$13:A$62,"<>",'New Tooling Jobs'!E$13:E$62,"<>Completed"),Reorders!AC$13:AC$62,0))),"") | E37: =IFERROR(IF(28<=COUNTIFS('New Tooling Jobs'!A$13:A$62,"<>",'New Tooling Jobs'!E$13:E$62,"<>Completed"),INDEX('New Tooling Jobs'!G$13:G$62,MATCH(28,'New Tooling Jobs'!AG$13:AG$62,0)),INDEX(Reorders!G$13:G$62,MATCH(28-COUNTIFS('New Tooling Jobs'!A$13:A$62,"<>",'New Tooling Jobs'!E$13:E$62,"<>Completed"),Reorders!AC$13:AC$62,0))),"") | F37: =IFERROR(IF(28<=COUNTIFS('New Tooling Jobs'!A$13:A$62,"<>",'New Tooling Jobs'!E$13:E$62,"<>Completed"),INDEX('New Tooling Jobs'!H$13:H$62,MATCH(28,'New Tooling Jobs'!AG$13:AG$62,0)),INDEX(Reorders!H$13:H$62,MATCH(28-COUNTIFS('New Tooling Jobs'!A$13:A$62,"<>",'New Tooling Jobs'!E$13:E$62,"<>Completed"),Reorders!AC$13:AC$62,0))),"") | G37: =IFERROR(IF(28<=COUNTIFS('New Tooling Jobs'!A$13:A$62,"<>",'New Tooling Jobs'!E$13:E$62,"<>Completed"),INDEX('New Tooling Jobs'!I$13:I$62,MATCH(28,'New Tooling Jobs'!AG$13:AG$62,0)),INDEX(Reorders!I$13:I$62,MATCH(28-COUNTIFS('New Tooling Jobs'!A$13:A$62,"<>",'New Tooling Jobs'!E$13:E$62,"<>Completed"),Reorders!AC$13:AC$62,0))),"")
A38: =IFERROR(IF(29<=COUNTIFS('New Tooling Jobs'!A$13:A$62,"<>",'New Tooling Jobs'!E$13:E$62,"<>Completed"),INDEX('New Tooling Jobs'!A$13:A$62,MATCH(29,'New Tooling Jobs'!AG$13:AG$62,0)),INDEX(Reorders!A$13:A$62,MATCH(29-COUNTIFS('New Tooling Jobs'!A$13:A$62,"<>",'New Tooling Jobs'!E$13:E$62,"<>Completed"),Reorders!AC$13:AC$62,0))),"") | B38: =IFERROR(IF(29<=COUNTIFS('New Tooling Jobs'!A$13:A$62,"<>",'New Tooling Jobs'!E$13:E$62,"<>Completed"),IF(INDEX('New Tooling Jobs'!A$13:A$62,MATCH(29,'New Tooling Jobs'!AG$13:AG$62,0))<>"","New Tooling",""),IF(INDEX(Reorders!A$13:A$62,MATCH(29-COUNTIFS('New Tooling Jobs'!A$13:A$62,"<>",'New Tooling Jobs'!E$13:E$62,"<>Completed"),Reorders!AC$13:AC$62,0))<>"","Reorder","")),"") | C38: =IFERROR(IF(29<=COUNTIFS('New Tooling Jobs'!A$13:A$62,"<>",'New Tooling Jobs'!E$13:E$62,"<>Completed"),INDEX('New Tooling Jobs'!B$13:B$62,MATCH(29,'New Tooling Jobs'!AG$13:AG$62,0)),INDEX(Reorders!B$13:B$62,MATCH(29-COUNTIFS('New Tooling Jobs'!A$13:A$62,"<>",'New Tooling Jobs'!E$13:E$62,"<>Completed"),Reorders!AC$13:AC$62,0))),"") | D38: =IFERROR(IF(29<=COUNTIFS('New Tooling Jobs'!A$13:A$62,"<>",'New Tooling Jobs'!E$13:E$62,"<>Completed"),INDEX('New Tooling Jobs'!E$13:E$62,MATCH(29,'New Tooling Jobs'!AG$13:AG$62,0)),INDEX(Reorders!E$13:E$62,MATCH(29-COUNTIFS('New Tooling Jobs'!A$13:A$62,"<>",'New Tooling Jobs'!E$13:E$62,"<>Completed"),Reorders!AC$13:AC$62,0))),"") | E38: =IFERROR(IF(29<=COUNTIFS('New Tooling Jobs'!A$13:A$62,"<>",'New Tooling Jobs'!E$13:E$62,"<>Completed"),INDEX('New Tooling Jobs'!G$13:G$62,MATCH(29,'New Tooling Jobs'!AG$13:AG$62,0)),INDEX(Reorders!G$13:G$62,MATCH(29-COUNTIFS('New Tooling Jobs'!A$13:A$62,"<>",'New Tooling Jobs'!E$13:E$62,"<>Completed"),Reorders!AC$13:AC$62,0))),"") | F38: =IFERROR(IF(29<=COUNTIFS('New Tooling Jobs'!A$13:A$62,"<>",'New Tooling Jobs'!E$13:E$62,"<>Completed"),INDEX('New Tooling Jobs'!H$13:H$62,MATCH(29,'New Tooling Jobs'!AG$13:AG$62,0)),INDEX(Reorders!H$13:H$62,MATCH(29-COUNTIFS('New Tooling Jobs'!A$13:A$62,"<>",'New Tooling Jobs'!E$13:E$62,"<>Completed"),Reorders!AC$13:AC$62,0))),"") | G38: =IFERROR(IF(29<=COUNTIFS('New Tooling Jobs'!A$13:A$62,"<>",'New Tooling Jobs'!E$13:E$62,"<>Completed"),INDEX('New Tooling Jobs'!I$13:I$62,MATCH(29,'New Tooling Jobs'!AG$13:AG$62,0)),INDEX(Reorders!I$13:I$62,MATCH(29-COUNTIFS('New Tooling Jobs'!A$13:A$62,"<>",'New Tooling Jobs'!E$13:E$62,"<>Completed"),Reorders!AC$13:AC$62,0))),"")
A39: =IFERROR(IF(30<=COUNTIFS('New Tooling Jobs'!A$13:A$62,"<>",'New Tooling Jobs'!E$13:E$62,"<>Completed"),INDEX('New Tooling Jobs'!A$13:A$62,MATCH(30,'New Tooling Jobs'!AG$13:AG$62,0)),INDEX(Reorders!A$13:A$62,MATCH(30-COUNTIFS('New Tooling Jobs'!A$13:A$62,"<>",'New Tooling Jobs'!E$13:E$62,"<>Completed"),Reorders!AC$13:AC$62,0))),"") | B39: =IFERROR(IF(30<=COUNTIFS('New Tooling Jobs'!A$13:A$62,"<>",'New Tooling Jobs'!E$13:E$62,"<>Completed"),IF(INDEX('New Tooling Jobs'!A$13:A$62,MATCH(30,'New Tooling Jobs'!AG$13:AG$62,0))<>"","New Tooling",""),IF(INDEX(Reorders!A$13:A$62,MATCH(30-COUNTIFS('New Tooling Jobs'!A$13:A$62,"<>",'New Tooling Jobs'!E$13:E$62,"<>Completed"),Reorders!AC$13:AC$62,0))<>"","Reorder","")),"") | C39: =IFERROR(IF(30<=COUNTIFS('New Tooling Jobs'!A$13:A$62,"<>",'New Tooling Jobs'!E$13:E$62,"<>Completed"),INDEX('New Tooling Jobs'!B$13:B$62,MATCH(30,'New Tooling Jobs'!AG$13:AG$62,0)),INDEX(Reorders!B$13:B$62,MATCH(30-COUNTIFS('New Tooling Jobs'!A$13:A$62,"<>",'New Tooling Jobs'!E$13:E$62,"<>Completed"),Reorders!AC$13:AC$62,0))),"") | D39: =IFERROR(IF(30<=COUNTIFS('New Tooling Jobs'!A$13:A$62,"<>",'New Tooling Jobs'!E$13:E$62,"<>Completed"),INDEX('New Tooling Jobs'!E$13:E$62,MATCH(30,'New Tooling Jobs'!AG$13:AG$62,0)),INDEX(Reorders!E$13:E$62,MATCH(30-COUNTIFS('New Tooling Jobs'!A$13:A$62,"<>",'New Tooling Jobs'!E$13:E$62,"<>Completed"),Reorders!AC$13:AC$62,0))),"") | E39: =IFERROR(IF(30<=COUNTIFS('New Tooling Jobs'!A$13:A$62,"<>",'New Tooling Jobs'!E$13:E$62,"<>Completed"),INDEX('New Tooling Jobs'!G$13:G$62,MATCH(30,'New Tooling Jobs'!AG$13:AG$62,0)),INDEX(Reorders!G$13:G$62,MATCH(30-COUNTIFS('New Tooling Jobs'!A$13:A$62,"<>",'New Tooling Jobs'!E$13:E$62,"<>Completed"),Reorders!AC$13:AC$62,0))),"") | F39: =IFERROR(IF(30<=COUNTIFS('New Tooling Jobs'!A$13:A$62,"<>",'New Tooling Jobs'!E$13:E$62,"<>Completed"),INDEX('New Tooling Jobs'!H$13:H$62,MATCH(30,'New Tooling Jobs'!AG$13:AG$62,0)),INDEX(Reorders!H$13:H$62,MATCH(30-COUNTIFS('New Tooling Jobs'!A$13:A$62,"<>",'New Tooling Jobs'!E$13:E$62,"<>Completed"),Reorders!AC$13:AC$62,0))),"") | G39: =IFERROR(IF(30<=COUNTIFS('New Tooling Jobs'!A$13:A$62,"<>",'New Tooling Jobs'!E$13:E$62,"<>Completed"),INDEX('New Tooling Jobs'!I$13:I$62,MATCH(30,'New Tooling Jobs'!AG$13:AG$62,0)),INDEX(Reorders!I$13:I$62,MATCH(30-COUNTIFS('New Tooling Jobs'!A$13:A$62,"<>",'New Tooling Jobs'!E$13:E$62,"<>Completed"),Reorders!AC$13:AC$62,0))),"")
A40: =IFERROR(IF(31<=COUNTIFS('New Tooling Jobs'!A$13:A$62,"<>",'New Tooling Jobs'!E$13:E$62,"<>Completed"),INDEX('New Tooling Jobs'!A$13:A$62,MATCH(31,'New Tooling Jobs'!AG$13:AG$62,0)),INDEX(Reorders!A$13:A$62,MATCH(31-COUNTIFS('New Tooling Jobs'!A$13:A$62,"<>",'New Tooling Jobs'!E$13:E$62,"<>Completed"),Reorders!AC$13:AC$62,0))),"") | B40: =IFERROR(IF(31<=COUNTIFS('New Tooling Jobs'!A$13:A$62,"<>",'New Tooling Jobs'!E$13:E$62,"<>Completed"),IF(INDEX('New Tooling Jobs'!A$13:A$62,MATCH(31,'New Tooling Jobs'!AG$13:AG$62,0))<>"","New Tooling",""),IF(INDEX(Reorders!A$13:A$62,MATCH(31-COUNTIFS('New Tooling Jobs'!A$13:A$62,"<>",'New Tooling Jobs'!E$13:E$62,"<>Completed"),Reorders!AC$13:AC$62,0))<>"","Reorder","")),"") | C40: =IFERROR(IF(31<=COUNTIFS('New Tooling Jobs'!A$13:A$62,"<>",'New Tooling Jobs'!E$13:E$62,"<>Completed"),INDEX('New Tooling Jobs'!B$13:B$62,MATCH(31,'New Tooling Jobs'!AG$13:AG$62,0)),INDEX(Reorders!B$13:B$62,MATCH(31-COUNTIFS('New Tooling Jobs'!A$13:A$62,"<>",'New Tooling Jobs'!E$13:E$62,"<>Completed"),Reorders!AC$13:AC$62,0))),"") | D40: =IFERROR(IF(31<=COUNTIFS('New Tooling Jobs'!A$13:A$62,"<>",'New Tooling Jobs'!E$13:E$62,"<>Completed"),INDEX('New Tooling Jobs'!E$13:E$62,MATCH(31,'New Tooling Jobs'!AG$13:AG$62,0)),INDEX(Reorders!E$13:E$62,MATCH(31-COUNTIFS('New Tooling Jobs'!A$13:A$62,"<>",'New Tooling Jobs'!E$13:E$62,"<>Completed"),Reorders!AC$13:AC$62,0))),"") | E40: =IFERROR(IF(31<=COUNTIFS('New Tooling Jobs'!A$13:A$62,"<>",'New Tooling Jobs'!E$13:E$62,"<>Completed"),INDEX('New Tooling Jobs'!G$13:G$62,MATCH(31,'New Tooling Jobs'!AG$13:AG$62,0)),INDEX(Reorders!G$13:G$62,MATCH(31-COUNTIFS('New Tooling Jobs'!A$13:A$62,"<>",'New Tooling Jobs'!E$13:E$62,"<>Completed"),Reorders!AC$13:AC$62,0))),"") | F40: =IFERROR(IF(31<=COUNTIFS('New Tooling Jobs'!A$13:A$62,"<>",'New Tooling Jobs'!E$13:E$62,"<>Completed"),INDEX('New Tooling Jobs'!H$13:H$62,MATCH(31,'New Tooling Jobs'!AG$13:AG$62,0)),INDEX(Reorders!H$13:H$62,MATCH(31-COUNTIFS('New Tooling Jobs'!A$13:A$62,"<>",'New Tooling Jobs'!E$13:E$62,"<>Completed"),Reorders!AC$13:AC$62,0))),"") | G40: =IFERROR(IF(31<=COUNTIFS('New Tooling Jobs'!A$13:A$62,"<>",'New Tooling Jobs'!E$13:E$62,"<>Completed"),INDEX('New Tooling Jobs'!I$13:I$62,MATCH(31,'New Tooling Jobs'!AG$13:AG$62,0)),INDEX(Reorders!I$13:I$62,MATCH(31-COUNTIFS('New Tooling Jobs'!A$13:A$62,"<>",'New Tooling Jobs'!E$13:E$62,"<>Completed"),Reorders!AC$13:AC$62,0))),"")
A41: =IFERROR(IF(32<=COUNTIFS('New Tooling Jobs'!A$13:A$62,"<>",'New Tooling Jobs'!E$13:E$62,"<>Completed"),INDEX('New Tooling Jobs'!A$13:A$62,MATCH(32,'New Tooling Jobs'!AG$13:AG$62,0)),INDEX(Reorders!A$13:A$62,MATCH(32-COUNTIFS('New Tooling Jobs'!A$13:A$62,"<>",'New Tooling Jobs'!E$13:E$62,"<>Completed"),Reorders!AC$13:AC$62,0))),"") | B41: =IFERROR(IF(32<=COUNTIFS('New Tooling Jobs'!A$13:A$62,"<>",'New Tooling Jobs'!E$13:E$62,"<>Completed"),IF(INDEX('New Tooling Jobs'!A$13:A$62,MATCH(32,'New Tooling Jobs'!AG$13:AG$62,0))<>"","New Tooling",""),IF(INDEX(Reorders!A$13:A$62,MATCH(32-COUNTIFS('New Tooling Jobs'!A$13:A$62,"<>",'New Tooling Jobs'!E$13:E$62,"<>Completed"),Reorders!AC$13:AC$62,0))<>"","Reorder","")),"") | C41: =IFERROR(IF(32<=COUNTIFS('New Tooling Jobs'!A$13:A$62,"<>",'New Tooling Jobs'!E$13:E$62,"<>Completed"),INDEX('New Tooling Jobs'!B$13:B$62,MATCH(32,'New Tooling Jobs'!AG$13:AG$62,0)),INDEX(Reorders!B$13:B$62,MATCH(32-COUNTIFS('New Tooling Jobs'!A$13:A$62,"<>",'New Tooling Jobs'!E$13:E$62,"<>Completed"),Reorders!AC$13:AC$62,0))),"") | D41: =IFERROR(IF(32<=COUNTIFS('New Tooling Jobs'!A$13:A$62,"<>",'New Tooling Jobs'!E$13:E$62,"<>Completed"),INDEX('New Tooling Jobs'!E$13:E$62,MATCH(32,'New Tooling Jobs'!AG$13:AG$62,0)),INDEX(Reorders!E$13:E$62,MATCH(32-COUNTIFS('New Tooling Jobs'!A$13:A$62,"<>",'New Tooling Jobs'!E$13:E$62,"<>Completed"),Reorders!AC$13:AC$62,0))),"") | E41: =IFERROR(IF(32<=COUNTIFS('New Tooling Jobs'!A$13:A$62,"<>",'New Tooling Jobs'!E$13:E$62,"<>Completed"),INDEX('New Tooling Jobs'!G$13:G$62,MATCH(32,'New Tooling Jobs'!AG$13:AG$62,0)),INDEX(Reorders!G$13:G$62,MATCH(32-COUNTIFS('New Tooling Jobs'!A$13:A$62,"<>",'New Tooling Jobs'!E$13:E$62,"<>Completed"),Reorders!AC$13:AC$62,0))),"") | F41: =IFERROR(IF(32<=COUNTIFS('New Tooling Jobs'!A$13:A$62,"<>",'New Tooling Jobs'!E$13:E$62,"<>Completed"),INDEX('New Tooling Jobs'!H$13:H$62,MATCH(32,'New Tooling Jobs'!AG$13:AG$62,0)),INDEX(Reorders!H$13:H$62,MATCH(32-COUNTIFS('New Tooling Jobs'!A$13:A$62,"<>",'New Tooling Jobs'!E$13:E$62,"<>Completed"),Reorders!AC$13:AC$62,0))),"") | G41: =IFERROR(IF(32<=COUNTIFS('New Tooling Jobs'!A$13:A$62,"<>",'New Tooling Jobs'!E$13:E$62,"<>Completed"),INDEX('New Tooling Jobs'!I$13:I$62,MATCH(32,'New Tooling Jobs'!AG$13:AG$62,0)),INDEX(Reorders!I$13:I$62,MATCH(32-COUNTIFS('New Tooling Jobs'!A$13:A$62,"<>",'New Tooling Jobs'!E$13:E$62,"<>Completed"),Reorders!AC$13:AC$62,0))),"")
A42: =IFERROR(IF(33<=COUNTIFS('New Tooling Jobs'!A$13:A$62,"<>",'New Tooling Jobs'!E$13:E$62,"<>Completed"),INDEX('New Tooling Jobs'!A$13:A$62,MATCH(33,'New Tooling Jobs'!AG$13:AG$62,0)),INDEX(Reorders!A$13:A$62,MATCH(33-COUNTIFS('New Tooling Jobs'!A$13:A$62,"<>",'New Tooling Jobs'!E$13:E$62,"<>Completed"),Reorders!AC$13:AC$62,0))),"") | B42: =IFERROR(IF(33<=COUNTIFS('New Tooling Jobs'!A$13:A$62,"<>",'New Tooling Jobs'!E$13:E$62,"<>Completed"),IF(INDEX('New Tooling Jobs'!A$13:A$62,MATCH(33,'New Tooling Jobs'!AG$13:AG$62,0))<>"","New Tooling",""),IF(INDEX(Reorders!A$13:A$62,MATCH(33-COUNTIFS('New Tooling Jobs'!A$13:A$62,"<>",'New Tooling Jobs'!E$13:E$62,"<>Completed"),Reorders!AC$13:AC$62,0))<>"","Reorder","")),"") | C42: =IFERROR(IF(33<=COUNTIFS('New Tooling Jobs'!A$13:A$62,"<>",'New Tooling Jobs'!E$13:E$62,"<>Completed"),INDEX('New Tooling Jobs'!B$13:B$62,MATCH(33,'New Tooling Jobs'!AG$13:AG$62,0)),INDEX(Reorders!B$13:B$62,MATCH(33-COUNTIFS('New Tooling Jobs'!A$13:A$62,"<>",'New Tooling Jobs'!E$13:E$62,"<>Completed"),Reorders!AC$13:AC$62,0))),"") | D42: =IFERROR(IF(33<=COUNTIFS('New Tooling Jobs'!A$13:A$62,"<>",'New Tooling Jobs'!E$13:E$62,"<>Completed"),INDEX('New Tooling Jobs'!E$13:E$62,MATCH(33,'New Tooling Jobs'!AG$13:AG$62,0)),INDEX(Reorders!E$13:E$62,MATCH(33-COUNTIFS('New Tooling Jobs'!A$13:A$62,"<>",'New Tooling Jobs'!E$13:E$62,"<>Completed"),Reorders!AC$13:AC$62,0))),"") | E42: =IFERROR(IF(33<=COUNTIFS('New Tooling Jobs'!A$13:A$62,"<>",'New Tooling Jobs'!E$13:E$62,"<>Completed"),INDEX('New Tooling Jobs'!G$13:G$62,MATCH(33,'New Tooling Jobs'!AG$13:AG$62,0)),INDEX(Reorders!G$13:G$62,MATCH(33-COUNTIFS('New Tooling Jobs'!A$13:A$62,"<>",'New Tooling Jobs'!E$13:E$62,"<>Completed"),Reorders!AC$13:AC$62,0))),"") | F42: =IFERROR(IF(33<=COUNTIFS('New Tooling Jobs'!A$13:A$62,"<>",'New Tooling Jobs'!E$13:E$62,"<>Completed"),INDEX('New Tooling Jobs'!H$13:H$62,MATCH(33,'New Tooling Jobs'!AG$13:AG$62,0)),INDEX(Reorders!H$13:H$62,MATCH(33-COUNTIFS('New Tooling Jobs'!A$13:A$62,"<>",'New Tooling Jobs'!E$13:E$62,"<>Completed"),Reorders!AC$13:AC$62,0))),"") | G42: =IFERROR(IF(33<=COUNTIFS('New Tooling Jobs'!A$13:A$62,"<>",'New Tooling Jobs'!E$13:E$62,"<>Completed"),INDEX('New Tooling Jobs'!I$13:I$62,MATCH(33,'New Tooling Jobs'!AG$13:AG$62,0)),INDEX(Reorders!I$13:I$62,MATCH(33-COUNTIFS('New Tooling Jobs'!A$13:A$62,"<>",'New Tooling Jobs'!E$13:E$62,"<>Completed"),Reorders!AC$13:AC$62,0))),"")
A43: =IFERROR(IF(34<=COUNTIFS('New Tooling Jobs'!A$13:A$62,"<>",'New Tooling Jobs'!E$13:E$62,"<>Completed"),INDEX('New Tooling Jobs'!A$13:A$62,MATCH(34,'New Tooling Jobs'!AG$13:AG$62,0)),INDEX(Reorders!A$13:A$62,MATCH(34-COUNTIFS('New Tooling Jobs'!A$13:A$62,"<>",'New Tooling Jobs'!E$13:E$62,"<>Completed"),Reorders!AC$13:AC$62,0))),"") | B43: =IFERROR(IF(34<=COUNTIFS('New Tooling Jobs'!A$13:A$62,"<>",'New Tooling Jobs'!E$13:E$62,"<>Completed"),IF(INDEX('New Tooling Jobs'!A$13:A$62,MATCH(34,'New Tooling Jobs'!AG$13:AG$62,0))<>"","New Tooling",""),IF(INDEX(Reorders!A$13:A$62,MATCH(34-COUNTIFS('New Tooling Jobs'!A$13:A$62,"<>",'New Tooling Jobs'!E$13:E$62,"<>Completed"),Reorders!AC$13:AC$62,0))<>"","Reorder","")),"") | C43: =IFERROR(IF(34<=COUNTIFS('New Tooling Jobs'!A$13:A$62,"<>",'New Tooling Jobs'!E$13:E$62,"<>Completed"),INDEX('New Tooling Jobs'!B$13:B$62,MATCH(34,'New Tooling Jobs'!AG$13:AG$62,0)),INDEX(Reorders!B$13:B$62,MATCH(34-COUNTIFS('New Tooling Jobs'!A$13:A$62,"<>",'New Tooling Jobs'!E$13:E$62,"<>Completed"),Reorders!AC$13:AC$62,0))),"") | D43: =IFERROR(IF(34<=COUNTIFS('New Tooling Jobs'!A$13:A$62,"<>",'New Tooling Jobs'!E$13:E$62,"<>Completed"),INDEX('New Tooling Jobs'!E$13:E$62,MATCH(34,'New Tooling Jobs'!AG$13:AG$62,0)),INDEX(Reorders!E$13:E$62,MATCH(34-COUNTIFS('New Tooling Jobs'!A$13:A$62,"<>",'New Tooling Jobs'!E$13:E$62,"<>Completed"),Reorders!AC$13:AC$62,0))),"") | E43: =IFERROR(IF(34<=COUNTIFS('New Tooling Jobs'!A$13:A$62,"<>",'New Tooling Jobs'!E$13:E$62,"<>Completed"),INDEX('New Tooling Jobs'!G$13:G$62,MATCH(34,'New Tooling Jobs'!AG$13:AG$62,0)),INDEX(Reorders!G$13:G$62,MATCH(34-COUNTIFS('New Tooling Jobs'!A$13:A$62,"<>",'New Tooling Jobs'!E$13:E$62,"<>Completed"),Reorders!AC$13:AC$62,0))),"") | F43: =IFERROR(IF(34<=COUNTIFS('New Tooling Jobs'!A$13:A$62,"<>",'New Tooling Jobs'!E$13:E$62,"<>Completed"),INDEX('New Tooling Jobs'!H$13:H$62,MATCH(34,'New Tooling Jobs'!AG$13:AG$62,0)),INDEX(Reorders!H$13:H$62,MATCH(34-COUNTIFS('New Tooling Jobs'!A$13:A$62,"<>",'New Tooling Jobs'!E$13:E$62,"<>Completed"),Reorders!AC$13:AC$62,0))),"") | G43: =IFERROR(IF(34<=COUNTIFS('New Tooling Jobs'!A$13:A$62,"<>",'New Tooling Jobs'!E$13:E$62,"<>Completed"),INDEX('New Tooling Jobs'!I$13:I$62,MATCH(34,'New Tooling Jobs'!AG$13:AG$62,0)),INDEX(Reorders!I$13:I$62,MATCH(34-COUNTIFS('New Tooling Jobs'!A$13:A$62,"<>",'New Tooling Jobs'!E$13:E$62,"<>Completed"),Reorders!AC$13:AC$62,0))),"")
A44: =IFERROR(IF(35<=COUNTIFS('New Tooling Jobs'!A$13:A$62,"<>",'New Tooling Jobs'!E$13:E$62,"<>Completed"),INDEX('New Tooling Jobs'!A$13:A$62,MATCH(35,'New Tooling Jobs'!AG$13:AG$62,0)),INDEX(Reorders!A$13:A$62,MATCH(35-COUNTIFS('New Tooling Jobs'!A$13:A$62,"<>",'New Tooling Jobs'!E$13:E$62,"<>Completed"),Reorders!AC$13:AC$62,0))),"") | B44: =IFERROR(IF(35<=COUNTIFS('New Tooling Jobs'!A$13:A$62,"<>",'New Tooling Jobs'!E$13:E$62,"<>Completed"),IF(INDEX('New Tooling Jobs'!A$13:A$62,MATCH(35,'New Tooling Jobs'!AG$13:AG$62,0))<>"","New Tooling",""),IF(INDEX(Reorders!A$13:A$62,MATCH(35-COUNTIFS('New Tooling Jobs'!A$13:A$62,"<>",'New Tooling Jobs'!E$13:E$62,"<>Completed"),Reorders!AC$13:AC$62,0))<>"","Reorder","")),"") | C44: =IFERROR(IF(35<=COUNTIFS('New Tooling Jobs'!A$13:A$62,"<>",'New Tooling Jobs'!E$13:E$62,"<>Completed"),INDEX('New Tooling Jobs'!B$13:B$62,MATCH(35,'New Tooling Jobs'!AG$13:AG$62,0)),INDEX(Reorders!B$13:B$62,MATCH(35-COUNTIFS('New Tooling Jobs'!A$13:A$62,"<>",'New Tooling Jobs'!E$13:E$62,"<>Completed"),Reorders!AC$13:AC$62,0))),"") | D44: =IFERROR(IF(35<=COUNTIFS('New Tooling Jobs'!A$13:A$62,"<>",'New Tooling Jobs'!E$13:E$62,"<>Completed"),INDEX('New Tooling Jobs'!E$13:E$62,MATCH(35,'New Tooling Jobs'!AG$13:AG$62,0)),INDEX(Reorders!E$13:E$62,MATCH(35-COUNTIFS('New Tooling Jobs'!A$13:A$62,"<>",'New Tooling Jobs'!E$13:E$62,"<>Completed"),Reorders!AC$13:AC$62,0))),"") | E44: =IFERROR(IF(35<=COUNTIFS('New Tooling Jobs'!A$13:A$62,"<>",'New Tooling Jobs'!E$13:E$62,"<>Completed"),INDEX('New Tooling Jobs'!G$13:G$62,MATCH(35,'New Tooling Jobs'!AG$13:AG$62,0)),INDEX(Reorders!G$13:G$62,MATCH(35-COUNTIFS('New Tooling Jobs'!A$13:A$62,"<>",'New Tooling Jobs'!E$13:E$62,"<>Completed"),Reorders!AC$13:AC$62,0))),"") | F44: =IFERROR(IF(35<=COUNTIFS('New Tooling Jobs'!A$13:A$62,"<>",'New Tooling Jobs'!E$13:E$62,"<>Completed"),INDEX('New Tooling Jobs'!H$13:H$62,MATCH(35,'New Tooling Jobs'!AG$13:AG$62,0)),INDEX(Reorders!H$13:H$62,MATCH(35-COUNTIFS('New Tooling Jobs'!A$13:A$62,"<>",'New Tooling Jobs'!E$13:E$62,"<>Completed"),Reorders!AC$13:AC$62,0))),"") | G44: =IFERROR(IF(35<=COUNTIFS('New Tooling Jobs'!A$13:A$62,"<>",'New Tooling Jobs'!E$13:E$62,"<>Completed"),INDEX('New Tooling Jobs'!I$13:I$62,MATCH(35,'New Tooling Jobs'!AG$13:AG$62,0)),INDEX(Reorders!I$13:I$62,MATCH(35-COUNTIFS('New Tooling Jobs'!A$13:A$62,"<>",'New Tooling Jobs'!E$13:E$62,"<>Completed"),Reorders!AC$13:AC$62,0))),"")
A45: =IFERROR(IF(36<=COUNTIFS('New Tooling Jobs'!A$13:A$62,"<>",'New Tooling Jobs'!E$13:E$62,"<>Completed"),INDEX('New Tooling Jobs'!A$13:A$62,MATCH(36,'New Tooling Jobs'!AG$13:AG$62,0)),INDEX(Reorders!A$13:A$62,MATCH(36-COUNTIFS('New Tooling Jobs'!A$13:A$62,"<>",'New Tooling Jobs'!E$13:E$62,"<>Completed"),Reorders!AC$13:AC$62,0))),"") | B45: =IFERROR(IF(36<=COUNTIFS('New Tooling Jobs'!A$13:A$62,"<>",'New Tooling Jobs'!E$13:E$62,"<>Completed"),IF(INDEX('New Tooling Jobs'!A$13:A$62,MATCH(36,'New Tooling Jobs'!AG$13:AG$62,0))<>"","New Tooling",""),IF(INDEX(Reorders!A$13:A$62,MATCH(36-COUNTIFS('New Tooling Jobs'!A$13:A$62,"<>",'New Tooling Jobs'!E$13:E$62,"<>Completed"),Reorders!AC$13:AC$62,0))<>"","Reorder","")),"") | C45: =IFERROR(IF(36<=COUNTIFS('New Tooling Jobs'!A$13:A$62,"<>",'New Tooling Jobs'!E$13:E$62,"<>Completed"),INDEX('New Tooling Jobs'!B$13:B$62,MATCH(36,'New Tooling Jobs'!AG$13:AG$62,0)),INDEX(Reorders!B$13:B$62,MATCH(36-COUNTIFS('New Tooling Jobs'!A$13:A$62,"<>",'New Tooling Jobs'!E$13:E$62,"<>Completed"),Reorders!AC$13:AC$62,0))),"") | D45: =IFERROR(IF(36<=COUNTIFS('New Tooling Jobs'!A$13:A$62,"<>",'New Tooling Jobs'!E$13:E$62,"<>Completed"),INDEX('New Tooling Jobs'!E$13:E$62,MATCH(36,'New Tooling Jobs'!AG$13:AG$62,0)),INDEX(Reorders!E$13:E$62,MATCH(36-COUNTIFS('New Tooling Jobs'!A$13:A$62,"<>",'New Tooling Jobs'!E$13:E$62,"<>Completed"),Reorders!AC$13:AC$62,0))),"") | E45: =IFERROR(IF(36<=COUNTIFS('New Tooling Jobs'!A$13:A$62,"<>",'New Tooling Jobs'!E$13:E$62,"<>Completed"),INDEX('New Tooling Jobs'!G$13:G$62,MATCH(36,'New Tooling Jobs'!AG$13:AG$62,0)),INDEX(Reorders!G$13:G$62,MATCH(36-COUNTIFS('New Tooling Jobs'!A$13:A$62,"<>",'New Tooling Jobs'!E$13:E$62,"<>Completed"),Reorders!AC$13:AC$62,0))),"") | F45: =IFERROR(IF(36<=COUNTIFS('New Tooling Jobs'!A$13:A$62,"<>",'New Tooling Jobs'!E$13:E$62,"<>Completed"),INDEX('New Tooling Jobs'!H$13:H$62,MATCH(36,'New Tooling Jobs'!AG$13:AG$62,0)),INDEX(Reorders!H$13:H$62,MATCH(36-COUNTIFS('New Tooling Jobs'!A$13:A$62,"<>",'New Tooling Jobs'!E$13:E$62,"<>Completed"),Reorders!AC$13:AC$62,0))),"") | G45: =IFERROR(IF(36<=COUNTIFS('New Tooling Jobs'!A$13:A$62,"<>",'New Tooling Jobs'!E$13:E$62,"<>Completed"),INDEX('New Tooling Jobs'!I$13:I$62,MATCH(36,'New Tooling Jobs'!AG$13:AG$62,0)),INDEX(Reorders!I$13:I$62,MATCH(36-COUNTIFS('New Tooling Jobs'!A$13:A$62,"<>",'New Tooling Jobs'!E$13:E$62,"<>Completed"),Reorders!AC$13:AC$62,0))),"")
A46: =IFERROR(IF(37<=COUNTIFS('New Tooling Jobs'!A$13:A$62,"<>",'New Tooling Jobs'!E$13:E$62,"<>Completed"),INDEX('New Tooling Jobs'!A$13:A$62,MATCH(37,'New Tooling Jobs'!AG$13:AG$62,0)),INDEX(Reorders!A$13:A$62,MATCH(37-COUNTIFS('New Tooling Jobs'!A$13:A$62,"<>",'New Tooling Jobs'!E$13:E$62,"<>Completed"),Reorders!AC$13:AC$62,0))),"") | B46: =IFERROR(IF(37<=COUNTIFS('New Tooling Jobs'!A$13:A$62,"<>",'New Tooling Jobs'!E$13:E$62,"<>Completed"),IF(INDEX('New Tooling Jobs'!A$13:A$62,MATCH(37,'New Tooling Jobs'!AG$13:AG$62,0))<>"","New Tooling",""),IF(INDEX(Reorders!A$13:A$62,MATCH(37-COUNTIFS('New Tooling Jobs'!A$13:A$62,"<>",'New Tooling Jobs'!E$13:E$62,"<>Completed"),Reorders!AC$13:AC$62,0))<>"","Reorder","")),"") | C46: =IFERROR(IF(37<=COUNTIFS('New Tooling Jobs'!A$13:A$62,"<>",'New Tooling Jobs'!E$13:E$62,"<>Completed"),INDEX('New Tooling Jobs'!B$13:B$62,MATCH(37,'New Tooling Jobs'!AG$13:AG$62,0)),INDEX(Reorders!B$13:B$62,MATCH(37-COUNTIFS('New Tooling Jobs'!A$13:A$62,"<>",'New Tooling Jobs'!E$13:E$62,"<>Completed"),Reorders!AC$13:AC$62,0))),"") | D46: =IFERROR(IF(37<=COUNTIFS('New Tooling Jobs'!A$13:A$62,"<>",'New Tooling Jobs'!E$13:E$62,"<>Completed"),INDEX('New Tooling Jobs'!E$13:E$62,MATCH(37,'New Tooling Jobs'!AG$13:AG$62,0)),INDEX(Reorders!E$13:E$62,MATCH(37-COUNTIFS('New Tooling Jobs'!A$13:A$62,"<>",'New Tooling Jobs'!E$13:E$62,"<>Completed"),Reorders!AC$13:AC$62,0))),"") | E46: =IFERROR(IF(37<=COUNTIFS('New Tooling Jobs'!A$13:A$62,"<>",'New Tooling Jobs'!E$13:E$62,"<>Completed"),INDEX('New Tooling Jobs'!G$13:G$62,MATCH(37,'New Tooling Jobs'!AG$13:AG$62,0)),INDEX(Reorders!G$13:G$62,MATCH(37-COUNTIFS('New Tooling Jobs'!A$13:A$62,"<>",'New Tooling Jobs'!E$13:E$62,"<>Completed"),Reorders!AC$13:AC$62,0))),"") | F46: =IFERROR(IF(37<=COUNTIFS('New Tooling Jobs'!A$13:A$62,"<>",'New Tooling Jobs'!E$13:E$62,"<>Completed"),INDEX('New Tooling Jobs'!H$13:H$62,MATCH(37,'New Tooling Jobs'!AG$13:AG$62,0)),INDEX(Reorders!H$13:H$62,MATCH(37-COUNTIFS('New Tooling Jobs'!A$13:A$62,"<>",'New Tooling Jobs'!E$13:E$62,"<>Completed"),Reorders!AC$13:AC$62,0))),"") | G46: =IFERROR(IF(37<=COUNTIFS('New Tooling Jobs'!A$13:A$62,"<>",'New Tooling Jobs'!E$13:E$62,"<>Completed"),INDEX('New Tooling Jobs'!I$13:I$62,MATCH(37,'New Tooling Jobs'!AG$13:AG$62,0)),INDEX(Reorders!I$13:I$62,MATCH(37-COUNTIFS('New Tooling Jobs'!A$13:A$62,"<>",'New Tooling Jobs'!E$13:E$62,"<>Completed"),Reorders!AC$13:AC$62,0))),"")
A47: =IFERROR(IF(38<=COUNTIFS('New Tooling Jobs'!A$13:A$62,"<>",'New Tooling Jobs'!E$13:E$62,"<>Completed"),INDEX('New Tooling Jobs'!A$13:A$62,MATCH(38,'New Tooling Jobs'!AG$13:AG$62,0)),INDEX(Reorders!A$13:A$62,MATCH(38-COUNTIFS('New Tooling Jobs'!A$13:A$62,"<>",'New Tooling Jobs'!E$13:E$62,"<>Completed"),Reorders!AC$13:AC$62,0))),"") | B47: =IFERROR(IF(38<=COUNTIFS('New Tooling Jobs'!A$13:A$62,"<>",'New Tooling Jobs'!E$13:E$62,"<>Completed"),IF(INDEX('New Tooling Jobs'!A$13:A$62,MATCH(38,'New Tooling Jobs'!AG$13:AG$62,0))<>"","New Tooling",""),IF(INDEX(Reorders!A$13:A$62,MATCH(38-COUNTIFS('New Tooling Jobs'!A$13:A$62,"<>",'New Tooling Jobs'!E$13:E$62,"<>Completed"),Reorders!AC$13:AC$62,0))<>"","Reorder","")),"") | C47: =IFERROR(IF(38<=COUNTIFS('New Tooling Jobs'!A$13:A$62,"<>",'New Tooling Jobs'!E$13:E$62,"<>Completed"),INDEX('New Tooling Jobs'!B$13:B$62,MATCH(38,'New Tooling Jobs'!AG$13:AG$62,0)),INDEX(Reorders!B$13:B$62,MATCH(38-COUNTIFS('New Tooling Jobs'!A$13:A$62,"<>",'New Tooling Jobs'!E$13:E$62,"<>Completed"),Reorders!AC$13:AC$62,0))),"") | D47: =IFERROR(IF(38<=COUNTIFS('New Tooling Jobs'!A$13:A$62,"<>",'New Tooling Jobs'!E$13:E$62,"<>Completed"),INDEX('New Tooling Jobs'!E$13:E$62,MATCH(38,'New Tooling Jobs'!AG$13:AG$62,0)),INDEX(Reorders!E$13:E$62,MATCH(38-COUNTIFS('New Tooling Jobs'!A$13:A$62,"<>",'New Tooling Jobs'!E$13:E$62,"<>Completed"),Reorders!AC$13:AC$62,0))),"") | E47: =IFERROR(IF(38<=COUNTIFS('New Tooling Jobs'!A$13:A$62,"<>",'New Tooling Jobs'!E$13:E$62,"<>Completed"),INDEX('New Tooling Jobs'!G$13:G$62,MATCH(38,'New Tooling Jobs'!AG$13:AG$62,0)),INDEX(Reorders!G$13:G$62,MATCH(38-COUNTIFS('New Tooling Jobs'!A$13:A$62,"<>",'New Tooling Jobs'!E$13:E$62,"<>Completed"),Reorders!AC$13:AC$62,0))),"") | F47: =IFERROR(IF(38<=COUNTIFS('New Tooling Jobs'!A$13:A$62,"<>",'New Tooling Jobs'!E$13:E$62,"<>Completed"),INDEX('New Tooling Jobs'!H$13:H$62,MATCH(38,'New Tooling Jobs'!AG$13:AG$62,0)),INDEX(Reorders!H$13:H$62,MATCH(38-COUNTIFS('New Tooling Jobs'!A$13:A$62,"<>",'New Tooling Jobs'!E$13:E$62,"<>Completed"),Reorders!AC$13:AC$62,0))),"") | G47: =IFERROR(IF(38<=COUNTIFS('New Tooling Jobs'!A$13:A$62,"<>",'New Tooling Jobs'!E$13:E$62,"<>Completed"),INDEX('New Tooling Jobs'!I$13:I$62,MATCH(38,'New Tooling Jobs'!AG$13:AG$62,0)),INDEX(Reorders!I$13:I$62,MATCH(38-COUNTIFS('New Tooling Jobs'!A$13:A$62,"<>",'New Tooling Jobs'!E$13:E$62,"<>Completed"),Reorders!AC$13:AC$62,0))),"")
A48: =IFERROR(IF(39<=COUNTIFS('New Tooling Jobs'!A$13:A$62,"<>",'New Tooling Jobs'!E$13:E$62,"<>Completed"),INDEX('New Tooling Jobs'!A$13:A$62,MATCH(39,'New Tooling Jobs'!AG$13:AG$62,0)),INDEX(Reorders!A$13:A$62,MATCH(39-COUNTIFS('New Tooling Jobs'!A$13:A$62,"<>",'New Tooling Jobs'!E$13:E$62,"<>Completed"),Reorders!AC$13:AC$62,0))),"") | B48: =IFERROR(IF(39<=COUNTIFS('New Tooling Jobs'!A$13:A$62,"<>",'New Tooling Jobs'!E$13:E$62,"<>Completed"),IF(INDEX('New Tooling Jobs'!A$13:A$62,MATCH(39,'New Tooling Jobs'!AG$13:AG$62,0))<>"","New Tooling",""),IF(INDEX(Reorders!A$13:A$62,MATCH(39-COUNTIFS('New Tooling Jobs'!A$13:A$62,"<>",'New Tooling Jobs'!E$13:E$62,"<>Completed"),Reorders!AC$13:AC$62,0))<>"","Reorder","")),"") | C48: =IFERROR(IF(39<=COUNTIFS('New Tooling Jobs'!A$13:A$62,"<>",'New Tooling Jobs'!E$13:E$62,"<>Completed"),INDEX('New Tooling Jobs'!B$13:B$62,MATCH(39,'New Tooling Jobs'!AG$13:AG$62,0)),INDEX(Reorders!B$13:B$62,MATCH(39-COUNTIFS('New Tooling Jobs'!A$13:A$62,"<>",'New Tooling Jobs'!E$13:E$62,"<>Completed"),Reorders!AC$13:AC$62,0))),"") | D48: =IFERROR(IF(39<=COUNTIFS('New Tooling Jobs'!A$13:A$62,"<>",'New Tooling Jobs'!E$13:E$62,"<>Completed"),INDEX('New Tooling Jobs'!E$13:E$62,MATCH(39,'New Tooling Jobs'!AG$13:AG$62,0)),INDEX(Reorders!E$13:E$62,MATCH(39-COUNTIFS('New Tooling Jobs'!A$13:A$62,"<>",'New Tooling Jobs'!E$13:E$62,"<>Completed"),Reorders!AC$13:AC$62,0))),"") | E48: =IFERROR(IF(39<=COUNTIFS('New Tooling Jobs'!A$13:A$62,"<>",'New Tooling Jobs'!E$13:E$62,"<>Completed"),INDEX('New Tooling Jobs'!G$13:G$62,MATCH(39,'New Tooling Jobs'!AG$13:AG$62,0)),INDEX(Reorders!G$13:G$62,MATCH(39-COUNTIFS('New Tooling Jobs'!A$13:A$62,"<>",'New Tooling Jobs'!E$13:E$62,"<>Completed"),Reorders!AC$13:AC$62,0))),"") | F48: =IFERROR(IF(39<=COUNTIFS('New Tooling Jobs'!A$13:A$62,"<>",'New Tooling Jobs'!E$13:E$62,"<>Completed"),INDEX('New Tooling Jobs'!H$13:H$62,MATCH(39,'New Tooling Jobs'!AG$13:AG$62,0)),INDEX(Reorders!H$13:H$62,MATCH(39-COUNTIFS('New Tooling Jobs'!A$13:A$62,"<>",'New Tooling Jobs'!E$13:E$62,"<>Completed"),Reorders!AC$13:AC$62,0))),"") | G48: =IFERROR(IF(39<=COUNTIFS('New Tooling Jobs'!A$13:A$62,"<>",'New Tooling Jobs'!E$13:E$62,"<>Completed"),INDEX('New Tooling Jobs'!I$13:I$62,MATCH(39,'New Tooling Jobs'!AG$13:AG$62,0)),INDEX(Reorders!I$13:I$62,MATCH(39-COUNTIFS('New Tooling Jobs'!A$13:A$62,"<>",'New Tooling Jobs'!E$13:E$62,"<>Completed"),Reorders!AC$13:AC$62,0))),"")
A49: =IFERROR(IF(40<=COUNTIFS('New Tooling Jobs'!A$13:A$62,"<>",'New Tooling Jobs'!E$13:E$62,"<>Completed"),INDEX('New Tooling Jobs'!A$13:A$62,MATCH(40,'New Tooling Jobs'!AG$13:AG$62,0)),INDEX(Reorders!A$13:A$62,MATCH(40-COUNTIFS('New Tooling Jobs'!A$13:A$62,"<>",'New Tooling Jobs'!E$13:E$62,"<>Completed"),Reorders!AC$13:AC$62,0))),"") | B49: =IFERROR(IF(40<=COUNTIFS('New Tooling Jobs'!A$13:A$62,"<>",'New Tooling Jobs'!E$13:E$62,"<>Completed"),IF(INDEX('New Tooling Jobs'!A$13:A$62,MATCH(40,'New Tooling Jobs'!AG$13:AG$62,0))<>"","New Tooling",""),IF(INDEX(Reorders!A$13:A$62,MATCH(40-COUNTIFS('New Tooling Jobs'!A$13:A$62,"<>",'New Tooling Jobs'!E$13:E$62,"<>Completed"),Reorders!AC$13:AC$62,0))<>"","Reorder","")),"") | C49: =IFERROR(IF(40<=COUNTIFS('New Tooling Jobs'!A$13:A$62,"<>",'New Tooling Jobs'!E$13:E$62,"<>Completed"),INDEX('New Tooling Jobs'!B$13:B$62,MATCH(40,'New Tooling Jobs'!AG$13:AG$62,0)),INDEX(Reorders!B$13:B$62,MATCH(40-COUNTIFS('New Tooling Jobs'!A$13:A$62,"<>",'New Tooling Jobs'!E$13:E$62,"<>Completed"),Reorders!AC$13:AC$62,0))),"") | D49: =IFERROR(IF(40<=COUNTIFS('New Tooling Jobs'!A$13:A$62,"<>",'New Tooling Jobs'!E$13:E$62,"<>Completed"),INDEX('New Tooling Jobs'!E$13:E$62,MATCH(40,'New Tooling Jobs'!AG$13:AG$62,0)),INDEX(Reorders!E$13:E$62,MATCH(40-COUNTIFS('New Tooling Jobs'!A$13:A$62,"<>",'New Tooling Jobs'!E$13:E$62,"<>Completed"),Reorders!AC$13:AC$62,0))),"") | E49: =IFERROR(IF(40<=COUNTIFS('New Tooling Jobs'!A$13:A$62,"<>",'New Tooling Jobs'!E$13:E$62,"<>Completed"),INDEX('New Tooling Jobs'!G$13:G$62,MATCH(40,'New Tooling Jobs'!AG$13:AG$62,0)),INDEX(Reorders!G$13:G$62,MATCH(40-COUNTIFS('New Tooling Jobs'!A$13:A$62,"<>",'New Tooling Jobs'!E$13:E$62,"<>Completed"),Reorders!AC$13:AC$62,0))),"") | F49: =IFERROR(IF(40<=COUNTIFS('New Tooling Jobs'!A$13:A$62,"<>",'New Tooling Jobs'!E$13:E$62,"<>Completed"),INDEX('New Tooling Jobs'!H$13:H$62,MATCH(40,'New Tooling Jobs'!AG$13:AG$62,0)),INDEX(Reorders!H$13:H$62,MATCH(40-COUNTIFS('New Tooling Jobs'!A$13:A$62,"<>",'New Tooling Jobs'!E$13:E$62,"<>Completed"),Reorders!AC$13:AC$62,0))),"") | G49: =IFERROR(IF(40<=COUNTIFS('New Tooling Jobs'!A$13:A$62,"<>",'New Tooling Jobs'!E$13:E$62,"<>Completed"),INDEX('New Tooling Jobs'!I$13:I$62,MATCH(40,'New Tooling Jobs'!AG$13:AG$62,0)),INDEX(Reorders!I$13:I$62,MATCH(40-COUNTIFS('New Tooling Jobs'!A$13:A$62,"<>",'New Tooling Jobs'!E$13:E$62,"<>Completed"),Reorders!AC$13:AC$62,0))),"")
A50: =IFERROR(IF(41<=COUNTIFS('New Tooling Jobs'!A$13:A$62,"<>",'New Tooling Jobs'!E$13:E$62,"<>Completed"),INDEX('New Tooling Jobs'!A$13:A$62,MATCH(41,'New Tooling Jobs'!AG$13:AG$62,0)),INDEX(Reorders!A$13:A$62,MATCH(41-COUNTIFS('New Tooling Jobs'!A$13:A$62,"<>",'New Tooling Jobs'!E$13:E$62,"<>Completed"),Reorders!AC$13:AC$62,0))),"") | B50: =IFERROR(IF(41<=COUNTIFS('New Tooling Jobs'!A$13:A$62,"<>",'New Tooling Jobs'!E$13:E$62,"<>Completed"),IF(INDEX('New Tooling Jobs'!A$13:A$62,MATCH(41,'New Tooling Jobs'!AG$13:AG$62,0))<>"","New Tooling",""),IF(INDEX(Reorders!A$13:A$62,MATCH(41-COUNTIFS('New Tooling Jobs'!A$13:A$62,"<>",'New Tooling Jobs'!E$13:E$62,"<>Completed"),Reorders!AC$13:AC$62,0))<>"","Reorder","")),"") | C50: =IFERROR(IF(41<=COUNTIFS('New Tooling Jobs'!A$13:A$62,"<>",'New Tooling Jobs'!E$13:E$62,"<>Completed"),INDEX('New Tooling Jobs'!B$13:B$62,MATCH(41,'New Tooling Jobs'!AG$13:AG$62,0)),INDEX(Reorders!B$13:B$62,MATCH(41-COUNTIFS('New Tooling Jobs'!A$13:A$62,"<>",'New Tooling Jobs'!E$13:E$62,"<>Completed"),Reorders!AC$13:AC$62,0))),"") | D50: =IFERROR(IF(41<=COUNTIFS('New Tooling Jobs'!A$13:A$62,"<>",'New Tooling Jobs'!E$13:E$62,"<>Completed"),INDEX('New Tooling Jobs'!E$13:E$62,MATCH(41,'New Tooling Jobs'!AG$13:AG$62,0)),INDEX(Reorders!E$13:E$62,MATCH(41-COUNTIFS('New Tooling Jobs'!A$13:A$62,"<>",'New Tooling Jobs'!E$13:E$62,"<>Completed"),Reorders!AC$13:AC$62,0))),"") | E50: =IFERROR(IF(41<=COUNTIFS('New Tooling Jobs'!A$13:A$62,"<>",'New Tooling Jobs'!E$13:E$62,"<>Completed"),INDEX('New Tooling Jobs'!G$13:G$62,MATCH(41,'New Tooling Jobs'!AG$13:AG$62,0)),INDEX(Reorders!G$13:G$62,MATCH(41-COUNTIFS('New Tooling Jobs'!A$13:A$62,"<>",'New Tooling Jobs'!E$13:E$62,"<>Completed"),Reorders!AC$13:AC$62,0))),"") | F50: =IFERROR(IF(41<=COUNTIFS('New Tooling Jobs'!A$13:A$62,"<>",'New Tooling Jobs'!E$13:E$62,"<>Completed"),INDEX('New Tooling Jobs'!H$13:H$62,MATCH(41,'New Tooling Jobs'!AG$13:AG$62,0)),INDEX(Reorders!H$13:H$62,MATCH(41-COUNTIFS('New Tooling Jobs'!A$13:A$62,"<>",'New Tooling Jobs'!E$13:E$62,"<>Completed"),Reorders!AC$13:AC$62,0))),"") | G50: =IFERROR(IF(41<=COUNTIFS('New Tooling Jobs'!A$13:A$62,"<>",'New Tooling Jobs'!E$13:E$62,"<>Completed"),INDEX('New Tooling Jobs'!I$13:I$62,MATCH(41,'New Tooling Jobs'!AG$13:AG$62,0)),INDEX(Reorders!I$13:I$62,MATCH(41-COUNTIFS('New Tooling Jobs'!A$13:A$62,"<>",'New Tooling Jobs'!E$13:E$62,"<>Completed"),Reorders!AC$13:AC$62,0))),"")
A51: =IFERROR(IF(42<=COUNTIFS('New Tooling Jobs'!A$13:A$62,"<>",'New Tooling Jobs'!E$13:E$62,"<>Completed"),INDEX('New Tooling Jobs'!A$13:A$62,MATCH(42,'New Tooling Jobs'!AG$13:AG$62,0)),INDEX(Reorders!A$13:A$62,MATCH(42-COUNTIFS('New Tooling Jobs'!A$13:A$62,"<>",'New Tooling Jobs'!E$13:E$62,"<>Completed"),Reorders!AC$13:AC$62,0))),"") | B51: =IFERROR(IF(42<=COUNTIFS('New Tooling Jobs'!A$13:A$62,"<>",'New Tooling Jobs'!E$13:E$62,"<>Completed"),IF(INDEX('New Tooling Jobs'!A$13:A$62,MATCH(42,'New Tooling Jobs'!AG$13:AG$62,0))<>"","New Tooling",""),IF(INDEX(Reorders!A$13:A$62,MATCH(42-COUNTIFS('New Tooling Jobs'!A$13:A$62,"<>",'New Tooling Jobs'!E$13:E$62,"<>Completed"),Reorders!AC$13:AC$62,0))<>"","Reorder","")),"") | C51: =IFERROR(IF(42<=COUNTIFS('New Tooling Jobs'!A$13:A$62,"<>",'New Tooling Jobs'!E$13:E$62,"<>Completed"),INDEX('New Tooling Jobs'!B$13:B$62,MATCH(42,'New Tooling Jobs'!AG$13:AG$62,0)),INDEX(Reorders!B$13:B$62,MATCH(42-COUNTIFS('New Tooling Jobs'!A$13:A$62,"<>",'New Tooling Jobs'!E$13:E$62,"<>Completed"),Reorders!AC$13:AC$62,0))),"") | D51: =IFERROR(IF(42<=COUNTIFS('New Tooling Jobs'!A$13:A$62,"<>",'New Tooling Jobs'!E$13:E$62,"<>Completed"),INDEX('New Tooling Jobs'!E$13:E$62,MATCH(42,'New Tooling Jobs'!AG$13:AG$62,0)),INDEX(Reorders!E$13:E$62,MATCH(42-COUNTIFS('New Tooling Jobs'!A$13:A$62,"<>",'New Tooling Jobs'!E$13:E$62,"<>Completed"),Reorders!AC$13:AC$62,0))),"") | E51: =IFERROR(IF(42<=COUNTIFS('New Tooling Jobs'!A$13:A$62,"<>",'New Tooling Jobs'!E$13:E$62,"<>Completed"),INDEX('New Tooling Jobs'!G$13:G$62,MATCH(42,'New Tooling Jobs'!AG$13:AG$62,0)),INDEX(Reorders!G$13:G$62,MATCH(42-COUNTIFS('New Tooling Jobs'!A$13:A$62,"<>",'New Tooling Jobs'!E$13:E$62,"<>Completed"),Reorders!AC$13:AC$62,0))),"") | F51: =IFERROR(IF(42<=COUNTIFS('New Tooling Jobs'!A$13:A$62,"<>",'New Tooling Jobs'!E$13:E$62,"<>Completed"),INDEX('New Tooling Jobs'!H$13:H$62,MATCH(42,'New Tooling Jobs'!AG$13:AG$62,0)),INDEX(Reorders!H$13:H$62,MATCH(42-COUNTIFS('New Tooling Jobs'!A$13:A$62,"<>",'New Tooling Jobs'!E$13:E$62,"<>Completed"),Reorders!AC$13:AC$62,0))),"") | G51: =IFERROR(IF(42<=COUNTIFS('New Tooling Jobs'!A$13:A$62,"<>",'New Tooling Jobs'!E$13:E$62,"<>Completed"),INDEX('New Tooling Jobs'!I$13:I$62,MATCH(42,'New Tooling Jobs'!AG$13:AG$62,0)),INDEX(Reorders!I$13:I$62,MATCH(42-COUNTIFS('New Tooling Jobs'!A$13:A$62,"<>",'New Tooling Jobs'!E$13:E$62,"<>Completed"),Reorders!AC$13:AC$62,0))),"")
A52: =IFERROR(IF(43<=COUNTIFS('New Tooling Jobs'!A$13:A$62,"<>",'New Tooling Jobs'!E$13:E$62,"<>Completed"),INDEX('New Tooling Jobs'!A$13:A$62,MATCH(43,'New Tooling Jobs'!AG$13:AG$62,0)),INDEX(Reorders!A$13:A$62,MATCH(43-COUNTIFS('New Tooling Jobs'!A$13:A$62,"<>",'New Tooling Jobs'!E$13:E$62,"<>Completed"),Reorders!AC$13:AC$62,0))),"") | B52: =IFERROR(IF(43<=COUNTIFS('New Tooling Jobs'!A$13:A$62,"<>",'New Tooling Jobs'!E$13:E$62,"<>Completed"),IF(INDEX('New Tooling Jobs'!A$13:A$62,MATCH(43,'New Tooling Jobs'!AG$13:AG$62,0))<>"","New Tooling",""),IF(INDEX(Reorders!A$13:A$62,MATCH(43-COUNTIFS('New Tooling Jobs'!A$13:A$62,"<>",'New Tooling Jobs'!E$13:E$62,"<>Completed"),Reorders!AC$13:AC$62,0))<>"","Reorder","")),"") | C52: =IFERROR(IF(43<=COUNTIFS('New Tooling Jobs'!A$13:A$62,"<>",'New Tooling Jobs'!E$13:E$62,"<>Completed"),INDEX('New Tooling Jobs'!B$13:B$62,MATCH(43,'New Tooling Jobs'!AG$13:AG$62,0)),INDEX(Reorders!B$13:B$62,MATCH(43-COUNTIFS('New Tooling Jobs'!A$13:A$62,"<>",'New Tooling Jobs'!E$13:E$62,"<>Completed"),Reorders!AC$13:AC$62,0))),"") | D52: =IFERROR(IF(43<=COUNTIFS('New Tooling Jobs'!A$13:A$62,"<>",'New Tooling Jobs'!E$13:E$62,"<>Completed"),INDEX('New Tooling Jobs'!E$13:E$62,MATCH(43,'New Tooling Jobs'!AG$13:AG$62,0)),INDEX(Reorders!E$13:E$62,MATCH(43-COUNTIFS('New Tooling Jobs'!A$13:A$62,"<>",'New Tooling Jobs'!E$13:E$62,"<>Completed"),Reorders!AC$13:AC$62,0))),"") | E52: =IFERROR(IF(43<=COUNTIFS('New Tooling Jobs'!A$13:A$62,"<>",'New Tooling Jobs'!E$13:E$62,"<>Completed"),INDEX('New Tooling Jobs'!G$13:G$62,MATCH(43,'New Tooling Jobs'!AG$13:AG$62,0)),INDEX(Reorders!G$13:G$62,MATCH(43-COUNTIFS('New Tooling Jobs'!A$13:A$62,"<>",'New Tooling Jobs'!E$13:E$62,"<>Completed"),Reorders!AC$13:AC$62,0))),"") | F52: =IFERROR(IF(43<=COUNTIFS('New Tooling Jobs'!A$13:A$62,"<>",'New Tooling Jobs'!E$13:E$62,"<>Completed"),INDEX('New Tooling Jobs'!H$13:H$62,MATCH(43,'New Tooling Jobs'!AG$13:AG$62,0)),INDEX(Reorders!H$13:H$62,MATCH(43-COUNTIFS('New Tooling Jobs'!A$13:A$62,"<>",'New Tooling Jobs'!E$13:E$62,"<>Completed"),Reorders!AC$13:AC$62,0))),"") | G52: =IFERROR(IF(43<=COUNTIFS('New Tooling Jobs'!A$13:A$62,"<>",'New Tooling Jobs'!E$13:E$62,"<>Completed"),INDEX('New Tooling Jobs'!I$13:I$62,MATCH(43,'New Tooling Jobs'!AG$13:AG$62,0)),INDEX(Reorders!I$13:I$62,MATCH(43-COUNTIFS('New Tooling Jobs'!A$13:A$62,"<>",'New Tooling Jobs'!E$13:E$62,"<>Completed"),Reorders!AC$13:AC$62,0))),"")
A53: =IFERROR(IF(44<=COUNTIFS('New Tooling Jobs'!A$13:A$62,"<>",'New Tooling Jobs'!E$13:E$62,"<>Completed"),INDEX('New Tooling Jobs'!A$13:A$62,MATCH(44,'New Tooling Jobs'!AG$13:AG$62,0)),INDEX(Reorders!A$13:A$62,MATCH(44-COUNTIFS('New Tooling Jobs'!A$13:A$62,"<>",'New Tooling Jobs'!E$13:E$62,"<>Completed"),Reorders!AC$13:AC$62,0))),"") | B53: =IFERROR(IF(44<=COUNTIFS('New Tooling Jobs'!A$13:A$62,"<>",'New Tooling Jobs'!E$13:E$62,"<>Completed"),IF(INDEX('New Tooling Jobs'!A$13:A$62,MATCH(44,'New Tooling Jobs'!AG$13:AG$62,0))<>"","New Tooling",""),IF(INDEX(Reorders!A$13:A$62,MATCH(44-COUNTIFS('New Tooling Jobs'!A$13:A$62,"<>",'New Tooling Jobs'!E$13:E$62,"<>Completed"),Reorders!AC$13:AC$62,0))<>"","Reorder","")),"") | C53: =IFERROR(IF(44<=COUNTIFS('New Tooling Jobs'!A$13:A$62,"<>",'New Tooling Jobs'!E$13:E$62,"<>Completed"),INDEX('New Tooling Jobs'!B$13:B$62,MATCH(44,'New Tooling Jobs'!AG$13:AG$62,0)),INDEX(Reorders!B$13:B$62,MATCH(44-COUNTIFS('New Tooling Jobs'!A$13:A$62,"<>",'New Tooling Jobs'!E$13:E$62,"<>Completed"),Reorders!AC$13:AC$62,0))),"") | D53: =IFERROR(IF(44<=COUNTIFS('New Tooling Jobs'!A$13:A$62,"<>",'New Tooling Jobs'!E$13:E$62,"<>Completed"),INDEX('New Tooling Jobs'!E$13:E$62,MATCH(44,'New Tooling Jobs'!AG$13:AG$62,0)),INDEX(Reorders!E$13:E$62,MATCH(44-COUNTIFS('New Tooling Jobs'!A$13:A$62,"<>",'New Tooling Jobs'!E$13:E$62,"<>Completed"),Reorders!AC$13:AC$62,0))),"") | E53: =IFERROR(IF(44<=COUNTIFS('New Tooling Jobs'!A$13:A$62,"<>",'New Tooling Jobs'!E$13:E$62,"<>Completed"),INDEX('New Tooling Jobs'!G$13:G$62,MATCH(44,'New Tooling Jobs'!AG$13:AG$62,0)),INDEX(Reorders!G$13:G$62,MATCH(44-COUNTIFS('New Tooling Jobs'!A$13:A$62,"<>",'New Tooling Jobs'!E$13:E$62,"<>Completed"),Reorders!AC$13:AC$62,0))),"") | F53: =IFERROR(IF(44<=COUNTIFS('New Tooling Jobs'!A$13:A$62,"<>",'New Tooling Jobs'!E$13:E$62,"<>Completed"),INDEX('New Tooling Jobs'!H$13:H$62,MATCH(44,'New Tooling Jobs'!AG$13:AG$62,0)),INDEX(Reorders!H$13:H$62,MATCH(44-COUNTIFS('New Tooling Jobs'!A$13:A$62,"<>",'New Tooling Jobs'!E$13:E$62,"<>Completed"),Reorders!AC$13:AC$62,0))),"") | G53: =IFERROR(IF(44<=COUNTIFS('New Tooling Jobs'!A$13:A$62,"<>",'New Tooling Jobs'!E$13:E$62,"<>Completed"),INDEX('New Tooling Jobs'!I$13:I$62,MATCH(44,'New Tooling Jobs'!AG$13:AG$62,0)),INDEX(Reorders!I$13:I$62,MATCH(44-COUNTIFS('New Tooling Jobs'!A$13:A$62,"<>",'New Tooling Jobs'!E$13:E$62,"<>Completed"),Reorders!AC$13:AC$62,0))),"")
A54: =IFERROR(IF(45<=COUNTIFS('New Tooling Jobs'!A$13:A$62,"<>",'New Tooling Jobs'!E$13:E$62,"<>Completed"),INDEX('New Tooling Jobs'!A$13:A$62,MATCH(45,'New Tooling Jobs'!AG$13:AG$62,0)),INDEX(Reorders!A$13:A$62,MATCH(45-COUNTIFS('New Tooling Jobs'!A$13:A$62,"<>",'New Tooling Jobs'!E$13:E$62,"<>Completed"),Reorders!AC$13:AC$62,0))),"") | B54: =IFERROR(IF(45<=COUNTIFS('New Tooling Jobs'!A$13:A$62,"<>",'New Tooling Jobs'!E$13:E$62,"<>Completed"),IF(INDEX('New Tooling Jobs'!A$13:A$62,MATCH(45,'New Tooling Jobs'!AG$13:AG$62,0))<>"","New Tooling",""),IF(INDEX(Reorders!A$13:A$62,MATCH(45-COUNTIFS('New Tooling Jobs'!A$13:A$62,"<>",'New Tooling Jobs'!E$13:E$62,"<>Completed"),Reorders!AC$13:AC$62,0))<>"","Reorder","")),"") | C54: =IFERROR(IF(45<=COUNTIFS('New Tooling Jobs'!A$13:A$62,"<>",'New Tooling Jobs'!E$13:E$62,"<>Completed"),INDEX('New Tooling Jobs'!B$13:B$62,MATCH(45,'New Tooling Jobs'!AG$13:AG$62,0)),INDEX(Reorders!B$13:B$62,MATCH(45-COUNTIFS('New Tooling Jobs'!A$13:A$62,"<>",'New Tooling Jobs'!E$13:E$62,"<>Completed"),Reorders!AC$13:AC$62,0))),"") | D54: =IFERROR(IF(45<=COUNTIFS('New Tooling Jobs'!A$13:A$62,"<>",'New Tooling Jobs'!E$13:E$62,"<>Completed"),INDEX('New Tooling Jobs'!E$13:E$62,MATCH(45,'New Tooling Jobs'!AG$13:AG$62,0)),INDEX(Reorders!E$13:E$62,MATCH(45-COUNTIFS('New Tooling Jobs'!A$13:A$62,"<>",'New Tooling Jobs'!E$13:E$62,"<>Completed"),Reorders!AC$13:AC$62,0))),"") | E54: =IFERROR(IF(45<=COUNTIFS('New Tooling Jobs'!A$13:A$62,"<>",'New Tooling Jobs'!E$13:E$62,"<>Completed"),INDEX('New Tooling Jobs'!G$13:G$62,MATCH(45,'New Tooling Jobs'!AG$13:AG$62,0)),INDEX(Reorders!G$13:G$62,MATCH(45-COUNTIFS('New Tooling Jobs'!A$13:A$62,"<>",'New Tooling Jobs'!E$13:E$62,"<>Completed"),Reorders!AC$13:AC$62,0))),"") | F54: =IFERROR(IF(45<=COUNTIFS('New Tooling Jobs'!A$13:A$62,"<>",'New Tooling Jobs'!E$13:E$62,"<>Completed"),INDEX('New Tooling Jobs'!H$13:H$62,MATCH(45,'New Tooling Jobs'!AG$13:AG$62,0)),INDEX(Reorders!H$13:H$62,MATCH(45-COUNTIFS('New Tooling Jobs'!A$13:A$62,"<>",'New Tooling Jobs'!E$13:E$62,"<>Completed"),Reorders!AC$13:AC$62,0))),"") | G54: =IFERROR(IF(45<=COUNTIFS('New Tooling Jobs'!A$13:A$62,"<>",'New Tooling Jobs'!E$13:E$62,"<>Completed"),INDEX('New Tooling Jobs'!I$13:I$62,MATCH(45,'New Tooling Jobs'!AG$13:AG$62,0)),INDEX(Reorders!I$13:I$62,MATCH(45-COUNTIFS('New Tooling Jobs'!A$13:A$62,"<>",'New Tooling Jobs'!E$13:E$62,"<>Completed"),Reorders!AC$13:AC$62,0))),"")
A55: =IFERROR(IF(46<=COUNTIFS('New Tooling Jobs'!A$13:A$62,"<>",'New Tooling Jobs'!E$13:E$62,"<>Completed"),INDEX('New Tooling Jobs'!A$13:A$62,MATCH(46,'New Tooling Jobs'!AG$13:AG$62,0)),INDEX(Reorders!A$13:A$62,MATCH(46-COUNTIFS('New Tooling Jobs'!A$13:A$62,"<>",'New Tooling Jobs'!E$13:E$62,"<>Completed"),Reorders!AC$13:AC$62,0))),"") | B55: =IFERROR(IF(46<=COUNTIFS('New Tooling Jobs'!A$13:A$62,"<>",'New Tooling Jobs'!E$13:E$62,"<>Completed"),IF(INDEX('New Tooling Jobs'!A$13:A$62,MATCH(46,'New Tooling Jobs'!AG$13:AG$62,0))<>"","New Tooling",""),IF(INDEX(Reorders!A$13:A$62,MATCH(46-COUNTIFS('New Tooling Jobs'!A$13:A$62,"<>",'New Tooling Jobs'!E$13:E$62,"<>Completed"),Reorders!AC$13:AC$62,0))<>"","Reorder","")),"") | C55: =IFERROR(IF(46<=COUNTIFS('New Tooling Jobs'!A$13:A$62,"<>",'New Tooling Jobs'!E$13:E$62,"<>Completed"),INDEX('New Tooling Jobs'!B$13:B$62,MATCH(46,'New Tooling Jobs'!AG$13:AG$62,0)),INDEX(Reorders!B$13:B$62,MATCH(46-COUNTIFS('New Tooling Jobs'!A$13:A$62,"<>",'New Tooling Jobs'!E$13:E$62,"<>Completed"),Reorders!AC$13:AC$62,0))),"") | D55: =IFERROR(IF(46<=COUNTIFS('New Tooling Jobs'!A$13:A$62,"<>",'New Tooling Jobs'!E$13:E$62,"<>Completed"),INDEX('New Tooling Jobs'!E$13:E$62,MATCH(46,'New Tooling Jobs'!AG$13:AG$62,0)),INDEX(Reorders!E$13:E$62,MATCH(46-COUNTIFS('New Tooling Jobs'!A$13:A$62,"<>",'New Tooling Jobs'!E$13:E$62,"<>Completed"),Reorders!AC$13:AC$62,0))),"") | E55: =IFERROR(IF(46<=COUNTIFS('New Tooling Jobs'!A$13:A$62,"<>",'New Tooling Jobs'!E$13:E$62,"<>Completed"),INDEX('New Tooling Jobs'!G$13:G$62,MATCH(46,'New Tooling Jobs'!AG$13:AG$62,0)),INDEX(Reorders!G$13:G$62,MATCH(46-COUNTIFS('New Tooling Jobs'!A$13:A$62,"<>",'New Tooling Jobs'!E$13:E$62,"<>Completed"),Reorders!AC$13:AC$62,0))),"") | F55: =IFERROR(IF(46<=COUNTIFS('New Tooling Jobs'!A$13:A$62,"<>",'New Tooling Jobs'!E$13:E$62,"<>Completed"),INDEX('New Tooling Jobs'!H$13:H$62,MATCH(46,'New Tooling Jobs'!AG$13:AG$62,0)),INDEX(Reorders!H$13:H$62,MATCH(46-COUNTIFS('New Tooling Jobs'!A$13:A$62,"<>",'New Tooling Jobs'!E$13:E$62,"<>Completed"),Reorders!AC$13:AC$62,0))),"") | G55: =IFERROR(IF(46<=COUNTIFS('New Tooling Jobs'!A$13:A$62,"<>",'New Tooling Jobs'!E$13:E$62,"<>Completed"),INDEX('New Tooling Jobs'!I$13:I$62,MATCH(46,'New Tooling Jobs'!AG$13:AG$62,0)),INDEX(Reorders!I$13:I$62,MATCH(46-COUNTIFS('New Tooling Jobs'!A$13:A$62,"<>",'New Tooling Jobs'!E$13:E$62,"<>Completed"),Reorders!AC$13:AC$62,0))),"")
A56: =IFERROR(IF(47<=COUNTIFS('New Tooling Jobs'!A$13:A$62,"<>",'New Tooling Jobs'!E$13:E$62,"<>Completed"),INDEX('New Tooling Jobs'!A$13:A$62,MATCH(47,'New Tooling Jobs'!AG$13:AG$62,0)),INDEX(Reorders!A$13:A$62,MATCH(47-COUNTIFS('New Tooling Jobs'!A$13:A$62,"<>",'New Tooling Jobs'!E$13:E$62,"<>Completed"),Reorders!AC$13:AC$62,0))),"") | B56: =IFERROR(IF(47<=COUNTIFS('New Tooling Jobs'!A$13:A$62,"<>",'New Tooling Jobs'!E$13:E$62,"<>Completed"),IF(INDEX('New Tooling Jobs'!A$13:A$62,MATCH(47,'New Tooling Jobs'!AG$13:AG$62,0))<>"","New Tooling",""),IF(INDEX(Reorders!A$13:A$62,MATCH(47-COUNTIFS('New Tooling Jobs'!A$13:A$62,"<>",'New Tooling Jobs'!E$13:E$62,"<>Completed"),Reorders!AC$13:AC$62,0))<>"","Reorder","")),"") | C56: =IFERROR(IF(47<=COUNTIFS('New Tooling Jobs'!A$13:A$62,"<>",'New Tooling Jobs'!E$13:E$62,"<>Completed"),INDEX('New Tooling Jobs'!B$13:B$62,MATCH(47,'New Tooling Jobs'!AG$13:AG$62,0)),INDEX(Reorders!B$13:B$62,MATCH(47-COUNTIFS('New Tooling Jobs'!A$13:A$62,"<>",'New Tooling Jobs'!E$13:E$62,"<>Completed"),Reorders!AC$13:AC$62,0))),"") | D56: =IFERROR(IF(47<=COUNTIFS('New Tooling Jobs'!A$13:A$62,"<>",'New Tooling Jobs'!E$13:E$62,"<>Completed"),INDEX('New Tooling Jobs'!E$13:E$62,MATCH(47,'New Tooling Jobs'!AG$13:AG$62,0)),INDEX(Reorders!E$13:E$62,MATCH(47-COUNTIFS('New Tooling Jobs'!A$13:A$62,"<>",'New Tooling Jobs'!E$13:E$62,"<>Completed"),Reorders!AC$13:AC$62,0))),"") | E56: =IFERROR(IF(47<=COUNTIFS('New Tooling Jobs'!A$13:A$62,"<>",'New Tooling Jobs'!E$13:E$62,"<>Completed"),INDEX('New Tooling Jobs'!G$13:G$62,MATCH(47,'New Tooling Jobs'!AG$13:AG$62,0)),INDEX(Reorders!G$13:G$62,MATCH(47-COUNTIFS('New Tooling Jobs'!A$13:A$62,"<>",'New Tooling Jobs'!E$13:E$62,"<>Completed"),Reorders!AC$13:AC$62,0))),"") | F56: =IFERROR(IF(47<=COUNTIFS('New Tooling Jobs'!A$13:A$62,"<>",'New Tooling Jobs'!E$13:E$62,"<>Completed"),INDEX('New Tooling Jobs'!H$13:H$62,MATCH(47,'New Tooling Jobs'!AG$13:AG$62,0)),INDEX(Reorders!H$13:H$62,MATCH(47-COUNTIFS('New Tooling Jobs'!A$13:A$62,"<>",'New Tooling Jobs'!E$13:E$62,"<>Completed"),Reorders!AC$13:AC$62,0))),"") | G56: =IFERROR(IF(47<=COUNTIFS('New Tooling Jobs'!A$13:A$62,"<>",'New Tooling Jobs'!E$13:E$62,"<>Completed"),INDEX('New Tooling Jobs'!I$13:I$62,MATCH(47,'New Tooling Jobs'!AG$13:AG$62,0)),INDEX(Reorders!I$13:I$62,MATCH(47-COUNTIFS('New Tooling Jobs'!A$13:A$62,"<>",'New Tooling Jobs'!E$13:E$62,"<>Completed"),Reorders!AC$13:AC$62,0))),"")
A57: =IFERROR(IF(48<=COUNTIFS('New Tooling Jobs'!A$13:A$62,"<>",'New Tooling Jobs'!E$13:E$62,"<>Completed"),INDEX('New Tooling Jobs'!A$13:A$62,MATCH(48,'New Tooling Jobs'!AG$13:AG$62,0)),INDEX(Reorders!A$13:A$62,MATCH(48-COUNTIFS('New Tooling Jobs'!A$13:A$62,"<>",'New Tooling Jobs'!E$13:E$62,"<>Completed"),Reorders!AC$13:AC$62,0))),"") | B57: =IFERROR(IF(48<=COUNTIFS('New Tooling Jobs'!A$13:A$62,"<>",'New Tooling Jobs'!E$13:E$62,"<>Completed"),IF(INDEX('New Tooling Jobs'!A$13:A$62,MATCH(48,'New Tooling Jobs'!AG$13:AG$62,0))<>"","New Tooling",""),IF(INDEX(Reorders!A$13:A$62,MATCH(48-COUNTIFS('New Tooling Jobs'!A$13:A$62,"<>",'New Tooling Jobs'!E$13:E$62,"<>Completed"),Reorders!AC$13:AC$62,0))<>"","Reorder","")),"") | C57: =IFERROR(IF(48<=COUNTIFS('New Tooling Jobs'!A$13:A$62,"<>",'New Tooling Jobs'!E$13:E$62,"<>Completed"),INDEX('New Tooling Jobs'!B$13:B$62,MATCH(48,'New Tooling Jobs'!AG$13:AG$62,0)),INDEX(Reorders!B$13:B$62,MATCH(48-COUNTIFS('New Tooling Jobs'!A$13:A$62,"<>",'New Tooling Jobs'!E$13:E$62,"<>Completed"),Reorders!AC$13:AC$62,0))),"") | D57: =IFERROR(IF(48<=COUNTIFS('New Tooling Jobs'!A$13:A$62,"<>",'New Tooling Jobs'!E$13:E$62,"<>Completed"),INDEX('New Tooling Jobs'!E$13:E$62,MATCH(48,'New Tooling Jobs'!AG$13:AG$62,0)),INDEX(Reorders!E$13:E$62,MATCH(48-COUNTIFS('New Tooling Jobs'!A$13:A$62,"<>",'New Tooling Jobs'!E$13:E$62,"<>Completed"),Reorders!AC$13:AC$62,0))),"") | E57: =IFERROR(IF(48<=COUNTIFS('New Tooling Jobs'!A$13:A$62,"<>",'New Tooling Jobs'!E$13:E$62,"<>Completed"),INDEX('New Tooling Jobs'!G$13:G$62,MATCH(48,'New Tooling Jobs'!AG$13:AG$62,0)),INDEX(Reorders!G$13:G$62,MATCH(48-COUNTIFS('New Tooling Jobs'!A$13:A$62,"<>",'New Tooling Jobs'!E$13:E$62,"<>Completed"),Reorders!AC$13:AC$62,0))),"") | F57: =IFERROR(IF(48<=COUNTIFS('New Tooling Jobs'!A$13:A$62,"<>",'New Tooling Jobs'!E$13:E$62,"<>Completed"),INDEX('New Tooling Jobs'!H$13:H$62,MATCH(48,'New Tooling Jobs'!AG$13:AG$62,0)),INDEX(Reorders!H$13:H$62,MATCH(48-COUNTIFS('New Tooling Jobs'!A$13:A$62,"<>",'New Tooling Jobs'!E$13:E$62,"<>Completed"),Reorders!AC$13:AC$62,0))),"") | G57: =IFERROR(IF(48<=COUNTIFS('New Tooling Jobs'!A$13:A$62,"<>",'New Tooling Jobs'!E$13:E$62,"<>Completed"),INDEX('New Tooling Jobs'!I$13:I$62,MATCH(48,'New Tooling Jobs'!AG$13:AG$62,0)),INDEX(Reorders!I$13:I$62,MATCH(48-COUNTIFS('New Tooling Jobs'!A$13:A$62,"<>",'New Tooling Jobs'!E$13:E$62,"<>Completed"),Reorders!AC$13:AC$62,0))),"")
A58: =IFERROR(IF(49<=COUNTIFS('New Tooling Jobs'!A$13:A$62,"<>",'New Tooling Jobs'!E$13:E$62,"<>Completed"),INDEX('New Tooling Jobs'!A$13:A$62,MATCH(49,'New Tooling Jobs'!AG$13:AG$62,0)),INDEX(Reorders!A$13:A$62,MATCH(49-COUNTIFS('New Tooling Jobs'!A$13:A$62,"<>",'New Tooling Jobs'!E$13:E$62,"<>Completed"),Reorders!AC$13:AC$62,0))),"") | B58: =IFERROR(IF(49<=COUNTIFS('New Tooling Jobs'!A$13:A$62,"<>",'New Tooling Jobs'!E$13:E$62,"<>Completed"),IF(INDEX('New Tooling Jobs'!A$13:A$62,MATCH(49,'New Tooling Jobs'!AG$13:AG$62,0))<>"","New Tooling",""),IF(INDEX(Reorders!A$13:A$62,MATCH(49-COUNTIFS('New Tooling Jobs'!A$13:A$62,"<>",'New Tooling Jobs'!E$13:E$62,"<>Completed"),Reorders!AC$13:AC$62,0))<>"","Reorder","")),"") | C58: =IFERROR(IF(49<=COUNTIFS('New Tooling Jobs'!A$13:A$62,"<>",'New Tooling Jobs'!E$13:E$62,"<>Completed"),INDEX('New Tooling Jobs'!B$13:B$62,MATCH(49,'New Tooling Jobs'!AG$13:AG$62,0)),INDEX(Reorders!B$13:B$62,MATCH(49-COUNTIFS('New Tooling Jobs'!A$13:A$62,"<>",'New Tooling Jobs'!E$13:E$62,"<>Completed"),Reorders!AC$13:AC$62,0))),"") | D58: =IFERROR(IF(49<=COUNTIFS('New Tooling Jobs'!A$13:A$62,"<>",'New Tooling Jobs'!E$13:E$62,"<>Completed"),INDEX('New Tooling Jobs'!E$13:E$62,MATCH(49,'New Tooling Jobs'!AG$13:AG$62,0)),INDEX(Reorders!E$13:E$62,MATCH(49-COUNTIFS('New Tooling Jobs'!A$13:A$62,"<>",'New Tooling Jobs'!E$13:E$62,"<>Completed"),Reorders!AC$13:AC$62,0))),"") | E58: =IFERROR(IF(49<=COUNTIFS('New Tooling Jobs'!A$13:A$62,"<>",'New Tooling Jobs'!E$13:E$62,"<>Completed"),INDEX('New Tooling Jobs'!G$13:G$62,MATCH(49,'New Tooling Jobs'!AG$13:AG$62,0)),INDEX(Reorders!G$13:G$62,MATCH(49-COUNTIFS('New Tooling Jobs'!A$13:A$62,"<>",'New Tooling Jobs'!E$13:E$62,"<>Completed"),Reorders!AC$13:AC$62,0))),"") | F58: =IFERROR(IF(49<=COUNTIFS('New Tooling Jobs'!A$13:A$62,"<>",'New Tooling Jobs'!E$13:E$62,"<>Completed"),INDEX('New Tooling Jobs'!H$13:H$62,MATCH(49,'New Tooling Jobs'!AG$13:AG$62,0)),INDEX(Reorders!H$13:H$62,MATCH(49-COUNTIFS('New Tooling Jobs'!A$13:A$62,"<>",'New Tooling Jobs'!E$13:E$62,"<>Completed"),Reorders!AC$13:AC$62,0))),"") | G58: =IFERROR(IF(49<=COUNTIFS('New Tooling Jobs'!A$13:A$62,"<>",'New Tooling Jobs'!E$13:E$62,"<>Completed"),INDEX('New Tooling Jobs'!I$13:I$62,MATCH(49,'New Tooling Jobs'!AG$13:AG$62,0)),INDEX(Reorders!I$13:I$62,MATCH(49-COUNTIFS('New Tooling Jobs'!A$13:A$62,"<>",'New Tooling Jobs'!E$13:E$62,"<>Completed"),Reorders!AC$13:AC$62,0))),"")
A59: =IFERROR(IF(50<=COUNTIFS('New Tooling Jobs'!A$13:A$62,"<>",'New Tooling Jobs'!E$13:E$62,"<>Completed"),INDEX('New Tooling Jobs'!A$13:A$62,MATCH(50,'New Tooling Jobs'!AG$13:AG$62,0)),INDEX(Reorders!A$13:A$62,MATCH(50-COUNTIFS('New Tooling Jobs'!A$13:A$62,"<>",'New Tooling Jobs'!E$13:E$62,"<>Completed"),Reorders!AC$13:AC$62,0))),"") | B59: =IFERROR(IF(50<=COUNTIFS('New Tooling Jobs'!A$13:A$62,"<>",'New Tooling Jobs'!E$13:E$62,"<>Completed"),IF(INDEX('New Tooling Jobs'!A$13:A$62,MATCH(50,'New Tooling Jobs'!AG$13:AG$62,0))<>"","New Tooling",""),IF(INDEX(Reorders!A$13:A$62,MATCH(50-COUNTIFS('New Tooling Jobs'!A$13:A$62,"<>",'New Tooling Jobs'!E$13:E$62,"<>Completed"),Reorders!AC$13:AC$62,0))<>"","Reorder","")),"") | C59: =IFERROR(IF(50<=COUNTIFS('New Tooling Jobs'!A$13:A$62,"<>",'New Tooling Jobs'!E$13:E$62,"<>Completed"),INDEX('New Tooling Jobs'!B$13:B$62,MATCH(50,'New Tooling Jobs'!AG$13:AG$62,0)),INDEX(Reorders!B$13:B$62,MATCH(50-COUNTIFS('New Tooling Jobs'!A$13:A$62,"<>",'New Tooling Jobs'!E$13:E$62,"<>Completed"),Reorders!AC$13:AC$62,0))),"") | D59: =IFERROR(IF(50<=COUNTIFS('New Tooling Jobs'!A$13:A$62,"<>",'New Tooling Jobs'!E$13:E$62,"<>Completed"),INDEX('New Tooling Jobs'!E$13:E$62,MATCH(50,'New Tooling Jobs'!AG$13:AG$62,0)),INDEX(Reorders!E$13:E$62,MATCH(50-COUNTIFS('New Tooling Jobs'!A$13:A$62,"<>",'New Tooling Jobs'!E$13:E$62,"<>Completed"),Reorders!AC$13:AC$62,0))),"") | E59: =IFERROR(IF(50<=COUNTIFS('New Tooling Jobs'!A$13:A$62,"<>",'New Tooling Jobs'!E$13:E$62,"<>Completed"),INDEX('New Tooling Jobs'!G$13:G$62,MATCH(50,'New Tooling Jobs'!AG$13:AG$62,0)),INDEX(Reorders!G$13:G$62,MATCH(50-COUNTIFS('New Tooling Jobs'!A$13:A$62,"<>",'New Tooling Jobs'!E$13:E$62,"<>Completed"),Reorders!AC$13:AC$62,0))),"") | F59: =IFERROR(IF(50<=COUNTIFS('New Tooling Jobs'!A$13:A$62,"<>",'New Tooling Jobs'!E$13:E$62,"<>Completed"),INDEX('New Tooling Jobs'!H$13:H$62,MATCH(50,'New Tooling Jobs'!AG$13:AG$62,0)),INDEX(Reorders!H$13:H$62,MATCH(50-COUNTIFS('New Tooling Jobs'!A$13:A$62,"<>",'New Tooling Jobs'!E$13:E$62,"<>Completed"),Reorders!AC$13:AC$62,0))),"") | G59: =IFERROR(IF(50<=COUNTIFS('New Tooling Jobs'!A$13:A$62,"<>",'New Tooling Jobs'!E$13:E$62,"<>Completed"),INDEX('New Tooling Jobs'!I$13:I$62,MATCH(50,'New Tooling Jobs'!AG$13:AG$62,0)),INDEX(Reorders!I$13:I$62,MATCH(50-COUNTIFS('New Tooling Jobs'!A$13:A$62,"<>",'New Tooling Jobs'!E$13:E$62,"<>Completed"),Reorders!AC$13:AC$62,0))),"")
A60: =IFERROR(IF(51<=COUNTIFS('New Tooling Jobs'!A$13:A$62,"<>",'New Tooling Jobs'!E$13:E$62,"<>Completed"),INDEX('New Tooling Jobs'!A$13:A$62,MATCH(51,'New Tooling Jobs'!AG$13:AG$62,0)),INDEX(Reorders!A$13:A$62,MATCH(51-COUNTIFS('New Tooling Jobs'!A$13:A$62,"<>",'New Tooling Jobs'!E$13:E$62,"<>Completed"),Reorders!AC$13:AC$62,0))),"") | B60: =IFERROR(IF(51<=COUNTIFS('New Tooling Jobs'!A$13:A$62,"<>",'New Tooling Jobs'!E$13:E$62,"<>Completed"),IF(INDEX('New Tooling Jobs'!A$13:A$62,MATCH(51,'New Tooling Jobs'!AG$13:AG$62,0))<>"","New Tooling",""),IF(INDEX(Reorders!A$13:A$62,MATCH(51-COUNTIFS('New Tooling Jobs'!A$13:A$62,"<>",'New Tooling Jobs'!E$13:E$62,"<>Completed"),Reorders!AC$13:AC$62,0))<>"","Reorder","")),"") | C60: =IFERROR(IF(51<=COUNTIFS('New Tooling Jobs'!A$13:A$62,"<>",'New Tooling Jobs'!E$13:E$62,"<>Completed"),INDEX('New Tooling Jobs'!B$13:B$62,MATCH(51,'New Tooling Jobs'!AG$13:AG$62,0)),INDEX(Reorders!B$13:B$62,MATCH(51-COUNTIFS('New Tooling Jobs'!A$13:A$62,"<>",'New Tooling Jobs'!E$13:E$62,"<>Completed"),Reorders!AC$13:AC$62,0))),"") | D60: =IFERROR(IF(51<=COUNTIFS('New Tooling Jobs'!A$13:A$62,"<>",'New Tooling Jobs'!E$13:E$62,"<>Completed"),INDEX('New Tooling Jobs'!E$13:E$62,MATCH(51,'New Tooling Jobs'!AG$13:AG$62,0)),INDEX(Reorders!E$13:E$62,MATCH(51-COUNTIFS('New Tooling Jobs'!A$13:A$62,"<>",'New Tooling Jobs'!E$13:E$62,"<>Completed"),Reorders!AC$13:AC$62,0))),"") | E60: =IFERROR(IF(51<=COUNTIFS('New Tooling Jobs'!A$13:A$62,"<>",'New Tooling Jobs'!E$13:E$62,"<>Completed"),INDEX('New Tooling Jobs'!G$13:G$62,MATCH(51,'New Tooling Jobs'!AG$13:AG$62,0)),INDEX(Reorders!G$13:G$62,MATCH(51-COUNTIFS('New Tooling Jobs'!A$13:A$62,"<>",'New Tooling Jobs'!E$13:E$62,"<>Completed"),Reorders!AC$13:AC$62,0))),"") | F60: =IFERROR(IF(51<=COUNTIFS('New Tooling Jobs'!A$13:A$62,"<>",'New Tooling Jobs'!E$13:E$62,"<>Completed"),INDEX('New Tooling Jobs'!H$13:H$62,MATCH(51,'New Tooling Jobs'!AG$13:AG$62,0)),INDEX(Reorders!H$13:H$62,MATCH(51-COUNTIFS('New Tooling Jobs'!A$13:A$62,"<>",'New Tooling Jobs'!E$13:E$62,"<>Completed"),Reorders!AC$13:AC$62,0))),"") | G60: =IFERROR(IF(51<=COUNTIFS('New Tooling Jobs'!A$13:A$62,"<>",'New Tooling Jobs'!E$13:E$62,"<>Completed"),INDEX('New Tooling Jobs'!I$13:I$62,MATCH(51,'New Tooling Jobs'!AG$13:AG$62,0)),INDEX(Reorders!I$13:I$62,MATCH(51-COUNTIFS('New Tooling Jobs'!A$13:A$62,"<>",'New Tooling Jobs'!E$13:E$62,"<>Completed"),Reorders!AC$13:AC$62,0))),"")
A61: =IFERROR(IF(52<=COUNTIFS('New Tooling Jobs'!A$13:A$62,"<>",'New Tooling Jobs'!E$13:E$62,"<>Completed"),INDEX('New Tooling Jobs'!A$13:A$62,MATCH(52,'New Tooling Jobs'!AG$13:AG$62,0)),INDEX(Reorders!A$13:A$62,MATCH(52-COUNTIFS('New Tooling Jobs'!A$13:A$62,"<>",'New Tooling Jobs'!E$13:E$62,"<>Completed"),Reorders!AC$13:AC$62,0))),"") | B61: =IFERROR(IF(52<=COUNTIFS('New Tooling Jobs'!A$13:A$62,"<>",'New Tooling Jobs'!E$13:E$62,"<>Completed"),IF(INDEX('New Tooling Jobs'!A$13:A$62,MATCH(52,'New Tooling Jobs'!AG$13:AG$62,0))<>"","New Tooling",""),IF(INDEX(Reorders!A$13:A$62,MATCH(52-COUNTIFS('New Tooling Jobs'!A$13:A$62,"<>",'New Tooling Jobs'!E$13:E$62,"<>Completed"),Reorders!AC$13:AC$62,0))<>"","Reorder","")),"") | C61: =IFERROR(IF(52<=COUNTIFS('New Tooling Jobs'!A$13:A$62,"<>",'New Tooling Jobs'!E$13:E$62,"<>Completed"),INDEX('New Tooling Jobs'!B$13:B$62,MATCH(52,'New Tooling Jobs'!AG$13:AG$62,0)),INDEX(Reorders!B$13:B$62,MATCH(52-COUNTIFS('New Tooling Jobs'!A$13:A$62,"<>",'New Tooling Jobs'!E$13:E$62,"<>Completed"),Reorders!AC$13:AC$62,0))),"") | D61: =IFERROR(IF(52<=COUNTIFS('New Tooling Jobs'!A$13:A$62,"<>",'New Tooling Jobs'!E$13:E$62,"<>Completed"),INDEX('New Tooling Jobs'!E$13:E$62,MATCH(52,'New Tooling Jobs'!AG$13:AG$62,0)),INDEX(Reorders!E$13:E$62,MATCH(52-COUNTIFS('New Tooling Jobs'!A$13:A$62,"<>",'New Tooling Jobs'!E$13:E$62,"<>Completed"),Reorders!AC$13:AC$62,0))),"") | E61: =IFERROR(IF(52<=COUNTIFS('New Tooling Jobs'!A$13:A$62,"<>",'New Tooling Jobs'!E$13:E$62,"<>Completed"),INDEX('New Tooling Jobs'!G$13:G$62,MATCH(52,'New Tooling Jobs'!AG$13:AG$62,0)),INDEX(Reorders!G$13:G$62,MATCH(52-COUNTIFS('New Tooling Jobs'!A$13:A$62,"<>",'New Tooling Jobs'!E$13:E$62,"<>Completed"),Reorders!AC$13:AC$62,0))),"") | F61: =IFERROR(IF(52<=COUNTIFS('New Tooling Jobs'!A$13:A$62,"<>",'New Tooling Jobs'!E$13:E$62,"<>Completed"),INDEX('New Tooling Jobs'!H$13:H$62,MATCH(52,'New Tooling Jobs'!AG$13:AG$62,0)),INDEX(Reorders!H$13:H$62,MATCH(52-COUNTIFS('New Tooling Jobs'!A$13:A$62,"<>",'New Tooling Jobs'!E$13:E$62,"<>Completed"),Reorders!AC$13:AC$62,0))),"") | G61: =IFERROR(IF(52<=COUNTIFS('New Tooling Jobs'!A$13:A$62,"<>",'New Tooling Jobs'!E$13:E$62,"<>Completed"),INDEX('New Tooling Jobs'!I$13:I$62,MATCH(52,'New Tooling Jobs'!AG$13:AG$62,0)),INDEX(Reorders!I$13:I$62,MATCH(52-COUNTIFS('New Tooling Jobs'!A$13:A$62,"<>",'New Tooling Jobs'!E$13:E$62,"<>Completed"),Reorders!AC$13:AC$62,0))),"")
A62: =IFERROR(IF(53<=COUNTIFS('New Tooling Jobs'!A$13:A$62,"<>",'New Tooling Jobs'!E$13:E$62,"<>Completed"),INDEX('New Tooling Jobs'!A$13:A$62,MATCH(53,'New Tooling Jobs'!AG$13:AG$62,0)),INDEX(Reorders!A$13:A$62,MATCH(53-COUNTIFS('New Tooling Jobs'!A$13:A$62,"<>",'New Tooling Jobs'!E$13:E$62,"<>Completed"),Reorders!AC$13:AC$62,0))),"") | B62: =IFERROR(IF(53<=COUNTIFS('New Tooling Jobs'!A$13:A$62,"<>",'New Tooling Jobs'!E$13:E$62,"<>Completed"),IF(INDEX('New Tooling Jobs'!A$13:A$62,MATCH(53,'New Tooling Jobs'!AG$13:AG$62,0))<>"","New Tooling",""),IF(INDEX(Reorders!A$13:A$62,MATCH(53-COUNTIFS('New Tooling Jobs'!A$13:A$62,"<>",'New Tooling Jobs'!E$13:E$62,"<>Completed"),Reorders!AC$13:AC$62,0))<>"","Reorder","")),"") | C62: =IFERROR(IF(53<=COUNTIFS('New Tooling Jobs'!A$13:A$62,"<>",'New Tooling Jobs'!E$13:E$62,"<>Completed"),INDEX('New Tooling Jobs'!B$13:B$62,MATCH(53,'New Tooling Jobs'!AG$13:AG$62,0)),INDEX(Reorders!B$13:B$62,MATCH(53-COUNTIFS('New Tooling Jobs'!A$13:A$62,"<>",'New Tooling Jobs'!E$13:E$62,"<>Completed"),Reorders!AC$13:AC$62,0))),"") | D62: =IFERROR(IF(53<=COUNTIFS('New Tooling Jobs'!A$13:A$62,"<>",'New Tooling Jobs'!E$13:E$62,"<>Completed"),INDEX('New Tooling Jobs'!E$13:E$62,MATCH(53,'New Tooling Jobs'!AG$13:AG$62,0)),INDEX(Reorders!E$13:E$62,MATCH(53-COUNTIFS('New Tooling Jobs'!A$13:A$62,"<>",'New Tooling Jobs'!E$13:E$62,"<>Completed"),Reorders!AC$13:AC$62,0))),"") | E62: =IFERROR(IF(53<=COUNTIFS('New Tooling Jobs'!A$13:A$62,"<>",'New Tooling Jobs'!E$13:E$62,"<>Completed"),INDEX('New Tooling Jobs'!G$13:G$62,MATCH(53,'New Tooling Jobs'!AG$13:AG$62,0)),INDEX(Reorders!G$13:G$62,MATCH(53-COUNTIFS('New Tooling Jobs'!A$13:A$62,"<>",'New Tooling Jobs'!E$13:E$62,"<>Completed"),Reorders!AC$13:AC$62,0))),"") | F62: =IFERROR(IF(53<=COUNTIFS('New Tooling Jobs'!A$13:A$62,"<>",'New Tooling Jobs'!E$13:E$62,"<>Completed"),INDEX('New Tooling Jobs'!H$13:H$62,MATCH(53,'New Tooling Jobs'!AG$13:AG$62,0)),INDEX(Reorders!H$13:H$62,MATCH(53-COUNTIFS('New Tooling Jobs'!A$13:A$62,"<>",'New Tooling Jobs'!E$13:E$62,"<>Completed"),Reorders!AC$13:AC$62,0))),"") | G62: =IFERROR(IF(53<=COUNTIFS('New Tooling Jobs'!A$13:A$62,"<>",'New Tooling Jobs'!E$13:E$62,"<>Completed"),INDEX('New Tooling Jobs'!I$13:I$62,MATCH(53,'New Tooling Jobs'!AG$13:AG$62,0)),INDEX(Reorders!I$13:I$62,MATCH(53-COUNTIFS('New Tooling Jobs'!A$13:A$62,"<>",'New Tooling Jobs'!E$13:E$62,"<>Completed"),Reorders!AC$13:AC$62,0))),"")
A63: =IFERROR(IF(54<=COUNTIFS('New Tooling Jobs'!A$13:A$62,"<>",'New Tooling Jobs'!E$13:E$62,"<>Completed"),INDEX('New Tooling Jobs'!A$13:A$62,MATCH(54,'New Tooling Jobs'!AG$13:AG$62,0)),INDEX(Reorders!A$13:A$62,MATCH(54-COUNTIFS('New Tooling Jobs'!A$13:A$62,"<>",'New Tooling Jobs'!E$13:E$62,"<>Completed"),Reorders!AC$13:AC$62,0))),"") | B63: =IFERROR(IF(54<=COUNTIFS('New Tooling Jobs'!A$13:A$62,"<>",'New Tooling Jobs'!E$13:E$62,"<>Completed"),IF(INDEX('New Tooling Jobs'!A$13:A$62,MATCH(54,'New Tooling Jobs'!AG$13:AG$62,0))<>"","New Tooling",""),IF(INDEX(Reorders!A$13:A$62,MATCH(54-COUNTIFS('New Tooling Jobs'!A$13:A$62,"<>",'New Tooling Jobs'!E$13:E$62,"<>Completed"),Reorders!AC$13:AC$62,0))<>"","Reorder","")),"") | C63: =IFERROR(IF(54<=COUNTIFS('New Tooling Jobs'!A$13:A$62,"<>",'New Tooling Jobs'!E$13:E$62,"<>Completed"),INDEX('New Tooling Jobs'!B$13:B$62,MATCH(54,'New Tooling Jobs'!AG$13:AG$62,0)),INDEX(Reorders!B$13:B$62,MATCH(54-COUNTIFS('New Tooling Jobs'!A$13:A$62,"<>",'New Tooling Jobs'!E$13:E$62,"<>Completed"),Reorders!AC$13:AC$62,0))),"") | D63: =IFERROR(IF(54<=COUNTIFS('New Tooling Jobs'!A$13:A$62,"<>",'New Tooling Jobs'!E$13:E$62,"<>Completed"),INDEX('New Tooling Jobs'!E$13:E$62,MATCH(54,'New Tooling Jobs'!AG$13:AG$62,0)),INDEX(Reorders!E$13:E$62,MATCH(54-COUNTIFS('New Tooling Jobs'!A$13:A$62,"<>",'New Tooling Jobs'!E$13:E$62,"<>Completed"),Reorders!AC$13:AC$62,0))),"") | E63: =IFERROR(IF(54<=COUNTIFS('New Tooling Jobs'!A$13:A$62,"<>",'New Tooling Jobs'!E$13:E$62,"<>Completed"),INDEX('New Tooling Jobs'!G$13:G$62,MATCH(54,'New Tooling Jobs'!AG$13:AG$62,0)),INDEX(Reorders!G$13:G$62,MATCH(54-COUNTIFS('New Tooling Jobs'!A$13:A$62,"<>",'New Tooling Jobs'!E$13:E$62,"<>Completed"),Reorders!AC$13:AC$62,0))),"") | F63: =IFERROR(IF(54<=COUNTIFS('New Tooling Jobs'!A$13:A$62,"<>",'New Tooling Jobs'!E$13:E$62,"<>Completed"),INDEX('New Tooling Jobs'!H$13:H$62,MATCH(54,'New Tooling Jobs'!AG$13:AG$62,0)),INDEX(Reorders!H$13:H$62,MATCH(54-COUNTIFS('New Tooling Jobs'!A$13:A$62,"<>",'New Tooling Jobs'!E$13:E$62,"<>Completed"),Reorders!AC$13:AC$62,0))),"") | G63: =IFERROR(IF(54<=COUNTIFS('New Tooling Jobs'!A$13:A$62,"<>",'New Tooling Jobs'!E$13:E$62,"<>Completed"),INDEX('New Tooling Jobs'!I$13:I$62,MATCH(54,'New Tooling Jobs'!AG$13:AG$62,0)),INDEX(Reorders!I$13:I$62,MATCH(54-COUNTIFS('New Tooling Jobs'!A$13:A$62,"<>",'New Tooling Jobs'!E$13:E$62,"<>Completed"),Reorders!AC$13:AC$62,0))),"")
A64: =IFERROR(IF(55<=COUNTIFS('New Tooling Jobs'!A$13:A$62,"<>",'New Tooling Jobs'!E$13:E$62,"<>Completed"),INDEX('New Tooling Jobs'!A$13:A$62,MATCH(55,'New Tooling Jobs'!AG$13:AG$62,0)),INDEX(Reorders!A$13:A$62,MATCH(55-COUNTIFS('New Tooling Jobs'!A$13:A$62,"<>",'New Tooling Jobs'!E$13:E$62,"<>Completed"),Reorders!AC$13:AC$62,0))),"") | B64: =IFERROR(IF(55<=COUNTIFS('New Tooling Jobs'!A$13:A$62,"<>",'New Tooling Jobs'!E$13:E$62,"<>Completed"),IF(INDEX('New Tooling Jobs'!A$13:A$62,MATCH(55,'New Tooling Jobs'!AG$13:AG$62,0))<>"","New Tooling",""),IF(INDEX(Reorders!A$13:A$62,MATCH(55-COUNTIFS('New Tooling Jobs'!A$13:A$62,"<>",'New Tooling Jobs'!E$13:E$62,"<>Completed"),Reorders!AC$13:AC$62,0))<>"","Reorder","")),"") | C64: =IFERROR(IF(55<=COUNTIFS('New Tooling Jobs'!A$13:A$62,"<>",'New Tooling Jobs'!E$13:E$62,"<>Completed"),INDEX('New Tooling Jobs'!B$13:B$62,MATCH(55,'New Tooling Jobs'!AG$13:AG$62,0)),INDEX(Reorders!B$13:B$62,MATCH(55-COUNTIFS('New Tooling Jobs'!A$13:A$62,"<>",'New Tooling Jobs'!E$13:E$62,"<>Completed"),Reorders!AC$13:AC$62,0))),"") | D64: =IFERROR(IF(55<=COUNTIFS('New Tooling Jobs'!A$13:A$62,"<>",'New Tooling Jobs'!E$13:E$62,"<>Completed"),INDEX('New Tooling Jobs'!E$13:E$62,MATCH(55,'New Tooling Jobs'!AG$13:AG$62,0)),INDEX(Reorders!E$13:E$62,MATCH(55-COUNTIFS('New Tooling Jobs'!A$13:A$62,"<>",'New Tooling Jobs'!E$13:E$62,"<>Completed"),Reorders!AC$13:AC$62,0))),"") | E64: =IFERROR(IF(55<=COUNTIFS('New Tooling Jobs'!A$13:A$62,"<>",'New Tooling Jobs'!E$13:E$62,"<>Completed"),INDEX('New Tooling Jobs'!G$13:G$62,MATCH(55,'New Tooling Jobs'!AG$13:AG$62,0)),INDEX(Reorders!G$13:G$62,MATCH(55-COUNTIFS('New Tooling Jobs'!A$13:A$62,"<>",'New Tooling Jobs'!E$13:E$62,"<>Completed"),Reorders!AC$13:AC$62,0))),"") | F64: =IFERROR(IF(55<=COUNTIFS('New Tooling Jobs'!A$13:A$62,"<>",'New Tooling Jobs'!E$13:E$62,"<>Completed"),INDEX('New Tooling Jobs'!H$13:H$62,MATCH(55,'New Tooling Jobs'!AG$13:AG$62,0)),INDEX(Reorders!H$13:H$62,MATCH(55-COUNTIFS('New Tooling Jobs'!A$13:A$62,"<>",'New Tooling Jobs'!E$13:E$62,"<>Completed"),Reorders!AC$13:AC$62,0))),"") | G64: =IFERROR(IF(55<=COUNTIFS('New Tooling Jobs'!A$13:A$62,"<>",'New Tooling Jobs'!E$13:E$62,"<>Completed"),INDEX('New Tooling Jobs'!I$13:I$62,MATCH(55,'New Tooling Jobs'!AG$13:AG$62,0)),INDEX(Reorders!I$13:I$62,MATCH(55-COUNTIFS('New Tooling Jobs'!A$13:A$62,"<>",'New Tooling Jobs'!E$13:E$62,"<>Completed"),Reorders!AC$13:AC$62,0))),"")
A65: =IFERROR(IF(56<=COUNTIFS('New Tooling Jobs'!A$13:A$62,"<>",'New Tooling Jobs'!E$13:E$62,"<>Completed"),INDEX('New Tooling Jobs'!A$13:A$62,MATCH(56,'New Tooling Jobs'!AG$13:AG$62,0)),INDEX(Reorders!A$13:A$62,MATCH(56-COUNTIFS('New Tooling Jobs'!A$13:A$62,"<>",'New Tooling Jobs'!E$13:E$62,"<>Completed"),Reorders!AC$13:AC$62,0))),"") | B65: =IFERROR(IF(56<=COUNTIFS('New Tooling Jobs'!A$13:A$62,"<>",'New Tooling Jobs'!E$13:E$62,"<>Completed"),IF(INDEX('New Tooling Jobs'!A$13:A$62,MATCH(56,'New Tooling Jobs'!AG$13:AG$62,0))<>"","New Tooling",""),IF(INDEX(Reorders!A$13:A$62,MATCH(56-COUNTIFS('New Tooling Jobs'!A$13:A$62,"<>",'New Tooling Jobs'!E$13:E$62,"<>Completed"),Reorders!AC$13:AC$62,0))<>"","Reorder","")),"") | C65: =IFERROR(IF(56<=COUNTIFS('New Tooling Jobs'!A$13:A$62,"<>",'New Tooling Jobs'!E$13:E$62,"<>Completed"),INDEX('New Tooling Jobs'!B$13:B$62,MATCH(56,'New Tooling Jobs'!AG$13:AG$62,0)),INDEX(Reorders!B$13:B$62,MATCH(56-COUNTIFS('New Tooling Jobs'!A$13:A$62,"<>",'New Tooling Jobs'!E$13:E$62,"<>Completed"),Reorders!AC$13:AC$62,0))),"") | D65: =IFERROR(IF(56<=COUNTIFS('New Tooling Jobs'!A$13:A$62,"<>",'New Tooling Jobs'!E$13:E$62,"<>Completed"),INDEX('New Tooling Jobs'!E$13:E$62,MATCH(56,'New Tooling Jobs'!AG$13:AG$62,0)),INDEX(Reorders!E$13:E$62,MATCH(56-COUNTIFS('New Tooling Jobs'!A$13:A$62,"<>",'New Tooling Jobs'!E$13:E$62,"<>Completed"),Reorders!AC$13:AC$62,0))),"") | E65: =IFERROR(IF(56<=COUNTIFS('New Tooling Jobs'!A$13:A$62,"<>",'New Tooling Jobs'!E$13:E$62,"<>Completed"),INDEX('New Tooling Jobs'!G$13:G$62,MATCH(56,'New Tooling Jobs'!AG$13:AG$62,0)),INDEX(Reorders!G$13:G$62,MATCH(56-COUNTIFS('New Tooling Jobs'!A$13:A$62,"<>",'New Tooling Jobs'!E$13:E$62,"<>Completed"),Reorders!AC$13:AC$62,0))),"") | F65: =IFERROR(IF(56<=COUNTIFS('New Tooling Jobs'!A$13:A$62,"<>",'New Tooling Jobs'!E$13:E$62,"<>Completed"),INDEX('New Tooling Jobs'!H$13:H$62,MATCH(56,'New Tooling Jobs'!AG$13:AG$62,0)),INDEX(Reorders!H$13:H$62,MATCH(56-COUNTIFS('New Tooling Jobs'!A$13:A$62,"<>",'New Tooling Jobs'!E$13:E$62,"<>Completed"),Reorders!AC$13:AC$62,0))),"") | G65: =IFERROR(IF(56<=COUNTIFS('New Tooling Jobs'!A$13:A$62,"<>",'New Tooling Jobs'!E$13:E$62,"<>Completed"),INDEX('New Tooling Jobs'!I$13:I$62,MATCH(56,'New Tooling Jobs'!AG$13:AG$62,0)),INDEX(Reorders!I$13:I$62,MATCH(56-COUNTIFS('New Tooling Jobs'!A$13:A$62,"<>",'New Tooling Jobs'!E$13:E$62,"<>Completed"),Reorders!AC$13:AC$62,0))),"")
A66: =IFERROR(IF(57<=COUNTIFS('New Tooling Jobs'!A$13:A$62,"<>",'New Tooling Jobs'!E$13:E$62,"<>Completed"),INDEX('New Tooling Jobs'!A$13:A$62,MATCH(57,'New Tooling Jobs'!AG$13:AG$62,0)),INDEX(Reorders!A$13:A$62,MATCH(57-COUNTIFS('New Tooling Jobs'!A$13:A$62,"<>",'New Tooling Jobs'!E$13:E$62,"<>Completed"),Reorders!AC$13:AC$62,0))),"") | B66: =IFERROR(IF(57<=COUNTIFS('New Tooling Jobs'!A$13:A$62,"<>",'New Tooling Jobs'!E$13:E$62,"<>Completed"),IF(INDEX('New Tooling Jobs'!A$13:A$62,MATCH(57,'New Tooling Jobs'!AG$13:AG$62,0))<>"","New Tooling",""),IF(INDEX(Reorders!A$13:A$62,MATCH(57-COUNTIFS('New Tooling Jobs'!A$13:A$62,"<>",'New Tooling Jobs'!E$13:E$62,"<>Completed"),Reorders!AC$13:AC$62,0))<>"","Reorder","")),"") | C66: =IFERROR(IF(57<=COUNTIFS('New Tooling Jobs'!A$13:A$62,"<>",'New Tooling Jobs'!E$13:E$62,"<>Completed"),INDEX('New Tooling Jobs'!B$13:B$62,MATCH(57,'New Tooling Jobs'!AG$13:AG$62,0)),INDEX(Reorders!B$13:B$62,MATCH(57-COUNTIFS('New Tooling Jobs'!A$13:A$62,"<>",'New Tooling Jobs'!E$13:E$62,"<>Completed"),Reorders!AC$13:AC$62,0))),"") | D66: =IFERROR(IF(57<=COUNTIFS('New Tooling Jobs'!A$13:A$62,"<>",'New Tooling Jobs'!E$13:E$62,"<>Completed"),INDEX('New Tooling Jobs'!E$13:E$62,MATCH(57,'New Tooling Jobs'!AG$13:AG$62,0)),INDEX(Reorders!E$13:E$62,MATCH(57-COUNTIFS('New Tooling Jobs'!A$13:A$62,"<>",'New Tooling Jobs'!E$13:E$62,"<>Completed"),Reorders!AC$13:AC$62,0))),"") | E66: =IFERROR(IF(57<=COUNTIFS('New Tooling Jobs'!A$13:A$62,"<>",'New Tooling Jobs'!E$13:E$62,"<>Completed"),INDEX('New Tooling Jobs'!G$13:G$62,MATCH(57,'New Tooling Jobs'!AG$13:AG$62,0)),INDEX(Reorders!G$13:G$62,MATCH(57-COUNTIFS('New Tooling Jobs'!A$13:A$62,"<>",'New Tooling Jobs'!E$13:E$62,"<>Completed"),Reorders!AC$13:AC$62,0))),"") | F66: =IFERROR(IF(57<=COUNTIFS('New Tooling Jobs'!A$13:A$62,"<>",'New Tooling Jobs'!E$13:E$62,"<>Completed"),INDEX('New Tooling Jobs'!H$13:H$62,MATCH(57,'New Tooling Jobs'!AG$13:AG$62,0)),INDEX(Reorders!H$13:H$62,MATCH(57-COUNTIFS('New Tooling Jobs'!A$13:A$62,"<>",'New Tooling Jobs'!E$13:E$62,"<>Completed"),Reorders!AC$13:AC$62,0))),"") | G66: =IFERROR(IF(57<=COUNTIFS('New Tooling Jobs'!A$13:A$62,"<>",'New Tooling Jobs'!E$13:E$62,"<>Completed"),INDEX('New Tooling Jobs'!I$13:I$62,MATCH(57,'New Tooling Jobs'!AG$13:AG$62,0)),INDEX(Reorders!I$13:I$62,MATCH(57-COUNTIFS('New Tooling Jobs'!A$13:A$62,"<>",'New Tooling Jobs'!E$13:E$62,"<>Completed"),Reorders!AC$13:AC$62,0))),"")
A67: =IFERROR(IF(58<=COUNTIFS('New Tooling Jobs'!A$13:A$62,"<>",'New Tooling Jobs'!E$13:E$62,"<>Completed"),INDEX('New Tooling Jobs'!A$13:A$62,MATCH(58,'New Tooling Jobs'!AG$13:AG$62,0)),INDEX(Reorders!A$13:A$62,MATCH(58-COUNTIFS('New Tooling Jobs'!A$13:A$62,"<>",'New Tooling Jobs'!E$13:E$62,"<>Completed"),Reorders!AC$13:AC$62,0))),"") | B67: =IFERROR(IF(58<=COUNTIFS('New Tooling Jobs'!A$13:A$62,"<>",'New Tooling Jobs'!E$13:E$62,"<>Completed"),IF(INDEX('New Tooling Jobs'!A$13:A$62,MATCH(58,'New Tooling Jobs'!AG$13:AG$62,0))<>"","New Tooling",""),IF(INDEX(Reorders!A$13:A$62,MATCH(58-COUNTIFS('New Tooling Jobs'!A$13:A$62,"<>",'New Tooling Jobs'!E$13:E$62,"<>Completed"),Reorders!AC$13:AC$62,0))<>"","Reorder","")),"") | C67: =IFERROR(IF(58<=COUNTIFS('New Tooling Jobs'!A$13:A$62,"<>",'New Tooling Jobs'!E$13:E$62,"<>Completed"),INDEX('New Tooling Jobs'!B$13:B$62,MATCH(58,'New Tooling Jobs'!AG$13:AG$62,0)),INDEX(Reorders!B$13:B$62,MATCH(58-COUNTIFS('New Tooling Jobs'!A$13:A$62,"<>",'New Tooling Jobs'!E$13:E$62,"<>Completed"),Reorders!AC$13:AC$62,0))),"") | D67: =IFERROR(IF(58<=COUNTIFS('New Tooling Jobs'!A$13:A$62,"<>",'New Tooling Jobs'!E$13:E$62,"<>Completed"),INDEX('New Tooling Jobs'!E$13:E$62,MATCH(58,'New Tooling Jobs'!AG$13:AG$62,0)),INDEX(Reorders!E$13:E$62,MATCH(58-COUNTIFS('New Tooling Jobs'!A$13:A$62,"<>",'New Tooling Jobs'!E$13:E$62,"<>Completed"),Reorders!AC$13:AC$62,0))),"") | E67: =IFERROR(IF(58<=COUNTIFS('New Tooling Jobs'!A$13:A$62,"<>",'New Tooling Jobs'!E$13:E$62,"<>Completed"),INDEX('New Tooling Jobs'!G$13:G$62,MATCH(58,'New Tooling Jobs'!AG$13:AG$62,0)),INDEX(Reorders!G$13:G$62,MATCH(58-COUNTIFS('New Tooling Jobs'!A$13:A$62,"<>",'New Tooling Jobs'!E$13:E$62,"<>Completed"),Reorders!AC$13:AC$62,0))),"") | F67: =IFERROR(IF(58<=COUNTIFS('New Tooling Jobs'!A$13:A$62,"<>",'New Tooling Jobs'!E$13:E$62,"<>Completed"),INDEX('New Tooling Jobs'!H$13:H$62,MATCH(58,'New Tooling Jobs'!AG$13:AG$62,0)),INDEX(Reorders!H$13:H$62,MATCH(58-COUNTIFS('New Tooling Jobs'!A$13:A$62,"<>",'New Tooling Jobs'!E$13:E$62,"<>Completed"),Reorders!AC$13:AC$62,0))),"") | G67: =IFERROR(IF(58<=COUNTIFS('New Tooling Jobs'!A$13:A$62,"<>",'New Tooling Jobs'!E$13:E$62,"<>Completed"),INDEX('New Tooling Jobs'!I$13:I$62,MATCH(58,'New Tooling Jobs'!AG$13:AG$62,0)),INDEX(Reorders!I$13:I$62,MATCH(58-COUNTIFS('New Tooling Jobs'!A$13:A$62,"<>",'New Tooling Jobs'!E$13:E$62,"<>Completed"),Reorders!AC$13:AC$62,0))),"")
A68: =IFERROR(IF(59<=COUNTIFS('New Tooling Jobs'!A$13:A$62,"<>",'New Tooling Jobs'!E$13:E$62,"<>Completed"),INDEX('New Tooling Jobs'!A$13:A$62,MATCH(59,'New Tooling Jobs'!AG$13:AG$62,0)),INDEX(Reorders!A$13:A$62,MATCH(59-COUNTIFS('New Tooling Jobs'!A$13:A$62,"<>",'New Tooling Jobs'!E$13:E$62,"<>Completed"),Reorders!AC$13:AC$62,0))),"") | B68: =IFERROR(IF(59<=COUNTIFS('New Tooling Jobs'!A$13:A$62,"<>",'New Tooling Jobs'!E$13:E$62,"<>Completed"),IF(INDEX('New Tooling Jobs'!A$13:A$62,MATCH(59,'New Tooling Jobs'!AG$13:AG$62,0))<>"","New Tooling",""),IF(INDEX(Reorders!A$13:A$62,MATCH(59-COUNTIFS('New Tooling Jobs'!A$13:A$62,"<>",'New Tooling Jobs'!E$13:E$62,"<>Completed"),Reorders!AC$13:AC$62,0))<>"","Reorder","")),"") | C68: =IFERROR(IF(59<=COUNTIFS('New Tooling Jobs'!A$13:A$62,"<>",'New Tooling Jobs'!E$13:E$62,"<>Completed"),INDEX('New Tooling Jobs'!B$13:B$62,MATCH(59,'New Tooling Jobs'!AG$13:AG$62,0)),INDEX(Reorders!B$13:B$62,MATCH(59-COUNTIFS('New Tooling Jobs'!A$13:A$62,"<>",'New Tooling Jobs'!E$13:E$62,"<>Completed"),Reorders!AC$13:AC$62,0))),"") | D68: =IFERROR(IF(59<=COUNTIFS('New Tooling Jobs'!A$13:A$62,"<>",'New Tooling Jobs'!E$13:E$62,"<>Completed"),INDEX('New Tooling Jobs'!E$13:E$62,MATCH(59,'New Tooling Jobs'!AG$13:AG$62,0)),INDEX(Reorders!E$13:E$62,MATCH(59-COUNTIFS('New Tooling Jobs'!A$13:A$62,"<>",'New Tooling Jobs'!E$13:E$62,"<>Completed"),Reorders!AC$13:AC$62,0))),"") | E68: =IFERROR(IF(59<=COUNTIFS('New Tooling Jobs'!A$13:A$62,"<>",'New Tooling Jobs'!E$13:E$62,"<>Completed"),INDEX('New Tooling Jobs'!G$13:G$62,MATCH(59,'New Tooling Jobs'!AG$13:AG$62,0)),INDEX(Reorders!G$13:G$62,MATCH(59-COUNTIFS('New Tooling Jobs'!A$13:A$62,"<>",'New Tooling Jobs'!E$13:E$62,"<>Completed"),Reorders!AC$13:AC$62,0))),"") | F68: =IFERROR(IF(59<=COUNTIFS('New Tooling Jobs'!A$13:A$62,"<>",'New Tooling Jobs'!E$13:E$62,"<>Completed"),INDEX('New Tooling Jobs'!H$13:H$62,MATCH(59,'New Tooling Jobs'!AG$13:AG$62,0)),INDEX(Reorders!H$13:H$62,MATCH(59-COUNTIFS('New Tooling Jobs'!A$13:A$62,"<>",'New Tooling Jobs'!E$13:E$62,"<>Completed"),Reorders!AC$13:AC$62,0))),"") | G68: =IFERROR(IF(59<=COUNTIFS('New Tooling Jobs'!A$13:A$62,"<>",'New Tooling Jobs'!E$13:E$62,"<>Completed"),INDEX('New Tooling Jobs'!I$13:I$62,MATCH(59,'New Tooling Jobs'!AG$13:AG$62,0)),INDEX(Reorders!I$13:I$62,MATCH(59-COUNTIFS('New Tooling Jobs'!A$13:A$62,"<>",'New Tooling Jobs'!E$13:E$62,"<>Completed"),Reorders!AC$13:AC$62,0))),"")
A69: =IFERROR(IF(60<=COUNTIFS('New Tooling Jobs'!A$13:A$62,"<>",'New Tooling Jobs'!E$13:E$62,"<>Completed"),INDEX('New Tooling Jobs'!A$13:A$62,MATCH(60,'New Tooling Jobs'!AG$13:AG$62,0)),INDEX(Reorders!A$13:A$62,MATCH(60-COUNTIFS('New Tooling Jobs'!A$13:A$62,"<>",'New Tooling Jobs'!E$13:E$62,"<>Completed"),Reorders!AC$13:AC$62,0))),"") | B69: =IFERROR(IF(60<=COUNTIFS('New Tooling Jobs'!A$13:A$62,"<>",'New Tooling Jobs'!E$13:E$62,"<>Completed"),IF(INDEX('New Tooling Jobs'!A$13:A$62,MATCH(60,'New Tooling Jobs'!AG$13:AG$62,0))<>"","New Tooling",""),IF(INDEX(Reorders!A$13:A$62,MATCH(60-COUNTIFS('New Tooling Jobs'!A$13:A$62,"<>",'New Tooling Jobs'!E$13:E$62,"<>Completed"),Reorders!AC$13:AC$62,0))<>"","Reorder","")),"") | C69: =IFERROR(IF(60<=COUNTIFS('New Tooling Jobs'!A$13:A$62,"<>",'New Tooling Jobs'!E$13:E$62,"<>Completed"),INDEX('New Tooling Jobs'!B$13:B$62,MATCH(60,'New Tooling Jobs'!AG$13:AG$62,0)),INDEX(Reorders!B$13:B$62,MATCH(60-COUNTIFS('New Tooling Jobs'!A$13:A$62,"<>",'New Tooling Jobs'!E$13:E$62,"<>Completed"),Reorders!AC$13:AC$62,0))),"") | D69: =IFERROR(IF(60<=COUNTIFS('New Tooling Jobs'!A$13:A$62,"<>",'New Tooling Jobs'!E$13:E$62,"<>Completed"),INDEX('New Tooling Jobs'!E$13:E$62,MATCH(60,'New Tooling Jobs'!AG$13:AG$62,0)),INDEX(Reorders!E$13:E$62,MATCH(60-COUNTIFS('New Tooling Jobs'!A$13:A$62,"<>",'New Tooling Jobs'!E$13:E$62,"<>Completed"),Reorders!AC$13:AC$62,0))),"") | E69: =IFERROR(IF(60<=COUNTIFS('New Tooling Jobs'!A$13:A$62,"<>",'New Tooling Jobs'!E$13:E$62,"<>Completed"),INDEX('New Tooling Jobs'!G$13:G$62,MATCH(60,'New Tooling Jobs'!AG$13:AG$62,0)),INDEX(Reorders!G$13:G$62,MATCH(60-COUNTIFS('New Tooling Jobs'!A$13:A$62,"<>",'New Tooling Jobs'!E$13:E$62,"<>Completed"),Reorders!AC$13:AC$62,0))),"") | F69: =IFERROR(IF(60<=COUNTIFS('New Tooling Jobs'!A$13:A$62,"<>",'New Tooling Jobs'!E$13:E$62,"<>Completed"),INDEX('New Tooling Jobs'!H$13:H$62,MATCH(60,'New Tooling Jobs'!AG$13:AG$62,0)),INDEX(Reorders!H$13:H$62,MATCH(60-COUNTIFS('New Tooling Jobs'!A$13:A$62,"<>",'New Tooling Jobs'!E$13:E$62,"<>Completed"),Reorders!AC$13:AC$62,0))),"") | G69: =IFERROR(IF(60<=COUNTIFS('New Tooling Jobs'!A$13:A$62,"<>",'New Tooling Jobs'!E$13:E$62,"<>Completed"),INDEX('New Tooling Jobs'!I$13:I$62,MATCH(60,'New Tooling Jobs'!AG$13:AG$62,0)),INDEX(Reorders!I$13:I$62,MATCH(60-COUNTIFS('New Tooling Jobs'!A$13:A$62,"<>",'New Tooling Jobs'!E$13:E$62,"<>Completed"),Reorders!AC$13:AC$62,0))),"")
A70: =IFERROR(IF(61<=COUNTIFS('New Tooling Jobs'!A$13:A$62,"<>",'New Tooling Jobs'!E$13:E$62,"<>Completed"),INDEX('New Tooling Jobs'!A$13:A$62,MATCH(61,'New Tooling Jobs'!AG$13:AG$62,0)),INDEX(Reorders!A$13:A$62,MATCH(61-COUNTIFS('New Tooling Jobs'!A$13:A$62,"<>",'New Tooling Jobs'!E$13:E$62,"<>Completed"),Reorders!AC$13:AC$62,0))),"") | B70: =IFERROR(IF(61<=COUNTIFS('New Tooling Jobs'!A$13:A$62,"<>",'New Tooling Jobs'!E$13:E$62,"<>Completed"),IF(INDEX('New Tooling Jobs'!A$13:A$62,MATCH(61,'New Tooling Jobs'!AG$13:AG$62,0))<>"","New Tooling",""),IF(INDEX(Reorders!A$13:A$62,MATCH(61-COUNTIFS('New Tooling Jobs'!A$13:A$62,"<>",'New Tooling Jobs'!E$13:E$62,"<>Completed"),Reorders!AC$13:AC$62,0))<>"","Reorder","")),"") | C70: =IFERROR(IF(61<=COUNTIFS('New Tooling Jobs'!A$13:A$62,"<>",'New Tooling Jobs'!E$13:E$62,"<>Completed"),INDEX('New Tooling Jobs'!B$13:B$62,MATCH(61,'New Tooling Jobs'!AG$13:AG$62,0)),INDEX(Reorders!B$13:B$62,MATCH(61-COUNTIFS('New Tooling Jobs'!A$13:A$62,"<>",'New Tooling Jobs'!E$13:E$62,"<>Completed"),Reorders!AC$13:AC$62,0))),"") | D70: =IFERROR(IF(61<=COUNTIFS('New Tooling Jobs'!A$13:A$62,"<>",'New Tooling Jobs'!E$13:E$62,"<>Completed"),INDEX('New Tooling Jobs'!E$13:E$62,MATCH(61,'New Tooling Jobs'!AG$13:AG$62,0)),INDEX(Reorders!E$13:E$62,MATCH(61-COUNTIFS('New Tooling Jobs'!A$13:A$62,"<>",'New Tooling Jobs'!E$13:E$62,"<>Completed"),Reorders!AC$13:AC$62,0))),"") | E70: =IFERROR(IF(61<=COUNTIFS('New Tooling Jobs'!A$13:A$62,"<>",'New Tooling Jobs'!E$13:E$62,"<>Completed"),INDEX('New Tooling Jobs'!G$13:G$62,MATCH(61,'New Tooling Jobs'!AG$13:AG$62,0)),INDEX(Reorders!G$13:G$62,MATCH(61-COUNTIFS('New Tooling Jobs'!A$13:A$62,"<>",'New Tooling Jobs'!E$13:E$62,"<>Completed"),Reorders!AC$13:AC$62,0))),"") | F70: =IFERROR(IF(61<=COUNTIFS('New Tooling Jobs'!A$13:A$62,"<>",'New Tooling Jobs'!E$13:E$62,"<>Completed"),INDEX('New Tooling Jobs'!H$13:H$62,MATCH(61,'New Tooling Jobs'!AG$13:AG$62,0)),INDEX(Reorders!H$13:H$62,MATCH(61-COUNTIFS('New Tooling Jobs'!A$13:A$62,"<>",'New Tooling Jobs'!E$13:E$62,"<>Completed"),Reorders!AC$13:AC$62,0))),"") | G70: =IFERROR(IF(61<=COUNTIFS('New Tooling Jobs'!A$13:A$62,"<>",'New Tooling Jobs'!E$13:E$62,"<>Completed"),INDEX('New Tooling Jobs'!I$13:I$62,MATCH(61,'New Tooling Jobs'!AG$13:AG$62,0)),INDEX(Reorders!I$13:I$62,MATCH(61-COUNTIFS('New Tooling Jobs'!A$13:A$62,"<>",'New Tooling Jobs'!E$13:E$62,"<>Completed"),Reorders!AC$13:AC$62,0))),"")
A71: =IFERROR(IF(62<=COUNTIFS('New Tooling Jobs'!A$13:A$62,"<>",'New Tooling Jobs'!E$13:E$62,"<>Completed"),INDEX('New Tooling Jobs'!A$13:A$62,MATCH(62,'New Tooling Jobs'!AG$13:AG$62,0)),INDEX(Reorders!A$13:A$62,MATCH(62-COUNTIFS('New Tooling Jobs'!A$13:A$62,"<>",'New Tooling Jobs'!E$13:E$62,"<>Completed"),Reorders!AC$13:AC$62,0))),"") | B71: =IFERROR(IF(62<=COUNTIFS('New Tooling Jobs'!A$13:A$62,"<>",'New Tooling Jobs'!E$13:E$62,"<>Completed"),IF(INDEX('New Tooling Jobs'!A$13:A$62,MATCH(62,'New Tooling Jobs'!AG$13:AG$62,0))<>"","New Tooling",""),IF(INDEX(Reorders!A$13:A$62,MATCH(62-COUNTIFS('New Tooling Jobs'!A$13:A$62,"<>",'New Tooling Jobs'!E$13:E$62,"<>Completed"),Reorders!AC$13:AC$62,0))<>"","Reorder","")),"") | C71: =IFERROR(IF(62<=COUNTIFS('New Tooling Jobs'!A$13:A$62,"<>",'New Tooling Jobs'!E$13:E$62,"<>Completed"),INDEX('New Tooling Jobs'!B$13:B$62,MATCH(62,'New Tooling Jobs'!AG$13:AG$62,0)),INDEX(Reorders!B$13:B$62,MATCH(62-COUNTIFS('New Tooling Jobs'!A$13:A$62,"<>",'New Tooling Jobs'!E$13:E$62,"<>Completed"),Reorders!AC$13:AC$62,0))),"") | D71: =IFERROR(IF(62<=COUNTIFS('New Tooling Jobs'!A$13:A$62,"<>",'New Tooling Jobs'!E$13:E$62,"<>Completed"),INDEX('New Tooling Jobs'!E$13:E$62,MATCH(62,'New Tooling Jobs'!AG$13:AG$62,0)),INDEX(Reorders!E$13:E$62,MATCH(62-COUNTIFS('New Tooling Jobs'!A$13:A$62,"<>",'New Tooling Jobs'!E$13:E$62,"<>Completed"),Reorders!AC$13:AC$62,0))),"") | E71: =IFERROR(IF(62<=COUNTIFS('New Tooling Jobs'!A$13:A$62,"<>",'New Tooling Jobs'!E$13:E$62,"<>Completed"),INDEX('New Tooling Jobs'!G$13:G$62,MATCH(62,'New Tooling Jobs'!AG$13:AG$62,0)),INDEX(Reorders!G$13:G$62,MATCH(62-COUNTIFS('New Tooling Jobs'!A$13:A$62,"<>",'New Tooling Jobs'!E$13:E$62,"<>Completed"),Reorders!AC$13:AC$62,0))),"") | F71: =IFERROR(IF(62<=COUNTIFS('New Tooling Jobs'!A$13:A$62,"<>",'New Tooling Jobs'!E$13:E$62,"<>Completed"),INDEX('New Tooling Jobs'!H$13:H$62,MATCH(62,'New Tooling Jobs'!AG$13:AG$62,0)),INDEX(Reorders!H$13:H$62,MATCH(62-COUNTIFS('New Tooling Jobs'!A$13:A$62,"<>",'New Tooling Jobs'!E$13:E$62,"<>Completed"),Reorders!AC$13:AC$62,0))),"") | G71: =IFERROR(IF(62<=COUNTIFS('New Tooling Jobs'!A$13:A$62,"<>",'New Tooling Jobs'!E$13:E$62,"<>Completed"),INDEX('New Tooling Jobs'!I$13:I$62,MATCH(62,'New Tooling Jobs'!AG$13:AG$62,0)),INDEX(Reorders!I$13:I$62,MATCH(62-COUNTIFS('New Tooling Jobs'!A$13:A$62,"<>",'New Tooling Jobs'!E$13:E$62,"<>Completed"),Reorders!AC$13:AC$62,0))),"")
A72: =IFERROR(IF(63<=COUNTIFS('New Tooling Jobs'!A$13:A$62,"<>",'New Tooling Jobs'!E$13:E$62,"<>Completed"),INDEX('New Tooling Jobs'!A$13:A$62,MATCH(63,'New Tooling Jobs'!AG$13:AG$62,0)),INDEX(Reorders!A$13:A$62,MATCH(63-COUNTIFS('New Tooling Jobs'!A$13:A$62,"<>",'New Tooling Jobs'!E$13:E$62,"<>Completed"),Reorders!AC$13:AC$62,0))),"") | B72: =IFERROR(IF(63<=COUNTIFS('New Tooling Jobs'!A$13:A$62,"<>",'New Tooling Jobs'!E$13:E$62,"<>Completed"),IF(INDEX('New Tooling Jobs'!A$13:A$62,MATCH(63,'New Tooling Jobs'!AG$13:AG$62,0))<>"","New Tooling",""),IF(INDEX(Reorders!A$13:A$62,MATCH(63-COUNTIFS('New Tooling Jobs'!A$13:A$62,"<>",'New Tooling Jobs'!E$13:E$62,"<>Completed"),Reorders!AC$13:AC$62,0))<>"","Reorder","")),"") | C72: =IFERROR(IF(63<=COUNTIFS('New Tooling Jobs'!A$13:A$62,"<>",'New Tooling Jobs'!E$13:E$62,"<>Completed"),INDEX('New Tooling Jobs'!B$13:B$62,MATCH(63,'New Tooling Jobs'!AG$13:AG$62,0)),INDEX(Reorders!B$13:B$62,MATCH(63-COUNTIFS('New Tooling Jobs'!A$13:A$62,"<>",'New Tooling Jobs'!E$13:E$62,"<>Completed"),Reorders!AC$13:AC$62,0))),"") | D72: =IFERROR(IF(63<=COUNTIFS('New Tooling Jobs'!A$13:A$62,"<>",'New Tooling Jobs'!E$13:E$62,"<>Completed"),INDEX('New Tooling Jobs'!E$13:E$62,MATCH(63,'New Tooling Jobs'!AG$13:AG$62,0)),INDEX(Reorders!E$13:E$62,MATCH(63-COUNTIFS('New Tooling Jobs'!A$13:A$62,"<>",'New Tooling Jobs'!E$13:E$62,"<>Completed"),Reorders!AC$13:AC$62,0))),"") | E72: =IFERROR(IF(63<=COUNTIFS('New Tooling Jobs'!A$13:A$62,"<>",'New Tooling Jobs'!E$13:E$62,"<>Completed"),INDEX('New Tooling Jobs'!G$13:G$62,MATCH(63,'New Tooling Jobs'!AG$13:AG$62,0)),INDEX(Reorders!G$13:G$62,MATCH(63-COUNTIFS('New Tooling Jobs'!A$13:A$62,"<>",'New Tooling Jobs'!E$13:E$62,"<>Completed"),Reorders!AC$13:AC$62,0))),"") | F72: =IFERROR(IF(63<=COUNTIFS('New Tooling Jobs'!A$13:A$62,"<>",'New Tooling Jobs'!E$13:E$62,"<>Completed"),INDEX('New Tooling Jobs'!H$13:H$62,MATCH(63,'New Tooling Jobs'!AG$13:AG$62,0)),INDEX(Reorders!H$13:H$62,MATCH(63-COUNTIFS('New Tooling Jobs'!A$13:A$62,"<>",'New Tooling Jobs'!E$13:E$62,"<>Completed"),Reorders!AC$13:AC$62,0))),"") | G72: =IFERROR(IF(63<=COUNTIFS('New Tooling Jobs'!A$13:A$62,"<>",'New Tooling Jobs'!E$13:E$62,"<>Completed"),INDEX('New Tooling Jobs'!I$13:I$62,MATCH(63,'New Tooling Jobs'!AG$13:AG$62,0)),INDEX(Reorders!I$13:I$62,MATCH(63-COUNTIFS('New Tooling Jobs'!A$13:A$62,"<>",'New Tooling Jobs'!E$13:E$62,"<>Completed"),Reorders!AC$13:AC$62,0))),"")
A73: =IFERROR(IF(64<=COUNTIFS('New Tooling Jobs'!A$13:A$62,"<>",'New Tooling Jobs'!E$13:E$62,"<>Completed"),INDEX('New Tooling Jobs'!A$13:A$62,MATCH(64,'New Tooling Jobs'!AG$13:AG$62,0)),INDEX(Reorders!A$13:A$62,MATCH(64-COUNTIFS('New Tooling Jobs'!A$13:A$62,"<>",'New Tooling Jobs'!E$13:E$62,"<>Completed"),Reorders!AC$13:AC$62,0))),"") | B73: =IFERROR(IF(64<=COUNTIFS('New Tooling Jobs'!A$13:A$62,"<>",'New Tooling Jobs'!E$13:E$62,"<>Completed"),IF(INDEX('New Tooling Jobs'!A$13:A$62,MATCH(64,'New Tooling Jobs'!AG$13:AG$62,0))<>"","New Tooling",""),IF(INDEX(Reorders!A$13:A$62,MATCH(64-COUNTIFS('New Tooling Jobs'!A$13:A$62,"<>",'New Tooling Jobs'!E$13:E$62,"<>Completed"),Reorders!AC$13:AC$62,0))<>"","Reorder","")),"") | C73: =IFERROR(IF(64<=COUNTIFS('New Tooling Jobs'!A$13:A$62,"<>",'New Tooling Jobs'!E$13:E$62,"<>Completed"),INDEX('New Tooling Jobs'!B$13:B$62,MATCH(64,'New Tooling Jobs'!AG$13:AG$62,0)),INDEX(Reorders!B$13:B$62,MATCH(64-COUNTIFS('New Tooling Jobs'!A$13:A$62,"<>",'New Tooling Jobs'!E$13:E$62,"<>Completed"),Reorders!AC$13:AC$62,0))),"") | D73: =IFERROR(IF(64<=COUNTIFS('New Tooling Jobs'!A$13:A$62,"<>",'New Tooling Jobs'!E$13:E$62,"<>Completed"),INDEX('New Tooling Jobs'!E$13:E$62,MATCH(64,'New Tooling Jobs'!AG$13:AG$62,0)),INDEX(Reorders!E$13:E$62,MATCH(64-COUNTIFS('New Tooling Jobs'!A$13:A$62,"<>",'New Tooling Jobs'!E$13:E$62,"<>Completed"),Reorders!AC$13:AC$62,0))),"") | E73: =IFERROR(IF(64<=COUNTIFS('New Tooling Jobs'!A$13:A$62,"<>",'New Tooling Jobs'!E$13:E$62,"<>Completed"),INDEX('New Tooling Jobs'!G$13:G$62,MATCH(64,'New Tooling Jobs'!AG$13:AG$62,0)),INDEX(Reorders!G$13:G$62,MATCH(64-COUNTIFS('New Tooling Jobs'!A$13:A$62,"<>",'New Tooling Jobs'!E$13:E$62,"<>Completed"),Reorders!AC$13:AC$62,0))),"") | F73: =IFERROR(IF(64<=COUNTIFS('New Tooling Jobs'!A$13:A$62,"<>",'New Tooling Jobs'!E$13:E$62,"<>Completed"),INDEX('New Tooling Jobs'!H$13:H$62,MATCH(64,'New Tooling Jobs'!AG$13:AG$62,0)),INDEX(Reorders!H$13:H$62,MATCH(64-COUNTIFS('New Tooling Jobs'!A$13:A$62,"<>",'New Tooling Jobs'!E$13:E$62,"<>Completed"),Reorders!AC$13:AC$62,0))),"") | G73: =IFERROR(IF(64<=COUNTIFS('New Tooling Jobs'!A$13:A$62,"<>",'New Tooling Jobs'!E$13:E$62,"<>Completed"),INDEX('New Tooling Jobs'!I$13:I$62,MATCH(64,'New Tooling Jobs'!AG$13:AG$62,0)),INDEX(Reorders!I$13:I$62,MATCH(64-COUNTIFS('New Tooling Jobs'!A$13:A$62,"<>",'New Tooling Jobs'!E$13:E$62,"<>Completed"),Reorders!AC$13:AC$62,0))),"")
A74: =IFERROR(IF(65<=COUNTIFS('New Tooling Jobs'!A$13:A$62,"<>",'New Tooling Jobs'!E$13:E$62,"<>Completed"),INDEX('New Tooling Jobs'!A$13:A$62,MATCH(65,'New Tooling Jobs'!AG$13:AG$62,0)),INDEX(Reorders!A$13:A$62,MATCH(65-COUNTIFS('New Tooling Jobs'!A$13:A$62,"<>",'New Tooling Jobs'!E$13:E$62,"<>Completed"),Reorders!AC$13:AC$62,0))),"") | B74: =IFERROR(IF(65<=COUNTIFS('New Tooling Jobs'!A$13:A$62,"<>",'New Tooling Jobs'!E$13:E$62,"<>Completed"),IF(INDEX('New Tooling Jobs'!A$13:A$62,MATCH(65,'New Tooling Jobs'!AG$13:AG$62,0))<>"","New Tooling",""),IF(INDEX(Reorders!A$13:A$62,MATCH(65-COUNTIFS('New Tooling Jobs'!A$13:A$62,"<>",'New Tooling Jobs'!E$13:E$62,"<>Completed"),Reorders!AC$13:AC$62,0))<>"","Reorder","")),"") | C74: =IFERROR(IF(65<=COUNTIFS('New Tooling Jobs'!A$13:A$62,"<>",'New Tooling Jobs'!E$13:E$62,"<>Completed"),INDEX('New Tooling Jobs'!B$13:B$62,MATCH(65,'New Tooling Jobs'!AG$13:AG$62,0)),INDEX(Reorders!B$13:B$62,MATCH(65-COUNTIFS('New Tooling Jobs'!A$13:A$62,"<>",'New Tooling Jobs'!E$13:E$62,"<>Completed"),Reorders!AC$13:AC$62,0))),"") | D74: =IFERROR(IF(65<=COUNTIFS('New Tooling Jobs'!A$13:A$62,"<>",'New Tooling Jobs'!E$13:E$62,"<>Completed"),INDEX('New Tooling Jobs'!E$13:E$62,MATCH(65,'New Tooling Jobs'!AG$13:AG$62,0)),INDEX(Reorders!E$13:E$62,MATCH(65-COUNTIFS('New Tooling Jobs'!A$13:A$62,"<>",'New Tooling Jobs'!E$13:E$62,"<>Completed"),Reorders!AC$13:AC$62,0))),"") | E74: =IFERROR(IF(65<=COUNTIFS('New Tooling Jobs'!A$13:A$62,"<>",'New Tooling Jobs'!E$13:E$62,"<>Completed"),INDEX('New Tooling Jobs'!G$13:G$62,MATCH(65,'New Tooling Jobs'!AG$13:AG$62,0)),INDEX(Reorders!G$13:G$62,MATCH(65-COUNTIFS('New Tooling Jobs'!A$13:A$62,"<>",'New Tooling Jobs'!E$13:E$62,"<>Completed"),Reorders!AC$13:AC$62,0))),"") | F74: =IFERROR(IF(65<=COUNTIFS('New Tooling Jobs'!A$13:A$62,"<>",'New Tooling Jobs'!E$13:E$62,"<>Completed"),INDEX('New Tooling Jobs'!H$13:H$62,MATCH(65,'New Tooling Jobs'!AG$13:AG$62,0)),INDEX(Reorders!H$13:H$62,MATCH(65-COUNTIFS('New Tooling Jobs'!A$13:A$62,"<>",'New Tooling Jobs'!E$13:E$62,"<>Completed"),Reorders!AC$13:AC$62,0))),"") | G74: =IFERROR(IF(65<=COUNTIFS('New Tooling Jobs'!A$13:A$62,"<>",'New Tooling Jobs'!E$13:E$62,"<>Completed"),INDEX('New Tooling Jobs'!I$13:I$62,MATCH(65,'New Tooling Jobs'!AG$13:AG$62,0)),INDEX(Reorders!I$13:I$62,MATCH(65-COUNTIFS('New Tooling Jobs'!A$13:A$62,"<>",'New Tooling Jobs'!E$13:E$62,"<>Completed"),Reorders!AC$13:AC$62,0))),"")
A75: =IFERROR(IF(66<=COUNTIFS('New Tooling Jobs'!A$13:A$62,"<>",'New Tooling Jobs'!E$13:E$62,"<>Completed"),INDEX('New Tooling Jobs'!A$13:A$62,MATCH(66,'New Tooling Jobs'!AG$13:AG$62,0)),INDEX(Reorders!A$13:A$62,MATCH(66-COUNTIFS('New Tooling Jobs'!A$13:A$62,"<>",'New Tooling Jobs'!E$13:E$62,"<>Completed"),Reorders!AC$13:AC$62,0))),"") | B75: =IFERROR(IF(66<=COUNTIFS('New Tooling Jobs'!A$13:A$62,"<>",'New Tooling Jobs'!E$13:E$62,"<>Completed"),IF(INDEX('New Tooling Jobs'!A$13:A$62,MATCH(66,'New Tooling Jobs'!AG$13:AG$62,0))<>"","New Tooling",""),IF(INDEX(Reorders!A$13:A$62,MATCH(66-COUNTIFS('New Tooling Jobs'!A$13:A$62,"<>",'New Tooling Jobs'!E$13:E$62,"<>Completed"),Reorders!AC$13:AC$62,0))<>"","Reorder","")),"") | C75: =IFERROR(IF(66<=COUNTIFS('New Tooling Jobs'!A$13:A$62,"<>",'New Tooling Jobs'!E$13:E$62,"<>Completed"),INDEX('New Tooling Jobs'!B$13:B$62,MATCH(66,'New Tooling Jobs'!AG$13:AG$62,0)),INDEX(Reorders!B$13:B$62,MATCH(66-COUNTIFS('New Tooling Jobs'!A$13:A$62,"<>",'New Tooling Jobs'!E$13:E$62,"<>Completed"),Reorders!AC$13:AC$62,0))),"") | D75: =IFERROR(IF(66<=COUNTIFS('New Tooling Jobs'!A$13:A$62,"<>",'New Tooling Jobs'!E$13:E$62,"<>Completed"),INDEX('New Tooling Jobs'!E$13:E$62,MATCH(66,'New Tooling Jobs'!AG$13:AG$62,0)),INDEX(Reorders!E$13:E$62,MATCH(66-COUNTIFS('New Tooling Jobs'!A$13:A$62,"<>",'New Tooling Jobs'!E$13:E$62,"<>Completed"),Reorders!AC$13:AC$62,0))),"") | E75: =IFERROR(IF(66<=COUNTIFS('New Tooling Jobs'!A$13:A$62,"<>",'New Tooling Jobs'!E$13:E$62,"<>Completed"),INDEX('New Tooling Jobs'!G$13:G$62,MATCH(66,'New Tooling Jobs'!AG$13:AG$62,0)),INDEX(Reorders!G$13:G$62,MATCH(66-COUNTIFS('New Tooling Jobs'!A$13:A$62,"<>",'New Tooling Jobs'!E$13:E$62,"<>Completed"),Reorders!AC$13:AC$62,0))),"") | F75: =IFERROR(IF(66<=COUNTIFS('New Tooling Jobs'!A$13:A$62,"<>",'New Tooling Jobs'!E$13:E$62,"<>Completed"),INDEX('New Tooling Jobs'!H$13:H$62,MATCH(66,'New Tooling Jobs'!AG$13:AG$62,0)),INDEX(Reorders!H$13:H$62,MATCH(66-COUNTIFS('New Tooling Jobs'!A$13:A$62,"<>",'New Tooling Jobs'!E$13:E$62,"<>Completed"),Reorders!AC$13:AC$62,0))),"") | G75: =IFERROR(IF(66<=COUNTIFS('New Tooling Jobs'!A$13:A$62,"<>",'New Tooling Jobs'!E$13:E$62,"<>Completed"),INDEX('New Tooling Jobs'!I$13:I$62,MATCH(66,'New Tooling Jobs'!AG$13:AG$62,0)),INDEX(Reorders!I$13:I$62,MATCH(66-COUNTIFS('New Tooling Jobs'!A$13:A$62,"<>",'New Tooling Jobs'!E$13:E$62,"<>Completed"),Reorders!AC$13:AC$62,0))),"")
A76: =IFERROR(IF(67<=COUNTIFS('New Tooling Jobs'!A$13:A$62,"<>",'New Tooling Jobs'!E$13:E$62,"<>Completed"),INDEX('New Tooling Jobs'!A$13:A$62,MATCH(67,'New Tooling Jobs'!AG$13:AG$62,0)),INDEX(Reorders!A$13:A$62,MATCH(67-COUNTIFS('New Tooling Jobs'!A$13:A$62,"<>",'New Tooling Jobs'!E$13:E$62,"<>Completed"),Reorders!AC$13:AC$62,0))),"") | B76: =IFERROR(IF(67<=COUNTIFS('New Tooling Jobs'!A$13:A$62,"<>",'New Tooling Jobs'!E$13:E$62,"<>Completed"),IF(INDEX('New Tooling Jobs'!A$13:A$62,MATCH(67,'New Tooling Jobs'!AG$13:AG$62,0))<>"","New Tooling",""),IF(INDEX(Reorders!A$13:A$62,MATCH(67-COUNTIFS('New Tooling Jobs'!A$13:A$62,"<>",'New Tooling Jobs'!E$13:E$62,"<>Completed"),Reorders!AC$13:AC$62,0))<>"","Reorder","")),"") | C76: =IFERROR(IF(67<=COUNTIFS('New Tooling Jobs'!A$13:A$62,"<>",'New Tooling Jobs'!E$13:E$62,"<>Completed"),INDEX('New Tooling Jobs'!B$13:B$62,MATCH(67,'New Tooling Jobs'!AG$13:AG$62,0)),INDEX(Reorders!B$13:B$62,MATCH(67-COUNTIFS('New Tooling Jobs'!A$13:A$62,"<>",'New Tooling Jobs'!E$13:E$62,"<>Completed"),Reorders!AC$13:AC$62,0))),"") | D76: =IFERROR(IF(67<=COUNTIFS('New Tooling Jobs'!A$13:A$62,"<>",'New Tooling Jobs'!E$13:E$62,"<>Completed"),INDEX('New Tooling Jobs'!E$13:E$62,MATCH(67,'New Tooling Jobs'!AG$13:AG$62,0)),INDEX(Reorders!E$13:E$62,MATCH(67-COUNTIFS('New Tooling Jobs'!A$13:A$62,"<>",'New Tooling Jobs'!E$13:E$62,"<>Completed"),Reorders!AC$13:AC$62,0))),"") | E76: =IFERROR(IF(67<=COUNTIFS('New Tooling Jobs'!A$13:A$62,"<>",'New Tooling Jobs'!E$13:E$62,"<>Completed"),INDEX('New Tooling Jobs'!G$13:G$62,MATCH(67,'New Tooling Jobs'!AG$13:AG$62,0)),INDEX(Reorders!G$13:G$62,MATCH(67-COUNTIFS('New Tooling Jobs'!A$13:A$62,"<>",'New Tooling Jobs'!E$13:E$62,"<>Completed"),Reorders!AC$13:AC$62,0))),"") | F76: =IFERROR(IF(67<=COUNTIFS('New Tooling Jobs'!A$13:A$62,"<>",'New Tooling Jobs'!E$13:E$62,"<>Completed"),INDEX('New Tooling Jobs'!H$13:H$62,MATCH(67,'New Tooling Jobs'!AG$13:AG$62,0)),INDEX(Reorders!H$13:H$62,MATCH(67-COUNTIFS('New Tooling Jobs'!A$13:A$62,"<>",'New Tooling Jobs'!E$13:E$62,"<>Completed"),Reorders!AC$13:AC$62,0))),"") | G76: =IFERROR(IF(67<=COUNTIFS('New Tooling Jobs'!A$13:A$62,"<>",'New Tooling Jobs'!E$13:E$62,"<>Completed"),INDEX('New Tooling Jobs'!I$13:I$62,MATCH(67,'New Tooling Jobs'!AG$13:AG$62,0)),INDEX(Reorders!I$13:I$62,MATCH(67-COUNTIFS('New Tooling Jobs'!A$13:A$62,"<>",'New Tooling Jobs'!E$13:E$62,"<>Completed"),Reorders!AC$13:AC$62,0))),"")
A77: =IFERROR(IF(68<=COUNTIFS('New Tooling Jobs'!A$13:A$62,"<>",'New Tooling Jobs'!E$13:E$62,"<>Completed"),INDEX('New Tooling Jobs'!A$13:A$62,MATCH(68,'New Tooling Jobs'!AG$13:AG$62,0)),INDEX(Reorders!A$13:A$62,MATCH(68-COUNTIFS('New Tooling Jobs'!A$13:A$62,"<>",'New Tooling Jobs'!E$13:E$62,"<>Completed"),Reorders!AC$13:AC$62,0))),"") | B77: =IFERROR(IF(68<=COUNTIFS('New Tooling Jobs'!A$13:A$62,"<>",'New Tooling Jobs'!E$13:E$62,"<>Completed"),IF(INDEX('New Tooling Jobs'!A$13:A$62,MATCH(68,'New Tooling Jobs'!AG$13:AG$62,0))<>"","New Tooling",""),IF(INDEX(Reorders!A$13:A$62,MATCH(68-COUNTIFS('New Tooling Jobs'!A$13:A$62,"<>",'New Tooling Jobs'!E$13:E$62,"<>Completed"),Reorders!AC$13:AC$62,0))<>"","Reorder","")),"") | C77: =IFERROR(IF(68<=COUNTIFS('New Tooling Jobs'!A$13:A$62,"<>",'New Tooling Jobs'!E$13:E$62,"<>Completed"),INDEX('New Tooling Jobs'!B$13:B$62,MATCH(68,'New Tooling Jobs'!AG$13:AG$62,0)),INDEX(Reorders!B$13:B$62,MATCH(68-COUNTIFS('New Tooling Jobs'!A$13:A$62,"<>",'New Tooling Jobs'!E$13:E$62,"<>Completed"),Reorders!AC$13:AC$62,0))),"") | D77: =IFERROR(IF(68<=COUNTIFS('New Tooling Jobs'!A$13:A$62,"<>",'New Tooling Jobs'!E$13:E$62,"<>Completed"),INDEX('New Tooling Jobs'!E$13:E$62,MATCH(68,'New Tooling Jobs'!AG$13:AG$62,0)),INDEX(Reorders!E$13:E$62,MATCH(68-COUNTIFS('New Tooling Jobs'!A$13:A$62,"<>",'New Tooling Jobs'!E$13:E$62,"<>Completed"),Reorders!AC$13:AC$62,0))),"") | E77: =IFERROR(IF(68<=COUNTIFS('New Tooling Jobs'!A$13:A$62,"<>",'New Tooling Jobs'!E$13:E$62,"<>Completed"),INDEX('New Tooling Jobs'!G$13:G$62,MATCH(68,'New Tooling Jobs'!AG$13:AG$62,0)),INDEX(Reorders!G$13:G$62,MATCH(68-COUNTIFS('New Tooling Jobs'!A$13:A$62,"<>",'New Tooling Jobs'!E$13:E$62,"<>Completed"),Reorders!AC$13:AC$62,0))),"") | F77: =IFERROR(IF(68<=COUNTIFS('New Tooling Jobs'!A$13:A$62,"<>",'New Tooling Jobs'!E$13:E$62,"<>Completed"),INDEX('New Tooling Jobs'!H$13:H$62,MATCH(68,'New Tooling Jobs'!AG$13:AG$62,0)),INDEX(Reorders!H$13:H$62,MATCH(68-COUNTIFS('New Tooling Jobs'!A$13:A$62,"<>",'New Tooling Jobs'!E$13:E$62,"<>Completed"),Reorders!AC$13:AC$62,0))),"") | G77: =IFERROR(IF(68<=COUNTIFS('New Tooling Jobs'!A$13:A$62,"<>",'New Tooling Jobs'!E$13:E$62,"<>Completed"),INDEX('New Tooling Jobs'!I$13:I$62,MATCH(68,'New Tooling Jobs'!AG$13:AG$62,0)),INDEX(Reorders!I$13:I$62,MATCH(68-COUNTIFS('New Tooling Jobs'!A$13:A$62,"<>",'New Tooling Jobs'!E$13:E$62,"<>Completed"),Reorders!AC$13:AC$62,0))),"")
A78: =IFERROR(IF(69<=COUNTIFS('New Tooling Jobs'!A$13:A$62,"<>",'New Tooling Jobs'!E$13:E$62,"<>Completed"),INDEX('New Tooling Jobs'!A$13:A$62,MATCH(69,'New Tooling Jobs'!AG$13:AG$62,0)),INDEX(Reorders!A$13:A$62,MATCH(69-COUNTIFS('New Tooling Jobs'!A$13:A$62,"<>",'New Tooling Jobs'!E$13:E$62,"<>Completed"),Reorders!AC$13:AC$62,0))),"") | B78: =IFERROR(IF(69<=COUNTIFS('New Tooling Jobs'!A$13:A$62,"<>",'New Tooling Jobs'!E$13:E$62,"<>Completed"),IF(INDEX('New Tooling Jobs'!A$13:A$62,MATCH(69,'New Tooling Jobs'!AG$13:AG$62,0))<>"","New Tooling",""),IF(INDEX(Reorders!A$13:A$62,MATCH(69-COUNTIFS('New Tooling Jobs'!A$13:A$62,"<>",'New Tooling Jobs'!E$13:E$62,"<>Completed"),Reorders!AC$13:AC$62,0))<>"","Reorder","")),"") | C78: =IFERROR(IF(69<=COUNTIFS('New Tooling Jobs'!A$13:A$62,"<>",'New Tooling Jobs'!E$13:E$62,"<>Completed"),INDEX('New Tooling Jobs'!B$13:B$62,MATCH(69,'New Tooling Jobs'!AG$13:AG$62,0)),INDEX(Reorders!B$13:B$62,MATCH(69-COUNTIFS('New Tooling Jobs'!A$13:A$62,"<>",'New Tooling Jobs'!E$13:E$62,"<>Completed"),Reorders!AC$13:AC$62,0))),"") | D78: =IFERROR(IF(69<=COUNTIFS('New Tooling Jobs'!A$13:A$62,"<>",'New Tooling Jobs'!E$13:E$62,"<>Completed"),INDEX('New Tooling Jobs'!E$13:E$62,MATCH(69,'New Tooling Jobs'!AG$13:AG$62,0)),INDEX(Reorders!E$13:E$62,MATCH(69-COUNTIFS('New Tooling Jobs'!A$13:A$62,"<>",'New Tooling Jobs'!E$13:E$62,"<>Completed"),Reorders!AC$13:AC$62,0))),"") | E78: =IFERROR(IF(69<=COUNTIFS('New Tooling Jobs'!A$13:A$62,"<>",'New Tooling Jobs'!E$13:E$62,"<>Completed"),INDEX('New Tooling Jobs'!G$13:G$62,MATCH(69,'New Tooling Jobs'!AG$13:AG$62,0)),INDEX(Reorders!G$13:G$62,MATCH(69-COUNTIFS('New Tooling Jobs'!A$13:A$62,"<>",'New Tooling Jobs'!E$13:E$62,"<>Completed"),Reorders!AC$13:AC$62,0))),"") | F78: =IFERROR(IF(69<=COUNTIFS('New Tooling Jobs'!A$13:A$62,"<>",'New Tooling Jobs'!E$13:E$62,"<>Completed"),INDEX('New Tooling Jobs'!H$13:H$62,MATCH(69,'New Tooling Jobs'!AG$13:AG$62,0)),INDEX(Reorders!H$13:H$62,MATCH(69-COUNTIFS('New Tooling Jobs'!A$13:A$62,"<>",'New Tooling Jobs'!E$13:E$62,"<>Completed"),Reorders!AC$13:AC$62,0))),"") | G78: =IFERROR(IF(69<=COUNTIFS('New Tooling Jobs'!A$13:A$62,"<>",'New Tooling Jobs'!E$13:E$62,"<>Completed"),INDEX('New Tooling Jobs'!I$13:I$62,MATCH(69,'New Tooling Jobs'!AG$13:AG$62,0)),INDEX(Reorders!I$13:I$62,MATCH(69-COUNTIFS('New Tooling Jobs'!A$13:A$62,"<>",'New Tooling Jobs'!E$13:E$62,"<>Completed"),Reorders!AC$13:AC$62,0))),"")
A79: =IFERROR(IF(70<=COUNTIFS('New Tooling Jobs'!A$13:A$62,"<>",'New Tooling Jobs'!E$13:E$62,"<>Completed"),INDEX('New Tooling Jobs'!A$13:A$62,MATCH(70,'New Tooling Jobs'!AG$13:AG$62,0)),INDEX(Reorders!A$13:A$62,MATCH(70-COUNTIFS('New Tooling Jobs'!A$13:A$62,"<>",'New Tooling Jobs'!E$13:E$62,"<>Completed"),Reorders!AC$13:AC$62,0))),"") | B79: =IFERROR(IF(70<=COUNTIFS('New Tooling Jobs'!A$13:A$62,"<>",'New Tooling Jobs'!E$13:E$62,"<>Completed"),IF(INDEX('New Tooling Jobs'!A$13:A$62,MATCH(70,'New Tooling Jobs'!AG$13:AG$62,0))<>"","New Tooling",""),IF(INDEX(Reorders!A$13:A$62,MATCH(70-COUNTIFS('New Tooling Jobs'!A$13:A$62,"<>",'New Tooling Jobs'!E$13:E$62,"<>Completed"),Reorders!AC$13:AC$62,0))<>"","Reorder","")),"") | C79: =IFERROR(IF(70<=COUNTIFS('New Tooling Jobs'!A$13:A$62,"<>",'New Tooling Jobs'!E$13:E$62,"<>Completed"),INDEX('New Tooling Jobs'!B$13:B$62,MATCH(70,'New Tooling Jobs'!AG$13:AG$62,0)),INDEX(Reorders!B$13:B$62,MATCH(70-COUNTIFS('New Tooling Jobs'!A$13:A$62,"<>",'New Tooling Jobs'!E$13:E$62,"<>Completed"),Reorders!AC$13:AC$62,0))),"") | D79: =IFERROR(IF(70<=COUNTIFS('New Tooling Jobs'!A$13:A$62,"<>",'New Tooling Jobs'!E$13:E$62,"<>Completed"),INDEX('New Tooling Jobs'!E$13:E$62,MATCH(70,'New Tooling Jobs'!AG$13:AG$62,0)),INDEX(Reorders!E$13:E$62,MATCH(70-COUNTIFS('New Tooling Jobs'!A$13:A$62,"<>",'New Tooling Jobs'!E$13:E$62,"<>Completed"),Reorders!AC$13:AC$62,0))),"") | E79: =IFERROR(IF(70<=COUNTIFS('New Tooling Jobs'!A$13:A$62,"<>",'New Tooling Jobs'!E$13:E$62,"<>Completed"),INDEX('New Tooling Jobs'!G$13:G$62,MATCH(70,'New Tooling Jobs'!AG$13:AG$62,0)),INDEX(Reorders!G$13:G$62,MATCH(70-COUNTIFS('New Tooling Jobs'!A$13:A$62,"<>",'New Tooling Jobs'!E$13:E$62,"<>Completed"),Reorders!AC$13:AC$62,0))),"") | F79: =IFERROR(IF(70<=COUNTIFS('New Tooling Jobs'!A$13:A$62,"<>",'New Tooling Jobs'!E$13:E$62,"<>Completed"),INDEX('New Tooling Jobs'!H$13:H$62,MATCH(70,'New Tooling Jobs'!AG$13:AG$62,0)),INDEX(Reorders!H$13:H$62,MATCH(70-COUNTIFS('New Tooling Jobs'!A$13:A$62,"<>",'New Tooling Jobs'!E$13:E$62,"<>Completed"),Reorders!AC$13:AC$62,0))),"") | G79: =IFERROR(IF(70<=COUNTIFS('New Tooling Jobs'!A$13:A$62,"<>",'New Tooling Jobs'!E$13:E$62,"<>Completed"),INDEX('New Tooling Jobs'!I$13:I$62,MATCH(70,'New Tooling Jobs'!AG$13:AG$62,0)),INDEX(Reorders!I$13:I$62,MATCH(70-COUNTIFS('New Tooling Jobs'!A$13:A$62,"<>",'New Tooling Jobs'!E$13:E$62,"<>Completed"),Reorders!AC$13:AC$62,0))),"")
A80: =IFERROR(IF(71<=COUNTIFS('New Tooling Jobs'!A$13:A$62,"<>",'New Tooling Jobs'!E$13:E$62,"<>Completed"),INDEX('New Tooling Jobs'!A$13:A$62,MATCH(71,'New Tooling Jobs'!AG$13:AG$62,0)),INDEX(Reorders!A$13:A$62,MATCH(71-COUNTIFS('New Tooling Jobs'!A$13:A$62,"<>",'New Tooling Jobs'!E$13:E$62,"<>Completed"),Reorders!AC$13:AC$62,0))),"") | B80: =IFERROR(IF(71<=COUNTIFS('New Tooling Jobs'!A$13:A$62,"<>",'New Tooling Jobs'!E$13:E$62,"<>Completed"),IF(INDEX('New Tooling Jobs'!A$13:A$62,MATCH(71,'New Tooling Jobs'!AG$13:AG$62,0))<>"","New Tooling",""),IF(INDEX(Reorders!A$13:A$62,MATCH(71-COUNTIFS('New Tooling Jobs'!A$13:A$62,"<>",'New Tooling Jobs'!E$13:E$62,"<>Completed"),Reorders!AC$13:AC$62,0))<>"","Reorder","")),"") | C80: =IFERROR(IF(71<=COUNTIFS('New Tooling Jobs'!A$13:A$62,"<>",'New Tooling Jobs'!E$13:E$62,"<>Completed"),INDEX('New Tooling Jobs'!B$13:B$62,MATCH(71,'New Tooling Jobs'!AG$13:AG$62,0)),INDEX(Reorders!B$13:B$62,MATCH(71-COUNTIFS('New Tooling Jobs'!A$13:A$62,"<>",'New Tooling Jobs'!E$13:E$62,"<>Completed"),Reorders!AC$13:AC$62,0))),"") | D80: =IFERROR(IF(71<=COUNTIFS('New Tooling Jobs'!A$13:A$62,"<>",'New Tooling Jobs'!E$13:E$62,"<>Completed"),INDEX('New Tooling Jobs'!E$13:E$62,MATCH(71,'New Tooling Jobs'!AG$13:AG$62,0)),INDEX(Reorders!E$13:E$62,MATCH(71-COUNTIFS('New Tooling Jobs'!A$13:A$62,"<>",'New Tooling Jobs'!E$13:E$62,"<>Completed"),Reorders!AC$13:AC$62,0))),"") | E80: =IFERROR(IF(71<=COUNTIFS('New Tooling Jobs'!A$13:A$62,"<>",'New Tooling Jobs'!E$13:E$62,"<>Completed"),INDEX('New Tooling Jobs'!G$13:G$62,MATCH(71,'New Tooling Jobs'!AG$13:AG$62,0)),INDEX(Reorders!G$13:G$62,MATCH(71-COUNTIFS('New Tooling Jobs'!A$13:A$62,"<>",'New Tooling Jobs'!E$13:E$62,"<>Completed"),Reorders!AC$13:AC$62,0))),"") | F80: =IFERROR(IF(71<=COUNTIFS('New Tooling Jobs'!A$13:A$62,"<>",'New Tooling Jobs'!E$13:E$62,"<>Completed"),INDEX('New Tooling Jobs'!H$13:H$62,MATCH(71,'New Tooling Jobs'!AG$13:AG$62,0)),INDEX(Reorders!H$13:H$62,MATCH(71-COUNTIFS('New Tooling Jobs'!A$13:A$62,"<>",'New Tooling Jobs'!E$13:E$62,"<>Completed"),Reorders!AC$13:AC$62,0))),"") | G80: =IFERROR(IF(71<=COUNTIFS('New Tooling Jobs'!A$13:A$62,"<>",'New Tooling Jobs'!E$13:E$62,"<>Completed"),INDEX('New Tooling Jobs'!I$13:I$62,MATCH(71,'New Tooling Jobs'!AG$13:AG$62,0)),INDEX(Reorders!I$13:I$62,MATCH(71-COUNTIFS('New Tooling Jobs'!A$13:A$62,"<>",'New Tooling Jobs'!E$13:E$62,"<>Completed"),Reorders!AC$13:AC$62,0))),"")
A81: =IFERROR(IF(72<=COUNTIFS('New Tooling Jobs'!A$13:A$62,"<>",'New Tooling Jobs'!E$13:E$62,"<>Completed"),INDEX('New Tooling Jobs'!A$13:A$62,MATCH(72,'New Tooling Jobs'!AG$13:AG$62,0)),INDEX(Reorders!A$13:A$62,MATCH(72-COUNTIFS('New Tooling Jobs'!A$13:A$62,"<>",'New Tooling Jobs'!E$13:E$62,"<>Completed"),Reorders!AC$13:AC$62,0))),"") | B81: =IFERROR(IF(72<=COUNTIFS('New Tooling Jobs'!A$13:A$62,"<>",'New Tooling Jobs'!E$13:E$62,"<>Completed"),IF(INDEX('New Tooling Jobs'!A$13:A$62,MATCH(72,'New Tooling Jobs'!AG$13:AG$62,0))<>"","New Tooling",""),IF(INDEX(Reorders!A$13:A$62,MATCH(72-COUNTIFS('New Tooling Jobs'!A$13:A$62,"<>",'New Tooling Jobs'!E$13:E$62,"<>Completed"),Reorders!AC$13:AC$62,0))<>"","Reorder","")),"") | C81: =IFERROR(IF(72<=COUNTIFS('New Tooling Jobs'!A$13:A$62,"<>",'New Tooling Jobs'!E$13:E$62,"<>Completed"),INDEX('New Tooling Jobs'!B$13:B$62,MATCH(72,'New Tooling Jobs'!AG$13:AG$62,0)),INDEX(Reorders!B$13:B$62,MATCH(72-COUNTIFS('New Tooling Jobs'!A$13:A$62,"<>",'New Tooling Jobs'!E$13:E$62,"<>Completed"),Reorders!AC$13:AC$62,0))),"") | D81: =IFERROR(IF(72<=COUNTIFS('New Tooling Jobs'!A$13:A$62,"<>",'New Tooling Jobs'!E$13:E$62,"<>Completed"),INDEX('New Tooling Jobs'!E$13:E$62,MATCH(72,'New Tooling Jobs'!AG$13:AG$62,0)),INDEX(Reorders!E$13:E$62,MATCH(72-COUNTIFS('New Tooling Jobs'!A$13:A$62,"<>",'New Tooling Jobs'!E$13:E$62,"<>Completed"),Reorders!AC$13:AC$62,0))),"") | E81: =IFERROR(IF(72<=COUNTIFS('New Tooling Jobs'!A$13:A$62,"<>",'New Tooling Jobs'!E$13:E$62,"<>Completed"),INDEX('New Tooling Jobs'!G$13:G$62,MATCH(72,'New Tooling Jobs'!AG$13:AG$62,0)),INDEX(Reorders!G$13:G$62,MATCH(72-COUNTIFS('New Tooling Jobs'!A$13:A$62,"<>",'New Tooling Jobs'!E$13:E$62,"<>Completed"),Reorders!AC$13:AC$62,0))),"") | F81: =IFERROR(IF(72<=COUNTIFS('New Tooling Jobs'!A$13:A$62,"<>",'New Tooling Jobs'!E$13:E$62,"<>Completed"),INDEX('New Tooling Jobs'!H$13:H$62,MATCH(72,'New Tooling Jobs'!AG$13:AG$62,0)),INDEX(Reorders!H$13:H$62,MATCH(72-COUNTIFS('New Tooling Jobs'!A$13:A$62,"<>",'New Tooling Jobs'!E$13:E$62,"<>Completed"),Reorders!AC$13:AC$62,0))),"") | G81: =IFERROR(IF(72<=COUNTIFS('New Tooling Jobs'!A$13:A$62,"<>",'New Tooling Jobs'!E$13:E$62,"<>Completed"),INDEX('New Tooling Jobs'!I$13:I$62,MATCH(72,'New Tooling Jobs'!AG$13:AG$62,0)),INDEX(Reorders!I$13:I$62,MATCH(72-COUNTIFS('New Tooling Jobs'!A$13:A$62,"<>",'New Tooling Jobs'!E$13:E$62,"<>Completed"),Reorders!AC$13:AC$62,0))),"")
A82: =IFERROR(IF(73<=COUNTIFS('New Tooling Jobs'!A$13:A$62,"<>",'New Tooling Jobs'!E$13:E$62,"<>Completed"),INDEX('New Tooling Jobs'!A$13:A$62,MATCH(73,'New Tooling Jobs'!AG$13:AG$62,0)),INDEX(Reorders!A$13:A$62,MATCH(73-COUNTIFS('New Tooling Jobs'!A$13:A$62,"<>",'New Tooling Jobs'!E$13:E$62,"<>Completed"),Reorders!AC$13:AC$62,0))),"") | B82: =IFERROR(IF(73<=COUNTIFS('New Tooling Jobs'!A$13:A$62,"<>",'New Tooling Jobs'!E$13:E$62,"<>Completed"),IF(INDEX('New Tooling Jobs'!A$13:A$62,MATCH(73,'New Tooling Jobs'!AG$13:AG$62,0))<>"","New Tooling",""),IF(INDEX(Reorders!A$13:A$62,MATCH(73-COUNTIFS('New Tooling Jobs'!A$13:A$62,"<>",'New Tooling Jobs'!E$13:E$62,"<>Completed"),Reorders!AC$13:AC$62,0))<>"","Reorder","")),"") | C82: =IFERROR(IF(73<=COUNTIFS('New Tooling Jobs'!A$13:A$62,"<>",'New Tooling Jobs'!E$13:E$62,"<>Completed"),INDEX('New Tooling Jobs'!B$13:B$62,MATCH(73,'New Tooling Jobs'!AG$13:AG$62,0)),INDEX(Reorders!B$13:B$62,MATCH(73-COUNTIFS('New Tooling Jobs'!A$13:A$62,"<>",'New Tooling Jobs'!E$13:E$62,"<>Completed"),Reorders!AC$13:AC$62,0))),"") | D82: =IFERROR(IF(73<=COUNTIFS('New Tooling Jobs'!A$13:A$62,"<>",'New Tooling Jobs'!E$13:E$62,"<>Completed"),INDEX('New Tooling Jobs'!E$13:E$62,MATCH(73,'New Tooling Jobs'!AG$13:AG$62,0)),INDEX(Reorders!E$13:E$62,MATCH(73-COUNTIFS('New Tooling Jobs'!A$13:A$62,"<>",'New Tooling Jobs'!E$13:E$62,"<>Completed"),Reorders!AC$13:AC$62,0))),"") | E82: =IFERROR(IF(73<=COUNTIFS('New Tooling Jobs'!A$13:A$62,"<>",'New Tooling Jobs'!E$13:E$62,"<>Completed"),INDEX('New Tooling Jobs'!G$13:G$62,MATCH(73,'New Tooling Jobs'!AG$13:AG$62,0)),INDEX(Reorders!G$13:G$62,MATCH(73-COUNTIFS('New Tooling Jobs'!A$13:A$62,"<>",'New Tooling Jobs'!E$13:E$62,"<>Completed"),Reorders!AC$13:AC$62,0))),"") | F82: =IFERROR(IF(73<=COUNTIFS('New Tooling Jobs'!A$13:A$62,"<>",'New Tooling Jobs'!E$13:E$62,"<>Completed"),INDEX('New Tooling Jobs'!H$13:H$62,MATCH(73,'New Tooling Jobs'!AG$13:AG$62,0)),INDEX(Reorders!H$13:H$62,MATCH(73-COUNTIFS('New Tooling Jobs'!A$13:A$62,"<>",'New Tooling Jobs'!E$13:E$62,"<>Completed"),Reorders!AC$13:AC$62,0))),"") | G82: =IFERROR(IF(73<=COUNTIFS('New Tooling Jobs'!A$13:A$62,"<>",'New Tooling Jobs'!E$13:E$62,"<>Completed"),INDEX('New Tooling Jobs'!I$13:I$62,MATCH(73,'New Tooling Jobs'!AG$13:AG$62,0)),INDEX(Reorders!I$13:I$62,MATCH(73-COUNTIFS('New Tooling Jobs'!A$13:A$62,"<>",'New Tooling Jobs'!E$13:E$62,"<>Completed"),Reorders!AC$13:AC$62,0))),"")
A83: =IFERROR(IF(74<=COUNTIFS('New Tooling Jobs'!A$13:A$62,"<>",'New Tooling Jobs'!E$13:E$62,"<>Completed"),INDEX('New Tooling Jobs'!A$13:A$62,MATCH(74,'New Tooling Jobs'!AG$13:AG$62,0)),INDEX(Reorders!A$13:A$62,MATCH(74-COUNTIFS('New Tooling Jobs'!A$13:A$62,"<>",'New Tooling Jobs'!E$13:E$62,"<>Completed"),Reorders!AC$13:AC$62,0))),"") | B83: =IFERROR(IF(74<=COUNTIFS('New Tooling Jobs'!A$13:A$62,"<>",'New Tooling Jobs'!E$13:E$62,"<>Completed"),IF(INDEX('New Tooling Jobs'!A$13:A$62,MATCH(74,'New Tooling Jobs'!AG$13:AG$62,0))<>"","New Tooling",""),IF(INDEX(Reorders!A$13:A$62,MATCH(74-COUNTIFS('New Tooling Jobs'!A$13:A$62,"<>",'New Tooling Jobs'!E$13:E$62,"<>Completed"),Reorders!AC$13:AC$62,0))<>"","Reorder","")),"") | C83: =IFERROR(IF(74<=COUNTIFS('New Tooling Jobs'!A$13:A$62,"<>",'New Tooling Jobs'!E$13:E$62,"<>Completed"),INDEX('New Tooling Jobs'!B$13:B$62,MATCH(74,'New Tooling Jobs'!AG$13:AG$62,0)),INDEX(Reorders!B$13:B$62,MATCH(74-COUNTIFS('New Tooling Jobs'!A$13:A$62,"<>",'New Tooling Jobs'!E$13:E$62,"<>Completed"),Reorders!AC$13:AC$62,0))),"") | D83: =IFERROR(IF(74<=COUNTIFS('New Tooling Jobs'!A$13:A$62,"<>",'New Tooling Jobs'!E$13:E$62,"<>Completed"),INDEX('New Tooling Jobs'!E$13:E$62,MATCH(74,'New Tooling Jobs'!AG$13:AG$62,0)),INDEX(Reorders!E$13:E$62,MATCH(74-COUNTIFS('New Tooling Jobs'!A$13:A$62,"<>",'New Tooling Jobs'!E$13:E$62,"<>Completed"),Reorders!AC$13:AC$62,0))),"") | E83: =IFERROR(IF(74<=COUNTIFS('New Tooling Jobs'!A$13:A$62,"<>",'New Tooling Jobs'!E$13:E$62,"<>Completed"),INDEX('New Tooling Jobs'!G$13:G$62,MATCH(74,'New Tooling Jobs'!AG$13:AG$62,0)),INDEX(Reorders!G$13:G$62,MATCH(74-COUNTIFS('New Tooling Jobs'!A$13:A$62,"<>",'New Tooling Jobs'!E$13:E$62,"<>Completed"),Reorders!AC$13:AC$62,0))),"") | F83: =IFERROR(IF(74<=COUNTIFS('New Tooling Jobs'!A$13:A$62,"<>",'New Tooling Jobs'!E$13:E$62,"<>Completed"),INDEX('New Tooling Jobs'!H$13:H$62,MATCH(74,'New Tooling Jobs'!AG$13:AG$62,0)),INDEX(Reorders!H$13:H$62,MATCH(74-COUNTIFS('New Tooling Jobs'!A$13:A$62,"<>",'New Tooling Jobs'!E$13:E$62,"<>Completed"),Reorders!AC$13:AC$62,0))),"") | G83: =IFERROR(IF(74<=COUNTIFS('New Tooling Jobs'!A$13:A$62,"<>",'New Tooling Jobs'!E$13:E$62,"<>Completed"),INDEX('New Tooling Jobs'!I$13:I$62,MATCH(74,'New Tooling Jobs'!AG$13:AG$62,0)),INDEX(Reorders!I$13:I$62,MATCH(74-COUNTIFS('New Tooling Jobs'!A$13:A$62,"<>",'New Tooling Jobs'!E$13:E$62,"<>Completed"),Reorders!AC$13:AC$62,0))),"")
A84: =IFERROR(IF(75<=COUNTIFS('New Tooling Jobs'!A$13:A$62,"<>",'New Tooling Jobs'!E$13:E$62,"<>Completed"),INDEX('New Tooling Jobs'!A$13:A$62,MATCH(75,'New Tooling Jobs'!AG$13:AG$62,0)),INDEX(Reorders!A$13:A$62,MATCH(75-COUNTIFS('New Tooling Jobs'!A$13:A$62,"<>",'New Tooling Jobs'!E$13:E$62,"<>Completed"),Reorders!AC$13:AC$62,0))),"") | B84: =IFERROR(IF(75<=COUNTIFS('New Tooling Jobs'!A$13:A$62,"<>",'New Tooling Jobs'!E$13:E$62,"<>Completed"),IF(INDEX('New Tooling Jobs'!A$13:A$62,MATCH(75,'New Tooling Jobs'!AG$13:AG$62,0))<>"","New Tooling",""),IF(INDEX(Reorders!A$13:A$62,MATCH(75-COUNTIFS('New Tooling Jobs'!A$13:A$62,"<>",'New Tooling Jobs'!E$13:E$62,"<>Completed"),Reorders!AC$13:AC$62,0))<>"","Reorder","")),"") | C84: =IFERROR(IF(75<=COUNTIFS('New Tooling Jobs'!A$13:A$62,"<>",'New Tooling Jobs'!E$13:E$62,"<>Completed"),INDEX('New Tooling Jobs'!B$13:B$62,MATCH(75,'New Tooling Jobs'!AG$13:AG$62,0)),INDEX(Reorders!B$13:B$62,MATCH(75-COUNTIFS('New Tooling Jobs'!A$13:A$62,"<>",'New Tooling Jobs'!E$13:E$62,"<>Completed"),Reorders!AC$13:AC$62,0))),"") | D84: =IFERROR(IF(75<=COUNTIFS('New Tooling Jobs'!A$13:A$62,"<>",'New Tooling Jobs'!E$13:E$62,"<>Completed"),INDEX('New Tooling Jobs'!E$13:E$62,MATCH(75,'New Tooling Jobs'!AG$13:AG$62,0)),INDEX(Reorders!E$13:E$62,MATCH(75-COUNTIFS('New Tooling Jobs'!A$13:A$62,"<>",'New Tooling Jobs'!E$13:E$62,"<>Completed"),Reorders!AC$13:AC$62,0))),"") | E84: =IFERROR(IF(75<=COUNTIFS('New Tooling Jobs'!A$13:A$62,"<>",'New Tooling Jobs'!E$13:E$62,"<>Completed"),INDEX('New Tooling Jobs'!G$13:G$62,MATCH(75,'New Tooling Jobs'!AG$13:AG$62,0)),INDEX(Reorders!G$13:G$62,MATCH(75-COUNTIFS('New Tooling Jobs'!A$13:A$62,"<>",'New Tooling Jobs'!E$13:E$62,"<>Completed"),Reorders!AC$13:AC$62,0))),"") | F84: =IFERROR(IF(75<=COUNTIFS('New Tooling Jobs'!A$13:A$62,"<>",'New Tooling Jobs'!E$13:E$62,"<>Completed"),INDEX('New Tooling Jobs'!H$13:H$62,MATCH(75,'New Tooling Jobs'!AG$13:AG$62,0)),INDEX(Reorders!H$13:H$62,MATCH(75-COUNTIFS('New Tooling Jobs'!A$13:A$62,"<>",'New Tooling Jobs'!E$13:E$62,"<>Completed"),Reorders!AC$13:AC$62,0))),"") | G84: =IFERROR(IF(75<=COUNTIFS('New Tooling Jobs'!A$13:A$62,"<>",'New Tooling Jobs'!E$13:E$62,"<>Completed"),INDEX('New Tooling Jobs'!I$13:I$62,MATCH(75,'New Tooling Jobs'!AG$13:AG$62,0)),INDEX(Reorders!I$13:I$62,MATCH(75-COUNTIFS('New Tooling Jobs'!A$13:A$62,"<>",'New Tooling Jobs'!E$13:E$62,"<>Completed"),Reorders!AC$13:AC$62,0))),"")
A85: =IFERROR(IF(76<=COUNTIFS('New Tooling Jobs'!A$13:A$62,"<>",'New Tooling Jobs'!E$13:E$62,"<>Completed"),INDEX('New Tooling Jobs'!A$13:A$62,MATCH(76,'New Tooling Jobs'!AG$13:AG$62,0)),INDEX(Reorders!A$13:A$62,MATCH(76-COUNTIFS('New Tooling Jobs'!A$13:A$62,"<>",'New Tooling Jobs'!E$13:E$62,"<>Completed"),Reorders!AC$13:AC$62,0))),"") | B85: =IFERROR(IF(76<=COUNTIFS('New Tooling Jobs'!A$13:A$62,"<>",'New Tooling Jobs'!E$13:E$62,"<>Completed"),IF(INDEX('New Tooling Jobs'!A$13:A$62,MATCH(76,'New Tooling Jobs'!AG$13:AG$62,0))<>"","New Tooling",""),IF(INDEX(Reorders!A$13:A$62,MATCH(76-COUNTIFS('New Tooling Jobs'!A$13:A$62,"<>",'New Tooling Jobs'!E$13:E$62,"<>Completed"),Reorders!AC$13:AC$62,0))<>"","Reorder","")),"") | C85: =IFERROR(IF(76<=COUNTIFS('New Tooling Jobs'!A$13:A$62,"<>",'New Tooling Jobs'!E$13:E$62,"<>Completed"),INDEX('New Tooling Jobs'!B$13:B$62,MATCH(76,'New Tooling Jobs'!AG$13:AG$62,0)),INDEX(Reorders!B$13:B$62,MATCH(76-COUNTIFS('New Tooling Jobs'!A$13:A$62,"<>",'New Tooling Jobs'!E$13:E$62,"<>Completed"),Reorders!AC$13:AC$62,0))),"") | D85: =IFERROR(IF(76<=COUNTIFS('New Tooling Jobs'!A$13:A$62,"<>",'New Tooling Jobs'!E$13:E$62,"<>Completed"),INDEX('New Tooling Jobs'!E$13:E$62,MATCH(76,'New Tooling Jobs'!AG$13:AG$62,0)),INDEX(Reorders!E$13:E$62,MATCH(76-COUNTIFS('New Tooling Jobs'!A$13:A$62,"<>",'New Tooling Jobs'!E$13:E$62,"<>Completed"),Reorders!AC$13:AC$62,0))),"") | E85: =IFERROR(IF(76<=COUNTIFS('New Tooling Jobs'!A$13:A$62,"<>",'New Tooling Jobs'!E$13:E$62,"<>Completed"),INDEX('New Tooling Jobs'!G$13:G$62,MATCH(76,'New Tooling Jobs'!AG$13:AG$62,0)),INDEX(Reorders!G$13:G$62,MATCH(76-COUNTIFS('New Tooling Jobs'!A$13:A$62,"<>",'New Tooling Jobs'!E$13:E$62,"<>Completed"),Reorders!AC$13:AC$62,0))),"") | F85: =IFERROR(IF(76<=COUNTIFS('New Tooling Jobs'!A$13:A$62,"<>",'New Tooling Jobs'!E$13:E$62,"<>Completed"),INDEX('New Tooling Jobs'!H$13:H$62,MATCH(76,'New Tooling Jobs'!AG$13:AG$62,0)),INDEX(Reorders!H$13:H$62,MATCH(76-COUNTIFS('New Tooling Jobs'!A$13:A$62,"<>",'New Tooling Jobs'!E$13:E$62,"<>Completed"),Reorders!AC$13:AC$62,0))),"") | G85: =IFERROR(IF(76<=COUNTIFS('New Tooling Jobs'!A$13:A$62,"<>",'New Tooling Jobs'!E$13:E$62,"<>Completed"),INDEX('New Tooling Jobs'!I$13:I$62,MATCH(76,'New Tooling Jobs'!AG$13:AG$62,0)),INDEX(Reorders!I$13:I$62,MATCH(76-COUNTIFS('New Tooling Jobs'!A$13:A$62,"<>",'New Tooling Jobs'!E$13:E$62,"<>Completed"),Reorders!AC$13:AC$62,0))),"")
A86: =IFERROR(IF(77<=COUNTIFS('New Tooling Jobs'!A$13:A$62,"<>",'New Tooling Jobs'!E$13:E$62,"<>Completed"),INDEX('New Tooling Jobs'!A$13:A$62,MATCH(77,'New Tooling Jobs'!AG$13:AG$62,0)),INDEX(Reorders!A$13:A$62,MATCH(77-COUNTIFS('New Tooling Jobs'!A$13:A$62,"<>",'New Tooling Jobs'!E$13:E$62,"<>Completed"),Reorders!AC$13:AC$62,0))),"") | B86: =IFERROR(IF(77<=COUNTIFS('New Tooling Jobs'!A$13:A$62,"<>",'New Tooling Jobs'!E$13:E$62,"<>Completed"),IF(INDEX('New Tooling Jobs'!A$13:A$62,MATCH(77,'New Tooling Jobs'!AG$13:AG$62,0))<>"","New Tooling",""),IF(INDEX(Reorders!A$13:A$62,MATCH(77-COUNTIFS('New Tooling Jobs'!A$13:A$62,"<>",'New Tooling Jobs'!E$13:E$62,"<>Completed"),Reorders!AC$13:AC$62,0))<>"","Reorder","")),"") | C86: =IFERROR(IF(77<=COUNTIFS('New Tooling Jobs'!A$13:A$62,"<>",'New Tooling Jobs'!E$13:E$62,"<>Completed"),INDEX('New Tooling Jobs'!B$13:B$62,MATCH(77,'New Tooling Jobs'!AG$13:AG$62,0)),INDEX(Reorders!B$13:B$62,MATCH(77-COUNTIFS('New Tooling Jobs'!A$13:A$62,"<>",'New Tooling Jobs'!E$13:E$62,"<>Completed"),Reorders!AC$13:AC$62,0))),"") | D86: =IFERROR(IF(77<=COUNTIFS('New Tooling Jobs'!A$13:A$62,"<>",'New Tooling Jobs'!E$13:E$62,"<>Completed"),INDEX('New Tooling Jobs'!E$13:E$62,MATCH(77,'New Tooling Jobs'!AG$13:AG$62,0)),INDEX(Reorders!E$13:E$62,MATCH(77-COUNTIFS('New Tooling Jobs'!A$13:A$62,"<>",'New Tooling Jobs'!E$13:E$62,"<>Completed"),Reorders!AC$13:AC$62,0))),"") | E86: =IFERROR(IF(77<=COUNTIFS('New Tooling Jobs'!A$13:A$62,"<>",'New Tooling Jobs'!E$13:E$62,"<>Completed"),INDEX('New Tooling Jobs'!G$13:G$62,MATCH(77,'New Tooling Jobs'!AG$13:AG$62,0)),INDEX(Reorders!G$13:G$62,MATCH(77-COUNTIFS('New Tooling Jobs'!A$13:A$62,"<>",'New Tooling Jobs'!E$13:E$62,"<>Completed"),Reorders!AC$13:AC$62,0))),"") | F86: =IFERROR(IF(77<=COUNTIFS('New Tooling Jobs'!A$13:A$62,"<>",'New Tooling Jobs'!E$13:E$62,"<>Completed"),INDEX('New Tooling Jobs'!H$13:H$62,MATCH(77,'New Tooling Jobs'!AG$13:AG$62,0)),INDEX(Reorders!H$13:H$62,MATCH(77-COUNTIFS('New Tooling Jobs'!A$13:A$62,"<>",'New Tooling Jobs'!E$13:E$62,"<>Completed"),Reorders!AC$13:AC$62,0))),"") | G86: =IFERROR(IF(77<=COUNTIFS('New Tooling Jobs'!A$13:A$62,"<>",'New Tooling Jobs'!E$13:E$62,"<>Completed"),INDEX('New Tooling Jobs'!I$13:I$62,MATCH(77,'New Tooling Jobs'!AG$13:AG$62,0)),INDEX(Reorders!I$13:I$62,MATCH(77-COUNTIFS('New Tooling Jobs'!A$13:A$62,"<>",'New Tooling Jobs'!E$13:E$62,"<>Completed"),Reorders!AC$13:AC$62,0))),"")
A87: =IFERROR(IF(78<=COUNTIFS('New Tooling Jobs'!A$13:A$62,"<>",'New Tooling Jobs'!E$13:E$62,"<>Completed"),INDEX('New Tooling Jobs'!A$13:A$62,MATCH(78,'New Tooling Jobs'!AG$13:AG$62,0)),INDEX(Reorders!A$13:A$62,MATCH(78-COUNTIFS('New Tooling Jobs'!A$13:A$62,"<>",'New Tooling Jobs'!E$13:E$62,"<>Completed"),Reorders!AC$13:AC$62,0))),"") | B87: =IFERROR(IF(78<=COUNTIFS('New Tooling Jobs'!A$13:A$62,"<>",'New Tooling Jobs'!E$13:E$62,"<>Completed"),IF(INDEX('New Tooling Jobs'!A$13:A$62,MATCH(78,'New Tooling Jobs'!AG$13:AG$62,0))<>"","New Tooling",""),IF(INDEX(Reorders!A$13:A$62,MATCH(78-COUNTIFS('New Tooling Jobs'!A$13:A$62,"<>",'New Tooling Jobs'!E$13:E$62,"<>Completed"),Reorders!AC$13:AC$62,0))<>"","Reorder","")),"") | C87: =IFERROR(IF(78<=COUNTIFS('New Tooling Jobs'!A$13:A$62,"<>",'New Tooling Jobs'!E$13:E$62,"<>Completed"),INDEX('New Tooling Jobs'!B$13:B$62,MATCH(78,'New Tooling Jobs'!AG$13:AG$62,0)),INDEX(Reorders!B$13:B$62,MATCH(78-COUNTIFS('New Tooling Jobs'!A$13:A$62,"<>",'New Tooling Jobs'!E$13:E$62,"<>Completed"),Reorders!AC$13:AC$62,0))),"") | D87: =IFERROR(IF(78<=COUNTIFS('New Tooling Jobs'!A$13:A$62,"<>",'New Tooling Jobs'!E$13:E$62,"<>Completed"),INDEX('New Tooling Jobs'!E$13:E$62,MATCH(78,'New Tooling Jobs'!AG$13:AG$62,0)),INDEX(Reorders!E$13:E$62,MATCH(78-COUNTIFS('New Tooling Jobs'!A$13:A$62,"<>",'New Tooling Jobs'!E$13:E$62,"<>Completed"),Reorders!AC$13:AC$62,0))),"") | E87: =IFERROR(IF(78<=COUNTIFS('New Tooling Jobs'!A$13:A$62,"<>",'New Tooling Jobs'!E$13:E$62,"<>Completed"),INDEX('New Tooling Jobs'!G$13:G$62,MATCH(78,'New Tooling Jobs'!AG$13:AG$62,0)),INDEX(Reorders!G$13:G$62,MATCH(78-COUNTIFS('New Tooling Jobs'!A$13:A$62,"<>",'New Tooling Jobs'!E$13:E$62,"<>Completed"),Reorders!AC$13:AC$62,0))),"") | F87: =IFERROR(IF(78<=COUNTIFS('New Tooling Jobs'!A$13:A$62,"<>",'New Tooling Jobs'!E$13:E$62,"<>Completed"),INDEX('New Tooling Jobs'!H$13:H$62,MATCH(78,'New Tooling Jobs'!AG$13:AG$62,0)),INDEX(Reorders!H$13:H$62,MATCH(78-COUNTIFS('New Tooling Jobs'!A$13:A$62,"<>",'New Tooling Jobs'!E$13:E$62,"<>Completed"),Reorders!AC$13:AC$62,0))),"") | G87: =IFERROR(IF(78<=COUNTIFS('New Tooling Jobs'!A$13:A$62,"<>",'New Tooling Jobs'!E$13:E$62,"<>Completed"),INDEX('New Tooling Jobs'!I$13:I$62,MATCH(78,'New Tooling Jobs'!AG$13:AG$62,0)),INDEX(Reorders!I$13:I$62,MATCH(78-COUNTIFS('New Tooling Jobs'!A$13:A$62,"<>",'New Tooling Jobs'!E$13:E$62,"<>Completed"),Reorders!AC$13:AC$62,0))),"")
A88: =IFERROR(IF(79<=COUNTIFS('New Tooling Jobs'!A$13:A$62,"<>",'New Tooling Jobs'!E$13:E$62,"<>Completed"),INDEX('New Tooling Jobs'!A$13:A$62,MATCH(79,'New Tooling Jobs'!AG$13:AG$62,0)),INDEX(Reorders!A$13:A$62,MATCH(79-COUNTIFS('New Tooling Jobs'!A$13:A$62,"<>",'New Tooling Jobs'!E$13:E$62,"<>Completed"),Reorders!AC$13:AC$62,0))),"") | B88: =IFERROR(IF(79<=COUNTIFS('New Tooling Jobs'!A$13:A$62,"<>",'New Tooling Jobs'!E$13:E$62,"<>Completed"),IF(INDEX('New Tooling Jobs'!A$13:A$62,MATCH(79,'New Tooling Jobs'!AG$13:AG$62,0))<>"","New Tooling",""),IF(INDEX(Reorders!A$13:A$62,MATCH(79-COUNTIFS('New Tooling Jobs'!A$13:A$62,"<>",'New Tooling Jobs'!E$13:E$62,"<>Completed"),Reorders!AC$13:AC$62,0))<>"","Reorder","")),"") | C88: =IFERROR(IF(79<=COUNTIFS('New Tooling Jobs'!A$13:A$62,"<>",'New Tooling Jobs'!E$13:E$62,"<>Completed"),INDEX('New Tooling Jobs'!B$13:B$62,MATCH(79,'New Tooling Jobs'!AG$13:AG$62,0)),INDEX(Reorders!B$13:B$62,MATCH(79-COUNTIFS('New Tooling Jobs'!A$13:A$62,"<>",'New Tooling Jobs'!E$13:E$62,"<>Completed"),Reorders!AC$13:AC$62,0))),"") | D88: =IFERROR(IF(79<=COUNTIFS('New Tooling Jobs'!A$13:A$62,"<>",'New Tooling Jobs'!E$13:E$62,"<>Completed"),INDEX('New Tooling Jobs'!E$13:E$62,MATCH(79,'New Tooling Jobs'!AG$13:AG$62,0)),INDEX(Reorders!E$13:E$62,MATCH(79-COUNTIFS('New Tooling Jobs'!A$13:A$62,"<>",'New Tooling Jobs'!E$13:E$62,"<>Completed"),Reorders!AC$13:AC$62,0))),"") | E88: =IFERROR(IF(79<=COUNTIFS('New Tooling Jobs'!A$13:A$62,"<>",'New Tooling Jobs'!E$13:E$62,"<>Completed"),INDEX('New Tooling Jobs'!G$13:G$62,MATCH(79,'New Tooling Jobs'!AG$13:AG$62,0)),INDEX(Reorders!G$13:G$62,MATCH(79-COUNTIFS('New Tooling Jobs'!A$13:A$62,"<>",'New Tooling Jobs'!E$13:E$62,"<>Completed"),Reorders!AC$13:AC$62,0))),"") | F88: =IFERROR(IF(79<=COUNTIFS('New Tooling Jobs'!A$13:A$62,"<>",'New Tooling Jobs'!E$13:E$62,"<>Completed"),INDEX('New Tooling Jobs'!H$13:H$62,MATCH(79,'New Tooling Jobs'!AG$13:AG$62,0)),INDEX(Reorders!H$13:H$62,MATCH(79-COUNTIFS('New Tooling Jobs'!A$13:A$62,"<>",'New Tooling Jobs'!E$13:E$62,"<>Completed"),Reorders!AC$13:AC$62,0))),"") | G88: =IFERROR(IF(79<=COUNTIFS('New Tooling Jobs'!A$13:A$62,"<>",'New Tooling Jobs'!E$13:E$62,"<>Completed"),INDEX('New Tooling Jobs'!I$13:I$62,MATCH(79,'New Tooling Jobs'!AG$13:AG$62,0)),INDEX(Reorders!I$13:I$62,MATCH(79-COUNTIFS('New Tooling Jobs'!A$13:A$62,"<>",'New Tooling Jobs'!E$13:E$62,"<>Completed"),Reorders!AC$13:AC$62,0))),"")
A89: =IFERROR(IF(80<=COUNTIFS('New Tooling Jobs'!A$13:A$62,"<>",'New Tooling Jobs'!E$13:E$62,"<>Completed"),INDEX('New Tooling Jobs'!A$13:A$62,MATCH(80,'New Tooling Jobs'!AG$13:AG$62,0)),INDEX(Reorders!A$13:A$62,MATCH(80-COUNTIFS('New Tooling Jobs'!A$13:A$62,"<>",'New Tooling Jobs'!E$13:E$62,"<>Completed"),Reorders!AC$13:AC$62,0))),"") | B89: =IFERROR(IF(80<=COUNTIFS('New Tooling Jobs'!A$13:A$62,"<>",'New Tooling Jobs'!E$13:E$62,"<>Completed"),IF(INDEX('New Tooling Jobs'!A$13:A$62,MATCH(80,'New Tooling Jobs'!AG$13:AG$62,0))<>"","New Tooling",""),IF(INDEX(Reorders!A$13:A$62,MATCH(80-COUNTIFS('New Tooling Jobs'!A$13:A$62,"<>",'New Tooling Jobs'!E$13:E$62,"<>Completed"),Reorders!AC$13:AC$62,0))<>"","Reorder","")),"") | C89: =IFERROR(IF(80<=COUNTIFS('New Tooling Jobs'!A$13:A$62,"<>",'New Tooling Jobs'!E$13:E$62,"<>Completed"),INDEX('New Tooling Jobs'!B$13:B$62,MATCH(80,'New Tooling Jobs'!AG$13:AG$62,0)),INDEX(Reorders!B$13:B$62,MATCH(80-COUNTIFS('New Tooling Jobs'!A$13:A$62,"<>",'New Tooling Jobs'!E$13:E$62,"<>Completed"),Reorders!AC$13:AC$62,0))),"") | D89: =IFERROR(IF(80<=COUNTIFS('New Tooling Jobs'!A$13:A$62,"<>",'New Tooling Jobs'!E$13:E$62,"<>Completed"),INDEX('New Tooling Jobs'!E$13:E$62,MATCH(80,'New Tooling Jobs'!AG$13:AG$62,0)),INDEX(Reorders!E$13:E$62,MATCH(80-COUNTIFS('New Tooling Jobs'!A$13:A$62,"<>",'New Tooling Jobs'!E$13:E$62,"<>Completed"),Reorders!AC$13:AC$62,0))),"") | E89: =IFERROR(IF(80<=COUNTIFS('New Tooling Jobs'!A$13:A$62,"<>",'New Tooling Jobs'!E$13:E$62,"<>Completed"),INDEX('New Tooling Jobs'!G$13:G$62,MATCH(80,'New Tooling Jobs'!AG$13:AG$62,0)),INDEX(Reorders!G$13:G$62,MATCH(80-COUNTIFS('New Tooling Jobs'!A$13:A$62,"<>",'New Tooling Jobs'!E$13:E$62,"<>Completed"),Reorders!AC$13:AC$62,0))),"") | F89: =IFERROR(IF(80<=COUNTIFS('New Tooling Jobs'!A$13:A$62,"<>",'New Tooling Jobs'!E$13:E$62,"<>Completed"),INDEX('New Tooling Jobs'!H$13:H$62,MATCH(80,'New Tooling Jobs'!AG$13:AG$62,0)),INDEX(Reorders!H$13:H$62,MATCH(80-COUNTIFS('New Tooling Jobs'!A$13:A$62,"<>",'New Tooling Jobs'!E$13:E$62,"<>Completed"),Reorders!AC$13:AC$62,0))),"") | G89: =IFERROR(IF(80<=COUNTIFS('New Tooling Jobs'!A$13:A$62,"<>",'New Tooling Jobs'!E$13:E$62,"<>Completed"),INDEX('New Tooling Jobs'!I$13:I$62,MATCH(80,'New Tooling Jobs'!AG$13:AG$62,0)),INDEX(Reorders!I$13:I$62,MATCH(80-COUNTIFS('New Tooling Jobs'!A$13:A$62,"<>",'New Tooling Jobs'!E$13:E$62,"<>Completed"),Reorders!AC$13:AC$62,0))),"")
A90: =IFERROR(IF(81<=COUNTIFS('New Tooling Jobs'!A$13:A$62,"<>",'New Tooling Jobs'!E$13:E$62,"<>Completed"),INDEX('New Tooling Jobs'!A$13:A$62,MATCH(81,'New Tooling Jobs'!AG$13:AG$62,0)),INDEX(Reorders!A$13:A$62,MATCH(81-COUNTIFS('New Tooling Jobs'!A$13:A$62,"<>",'New Tooling Jobs'!E$13:E$62,"<>Completed"),Reorders!AC$13:AC$62,0))),"") | B90: =IFERROR(IF(81<=COUNTIFS('New Tooling Jobs'!A$13:A$62,"<>",'New Tooling Jobs'!E$13:E$62,"<>Completed"),IF(INDEX('New Tooling Jobs'!A$13:A$62,MATCH(81,'New Tooling Jobs'!AG$13:AG$62,0))<>"","New Tooling",""),IF(INDEX(Reorders!A$13:A$62,MATCH(81-COUNTIFS('New Tooling Jobs'!A$13:A$62,"<>",'New Tooling Jobs'!E$13:E$62,"<>Completed"),Reorders!AC$13:AC$62,0))<>"","Reorder","")),"") | C90: =IFERROR(IF(81<=COUNTIFS('New Tooling Jobs'!A$13:A$62,"<>",'New Tooling Jobs'!E$13:E$62,"<>Completed"),INDEX('New Tooling Jobs'!B$13:B$62,MATCH(81,'New Tooling Jobs'!AG$13:AG$62,0)),INDEX(Reorders!B$13:B$62,MATCH(81-COUNTIFS('New Tooling Jobs'!A$13:A$62,"<>",'New Tooling Jobs'!E$13:E$62,"<>Completed"),Reorders!AC$13:AC$62,0))),"") | D90: =IFERROR(IF(81<=COUNTIFS('New Tooling Jobs'!A$13:A$62,"<>",'New Tooling Jobs'!E$13:E$62,"<>Completed"),INDEX('New Tooling Jobs'!E$13:E$62,MATCH(81,'New Tooling Jobs'!AG$13:AG$62,0)),INDEX(Reorders!E$13:E$62,MATCH(81-COUNTIFS('New Tooling Jobs'!A$13:A$62,"<>",'New Tooling Jobs'!E$13:E$62,"<>Completed"),Reorders!AC$13:AC$62,0))),"") | E90: =IFERROR(IF(81<=COUNTIFS('New Tooling Jobs'!A$13:A$62,"<>",'New Tooling Jobs'!E$13:E$62,"<>Completed"),INDEX('New Tooling Jobs'!G$13:G$62,MATCH(81,'New Tooling Jobs'!AG$13:AG$62,0)),INDEX(Reorders!G$13:G$62,MATCH(81-COUNTIFS('New Tooling Jobs'!A$13:A$62,"<>",'New Tooling Jobs'!E$13:E$62,"<>Completed"),Reorders!AC$13:AC$62,0))),"") | F90: =IFERROR(IF(81<=COUNTIFS('New Tooling Jobs'!A$13:A$62,"<>",'New Tooling Jobs'!E$13:E$62,"<>Completed"),INDEX('New Tooling Jobs'!H$13:H$62,MATCH(81,'New Tooling Jobs'!AG$13:AG$62,0)),INDEX(Reorders!H$13:H$62,MATCH(81-COUNTIFS('New Tooling Jobs'!A$13:A$62,"<>",'New Tooling Jobs'!E$13:E$62,"<>Completed"),Reorders!AC$13:AC$62,0))),"") | G90: =IFERROR(IF(81<=COUNTIFS('New Tooling Jobs'!A$13:A$62,"<>",'New Tooling Jobs'!E$13:E$62,"<>Completed"),INDEX('New Tooling Jobs'!I$13:I$62,MATCH(81,'New Tooling Jobs'!AG$13:AG$62,0)),INDEX(Reorders!I$13:I$62,MATCH(81-COUNTIFS('New Tooling Jobs'!A$13:A$62,"<>",'New Tooling Jobs'!E$13:E$62,"<>Completed"),Reorders!AC$13:AC$62,0))),"")
A91: =IFERROR(IF(82<=COUNTIFS('New Tooling Jobs'!A$13:A$62,"<>",'New Tooling Jobs'!E$13:E$62,"<>Completed"),INDEX('New Tooling Jobs'!A$13:A$62,MATCH(82,'New Tooling Jobs'!AG$13:AG$62,0)),INDEX(Reorders!A$13:A$62,MATCH(82-COUNTIFS('New Tooling Jobs'!A$13:A$62,"<>",'New Tooling Jobs'!E$13:E$62,"<>Completed"),Reorders!AC$13:AC$62,0))),"") | B91: =IFERROR(IF(82<=COUNTIFS('New Tooling Jobs'!A$13:A$62,"<>",'New Tooling Jobs'!E$13:E$62,"<>Completed"),IF(INDEX('New Tooling Jobs'!A$13:A$62,MATCH(82,'New Tooling Jobs'!AG$13:AG$62,0))<>"","New Tooling",""),IF(INDEX(Reorders!A$13:A$62,MATCH(82-COUNTIFS('New Tooling Jobs'!A$13:A$62,"<>",'New Tooling Jobs'!E$13:E$62,"<>Completed"),Reorders!AC$13:AC$62,0))<>"","Reorder","")),"") | C91: =IFERROR(IF(82<=COUNTIFS('New Tooling Jobs'!A$13:A$62,"<>",'New Tooling Jobs'!E$13:E$62,"<>Completed"),INDEX('New Tooling Jobs'!B$13:B$62,MATCH(82,'New Tooling Jobs'!AG$13:AG$62,0)),INDEX(Reorders!B$13:B$62,MATCH(82-COUNTIFS('New Tooling Jobs'!A$13:A$62,"<>",'New Tooling Jobs'!E$13:E$62,"<>Completed"),Reorders!AC$13:AC$62,0))),"") | D91: =IFERROR(IF(82<=COUNTIFS('New Tooling Jobs'!A$13:A$62,"<>",'New Tooling Jobs'!E$13:E$62,"<>Completed"),INDEX('New Tooling Jobs'!E$13:E$62,MATCH(82,'New Tooling Jobs'!AG$13:AG$62,0)),INDEX(Reorders!E$13:E$62,MATCH(82-COUNTIFS('New Tooling Jobs'!A$13:A$62,"<>",'New Tooling Jobs'!E$13:E$62,"<>Completed"),Reorders!AC$13:AC$62,0))),"") | E91: =IFERROR(IF(82<=COUNTIFS('New Tooling Jobs'!A$13:A$62,"<>",'New Tooling Jobs'!E$13:E$62,"<>Completed"),INDEX('New Tooling Jobs'!G$13:G$62,MATCH(82,'New Tooling Jobs'!AG$13:AG$62,0)),INDEX(Reorders!G$13:G$62,MATCH(82-COUNTIFS('New Tooling Jobs'!A$13:A$62,"<>",'New Tooling Jobs'!E$13:E$62,"<>Completed"),Reorders!AC$13:AC$62,0))),"") | F91: =IFERROR(IF(82<=COUNTIFS('New Tooling Jobs'!A$13:A$62,"<>",'New Tooling Jobs'!E$13:E$62,"<>Completed"),INDEX('New Tooling Jobs'!H$13:H$62,MATCH(82,'New Tooling Jobs'!AG$13:AG$62,0)),INDEX(Reorders!H$13:H$62,MATCH(82-COUNTIFS('New Tooling Jobs'!A$13:A$62,"<>",'New Tooling Jobs'!E$13:E$62,"<>Completed"),Reorders!AC$13:AC$62,0))),"") | G91: =IFERROR(IF(82<=COUNTIFS('New Tooling Jobs'!A$13:A$62,"<>",'New Tooling Jobs'!E$13:E$62,"<>Completed"),INDEX('New Tooling Jobs'!I$13:I$62,MATCH(82,'New Tooling Jobs'!AG$13:AG$62,0)),INDEX(Reorders!I$13:I$62,MATCH(82-COUNTIFS('New Tooling Jobs'!A$13:A$62,"<>",'New Tooling Jobs'!E$13:E$62,"<>Completed"),Reorders!AC$13:AC$62,0))),"")
